Workbook
Name CAD_USD: captable!#REF!
Name infor_basic_shares: captable!$F$17
Name infor_cap_output_ccy: captable!$F$5
Name infor_cap_picture_range: captable!$B$15:$F$40
Name infor_cap_share_inputs: captable!$F$168:$F$185
Name infor_cap_ticker: captable!$F$3
Name infor_comps_group1_block: comps!$B$10:$AA$15
Name infor_comps_group1_label: comps!$D$9
Name infor_comps_group2_block: comps!$B$20:$AA$25
Name infor_comps_group2_label: comps!$D$19
Name infor_comps_group3_block: comps!$B$30:$AA$35
Name infor_comps_group3_label: comps!$D$29
Name infor_comps_output_ccy: comps!$F$3
Name infor_fx_rate: captable!$F$7
Name infor_ltm_ebitda_valuation: captable!$D$48
Name infor_ltm_revenue_valuation: captable!$D$47
Name infor_own_bbg_holder_block: 'Bloomberg Output'!$C$14:$AC$131
Name infor_own_bbg_link_block: Ownership!$H$68:$J$185
Name infor_own_insider_block: Ownership!$B$39:$J$65
Name infor_own_insiders_picture_range: Ownership!$B$4:$G$17
Name infor_own_institutions_picture_range: Ownership!$B$19:$G$35
Name infor_own_total_shares: Ownership!$F$35
Name infor_prec_group1_block: precedents!$B$8:$AI$13
Name infor_prec_group1_label: precedents!$E$7
Name infor_prec_group2_block: precedents!$B$17:$AI$22
Name infor_prec_group2_label: precedents!$E$16
Name infor_prec_output_ccy: precedents!$C$2
Name infor_share_price: captable!$F$16
Name IQ_CH: 110000
Name IQ_CQ: 5000
Name IQ_CY: 10000
Name IQ_DAILY: 500000
Name IQ_FH: 100000
Name IQ_FQ: 500
Name IQ_FY: 1000
Name IQ_LTM: 2000
Name IQ_MONTH: 15000
Name IQ_NTM: 6000
Name IQ_WEEK: 50000
Name IQ_YTD: 3000

Sheet captable
B2: Name: | F2: {=_xll.SNL.Clients.Office.Excel.Functions.SPG($F$3,"SP_COMPANY_NAME")} -> #NAME?
B3: Ticker:
B4: Input Currency: | F4: {=_xll.SNL.Clients.Office.Excel.Functions.SPG($F$3,"IQ_CURRENCY_FINANCIALS","FY0",$F$6,"Options: NA=NA")} -> #NAME?
B5: Output Currency: | F5: CAD
B6: Date: | F6: =TODAY()-1 -> 46230
B7: FX Rate:
B9: Toggles
B10: Dilutives Method: | F10: Treasury Stock
B11: Lease Toggle: | F11: ON
B13: =F2&" Cap Table" -> #NAME?
B15: Company Ticker: | F15: =F3 -> 0
B16: =CONCATENATE("Share Price (",TEXT(F6,"dd-mmm-yy"),")") -> Share Price (27-Jul-26)
B17: Basic Shares Outstanding | F17: =F186 -> 0
B18: Basic Market Cap | F18: =F16*F17 -> 0
B19: =IF(F10="Treasury Stock","Net","")&" ITM Dilutive Securities" -> Net ITM Dilutive Securities | F19: =IF(F10="Treasury Stock",F86,F84) -> #DIV/0!
B20: ITM Convertible Debentures | F20: =F104 -> 0
B21: Fully-Diluted Shares Outstanding | F21: =F17+F19+F20 -> #DIV/0!
B22: Fully-Diluted Market Cap | F22: =F16*F21 -> #DIV/0!
B24: Add: Debt | F24: =F122*F7 -> 0
B25: Add: Leases | F25: =IF($F$11="ON",$F$143,0)*F7 -> 0
B26: Less: Cash | F26: =-F164*F7 -> 0
B27: Less: Cash from ITM Proceeds | F27: =IF(F10="Treasury Stock",0,-F82)*F7 -> 0
B28: Net Debt | F28: =F24+F25+F26+F27 -> 0
B29: Preferred Shares | F29: =+$F$52*F7 -> 0
B30: Non-Controlling Interest | F30: =+$F$53*F7 -> 0
B31: Enterprise Value | F31: =F22+F28+F29+F30 -> #DIV/0!
B33: Financial Metrics | D33: LTM | E33: CY2026 | F33: CY2027
B34: Revenue | D34: =IFERROR(IF(D47="NULL","na ",D47),"n/a ") -> 0 | E34: =IFERROR(IF(E47="NULL","na ",E47),"n/a ") -> n/a | F34: =IFERROR(IF(F47="NULL","na ",F47),"n/a ") -> n/a
B35: Adj. EBITDA | D35: =IFERROR(IF(D48="NULL","na ",D48),"n/a ") -> 0 | E35: =IFERROR(IF(E48="NULL","na ",E48),"n/a ") -> n/a | F35: =IFERROR(IF(F48="NULL","na ",F48),"n/a ") -> n/a
B36: Adj. EBITDA Margin | D36: =IFERROR(IF(D35<0,"nmf ",D35/D34),"n/a ") -> n/a | E36: =IFERROR(IF(E35<0,"nmf ",E35/E34),"n/a ") -> n/a | F36: =IFERROR(IF(F35<0,"nmf ",F35/F34),"n/a ") -> n/a
B38: Valuation Metrics
B39: EV / Revenue | D39: =+$F$31/D$34 -> #DIV/0! | E39: =+$F$31/E$34 -> #DIV/0! | F39: =+$F$31/F$34 -> #DIV/0!
B40: EV / Adj. EBITDA | D40: =+$F$31/D$35 -> #DIV/0! | E40: =+$F$31/E$35 -> #DIV/0! | F40: =+$F$31/F$35 -> #DIV/0!
B42: Street Metrics
B43: Analyst Coverage (# of Analysts) | F43: {=_xll.SNL.Clients.Office.Excel.Functions.SPG($F$3,"SP_NUM_BROKER_REC",$F$6,"Options:NA=NA")} -> #NAME?
B44: Average Target Price | F44: {=_xll.SNL.Clients.Office.Excel.Functions.SPG($F$3,"SP_PRICE_TARGET",$F$6,"Options: NA=NA,Curr="&$F$4)} -> #NAME?
B45: % Upside vs. Current | F45: =IFERROR(F44/F16-1,"n/a ") -> n/a
B47: Revenue | E47: {=_xll.SNL.Clients.Office.Excel.Functions.SPG($F$3,"SP_REV_EST",E$33,$F$6,"Options:Mag=Millions,NA=NA,Curr="&$F$5)} -> #NAME? | F47: {=_xll.SNL.Clients.Office.Excel.Functions.SPG($F$3,"SP_REV_EST",F$33,$F$6,"Options:Mag=Millions,NA=NA,Curr="&$F$5)} -> #NAME?
B48: Adj. EBITDA | E48: {=_xll.SNL.Clients.Office.Excel.Functions.SPG($F$3,"SP_EBITDA_EST",E$33,$F$6,"Options:Mag=Millions,NA=NA,Curr="&$F$5)} -> #NAME? | F48: {=_xll.SNL.Clients.Office.Excel.Functions.SPG($F$3,"SP_EBITDA_EST",F$33,$F$6,"Options:Mag=Millions,NA=NA,Curr="&$F$5)} -> #NAME?
B50: I. Non-Controlling Interest & Preferred Shares
B51: Type | E51: Date | F51: Amount
B52: Preferred Shares
B53: Non-Controlling Interest
B55: II. ITM OPTIONS, WARRANTS, RSUs, DSUs
B56: Type | C56: Amount | D56: Strike | E56: ITM | F56: Proceeds
E57: =IF(D57<F$16,C57,0) -> 0 | F57: =E57*D57 -> 0
E58: =IF(D58<F$16,C58,0) -> 0 | F58: =E58*D58 -> 0
E59: =IF(D59<F$16,C59,0) -> 0 | F59: =E59*D59 -> 0
E60: =IF(D60<F$16,C60,0) -> 0 | F60: =E60*D60 -> 0
E61: =IF(D61<F$16,C61,0) -> 0 | F61: =E61*D61 -> 0
E62: =IF(D62<F$16,C62,0) -> 0 | F62: =E62*D62 -> 0
E63: =IF(D63<F$16,C63,0) -> 0 | F63: =E63*D63 -> 0
E64: =IF(D64<F$16,C64,0) -> 0 | F64: =E64*D64 -> 0
E65: =IF(D65<F$16,C65,0) -> 0 | F65: =E65*D65 -> 0
E66: =IF(D66<F$16,C66,0) -> 0 | F66: =E66*D66 -> 0
E67: =IF(D67<F$16,C67,0) -> 0 | F67: =E67*D67 -> 0
E68: =IF(D68<F$16,C68,0) -> 0 | F68: =E68*D68 -> 0
... E81: =IF(D81<F$16,C81,0) -> 0 | F81: =E81*D81 -> 0
B82: Total | E82: =SUM(E57:E81) -> 0 | F82: =SUM(F57:F81) -> 0
B84: Total ITM Options, Warrants, etc. | F84: =E82 -> 0
B85: Less: Total Repurchased and Cancelled | F85: =-F82/F16 -> #DIV/0!
B86: Net ITM Options, Warrants, etc. | F86: =SUM(F84:F85) -> #DIV/0!
B88: III. ITM CONVERTIBLE DEBENTURES OR CONVERTIBLE PREFERRED SHARES
B89: Type | C89: Amount | D89: Shares / $1,000 | E89: Strike | F89: ITM
F90: =IF(E90<F$16,(C90/1000)*D90,0) -> 0
F91: =IF(E91<F$16,(C91/1000)*D91,0) -> 0
F92: =IF(E92<F$16,(C92/1000)*D92,0) -> 0
F93: =IF(E93<F$16,(C93/1000)*D93,0) -> 0
F94: =IF(E94<F$16,(C94/1000)*D94,0) -> 0
F95: =IF(E95<F$16,(C95/1000)*D95,0) -> 0
F96: =IF(E96<F$16,(C96/1000)*D96,0) -> 0
F97: =IF(E97<F$16,(C97/1000)*D97,0) -> 0
F98: =IF(E98<F$16,(C98/1000)*D98,0) -> 0
F99: =IF(E99<F$16,(C99/1000)*D99,0) -> 0
F100: =IF(E100<F$16,(C100/1000)*D100,0) -> 0
F101: =IF(E101<F$16,(C101/1000)*D101,0) -> 0
... F103: =IF(E103<F$16,(C103/1000)*D103,0) -> 0
B104: Total ITM Convertible Debentures & Preferreds | F104: =SUM(F90:F103) -> 0
B106: IV. DEBT
B107: Type | E107: Date | F107: Amount
B122: Total Debt | F122: =SUM(F108:F121) -> 0
B124: V. LEASES
B125: Type | E125: Date | F125: Amount
B143: Total Debt | F143: =SUM(F126:F142) -> 0
B145: VI. CASH
B146: Type | E146: Date | F146: Amount
B164: Total Cash | F164: =SUM(F147:F163) -> 0
B166: VII. BASIC SHARES OUTSTANDING
B167: Description | E167: Date | F167: Amount
B186: Total Basic Shares Outstanding | F186: =SUM(F168:F185) -> 0

Sheet comps
E2: $F$2 | F2: =TODAY()-1 -> 46230 | L2: EV/Revenue | O2: EV/EBITDA
E3: Currency: | F3: CAD | K3: Min | L3: 0 | M3: 0 | N3: 0 | O3: 0 | P3: 0 | Q3: 0
E4: Period: | F4: 2026 | K4: Max | L4: 20 | M4: 20 | N4: 20 | O4: 50 | P4: 50 | Q4: 50
D6: ="(In "&IF(F3="USD","US","C")&"$MM, unless otherwise noted)" -> (In C$MM, unless otherwise noted) | G6: Price | H6: Price | I6: Native | J6: Market | K6: Enterprise | L6: EV / Revenue | O6: EV / EBITDA | R6: Rev. Growth | U6: P / E | X6: ROE | Y6: P / B | Z6: P / TBV | AC6: Revenue | AH6: EBITDA | AM6: EPS | AR6: ROE | AT6: BVPS | AV6: TBVPS | AX6: Div. | AY6: Book | BA6: Cash & ST | BE6: Gross Margin (%)
D7: Company | G7: =CONCATENATE("(",TEXT($F$2,"dd-mmm-yy"),")") -> (27-Jul-26) | H7: ="("&F3&")" -> (CAD) | I7: Currency | J7: Cap | K7: Value | L7: LTM | M7: ="CY"&$F$4&"E" -> CY2026E | N7: ="CY"&$F$4+1&"E" -> CY2027E | O7: LTM | P7: ="CY"&$F$4&"E" -> CY2026E | Q7: ="CY"&$F$4+1&"E" -> CY2027E | R7: =RIGHT(AD7,2)&"E-"&RIGHT(AE7,2)&"E" -> 25E-26E | S7: =RIGHT(AE7,2)&"E-"&RIGHT(AF7,2)&"E" -> 26E-27E | U7: LTM | V7: ="CY"&$F$4&"E" -> CY2026E | W7: ="CY"&$F$4+1&"E" -> CY2027E | X7: LTM | Y7: Current | Z7: Current | AA7: Description | AC7: LTM | AD7: ="CY"&$F$4-1 -> CY2025 | AE7: ="CY"&$F$4 -> CY2026 | AF7: ="CY"&$F$4+1 -> CY2027 | AH7: LTM | AI7: ="CY"&$F$4-1 -> CY2025 | AJ7: ="CY"&$F$4 -> CY2026 | AK7: ="CY"&$F$4+1 -> CY2027 | AM7: LTM | AN7: ="CY"&$F$4-1 -> CY2025 | AO7: ="CY"&$F$4 -> CY2026 | AP7: ="CY"&$F$4+1 -> CY2027 | AR7: LTM | AT7: LTM | AV7: LTM | AX7: Yield | AY7: Value | AZ7: Debt | BA7: Investments | BB7: Net Debt | BC7: Equity | BE7: LTM | BF7: ="CY"&$F$4-1 -> CY2025 | BG7: ="CY"&$F$4 -> CY2026 | BH7: ="CY"&$F$4+1 -> CY2027
BE8: \
D9: [Group #1]
D10: {=IF($B10="","",_xll.SNL.Clients.Office.Excel.Functions.SPG($B10, "SP_COMPANY_NAME"))} | G10: {=IF($B10="","",_xll.SNL.Clients.Office.Excel.Functions.SPG($B10,"SP_LASTSALEPRICE",WORKDAY($F$2+1,-1),"Options:Curr="&I10&",NA=--"))} | H10: {=IF($B10="","",_xll.SNL.Clients.Office.Excel.Functions.SPG($B10,"SP_PRICE_CLOSE",WORKDAY($F$2+1,-1),"Options:Curr="&$F$3&", NA=--"))} | I10: {=IF($B10="","",_xll.SNL.Clients.Office.Excel.Functions.SPG($B10,"SP_TRADING_CURRENCY","Options: NA=--"))} | J10: {=IF($B10="","n/a ",_xll.SNL.Clients.Office.Excel.Functions.SPG($B10,"SP_MARKETCAP",WORKDAY($F$2+1,-1),"Options:Curr="&$F$3&", Mag=Millions, NA=--"))} -> n/a | K10: {=IF($B10="","n/a ",_xll.SNL.Clients.Office.Excel.Functions.SPG($B10,"IQ_TEV",WORKDAY($F$2+1,-1),"Options:Curr="&$F$3&", Mag=Millions, NA=--"))} -> n/a | L10: =IFERROR(IF(OR($K10/AC10>L$4,$K10/AC10<L$3),"nmf ",$K10/AC10),"n/a ") -> n/a | M10: =IFERROR(IF(OR($K10/AE10>M$4,$K10/AE10<M$3),"nmf ",$K10/AE10),"n/a ") -> n/a | N10: =IFERROR(IF(OR($K10/AF10>N$4,$K10/AF10<N$3),"nmf ",$K10/AF10),"n/a ") -> n/a | O10: =IFERROR(IF(OR($K10/AH10>O$4,$K10/AH10<O$3),"nmf ",$K10/AH10),"n/a ") -> n/a | P10: =IFERROR(IF(OR($K10/AJ10>P$4,$K10/AJ10<P$3),"nmf ",$K10/AJ10),"n/a ") -> n/a | Q10: =IFERROR(IF(OR($K10/AK10>Q$4,$K10/AK10<Q$3),"nmf ",$K10/AK10),"n/a ") -> n/a | R10: =IFERROR((AE10/AD10)-1,"n/a ") -> n/a | S10: =IFERROR((AF10/AE10)-1,"n/a ") -> n/a | U10: =IFERROR($H10/AM10,"n/a ") -> n/a | V10: =IFERROR($H10/AO10,"n/a ") -> n/a | W10: =IFERROR($H10/AP10,"n/a ") -> n/a | X10: =IFERROR(AR10/100,"n/a ") -> n/a | Y10: =IFERROR(H10/AT10,"n/a ") -> n/a | Z10: =IFERROR(H10/AV10,"n/a ") -> n/a | AC10: {=IF($B10="","",_xll.SNL.Clients.Office.Excel.Functions.SPG($B10,"IQ_REV",AC$7,$F$2,"Options:Curr="&$F$3&", Mag=Millions, NA=--"))} | AD10: {=IF($B10="","",_xll.SNL.Clients.Office.Excel.Functions.SPG($B10,"SP_REV_EST",AD$7,$F$2,"Options:Curr="&$F$3&", Mag=Millions, NA=--"))} | AE10: {=IF($B10="","",_xll.SNL.Clients.Office.Excel.Functions.SPG($B10,"SP_REV_EST",AE$7,$F$2,"Options:Curr="&$F$3&", Mag=Millions, NA=--"))} | AF10: {=IF($B10="","",_xll.SNL.Clients.Office.Excel.Functions.SPG($B10,"SP_REV_EST",AF$7,$F$2,"Options:Curr="&$F$3&", Mag=Millions, NA=--"))} | AH10: {=IF($B10="","",_xll.SNL.Clients.Office.Excel.Functions.SPG($B10,"SP_EBITDA",AH$7,$F$2,"Options:Curr="&$F$3&", Mag=Millions, NA=--"))} | AI10: {=IF($B10="","",_xll.SNL.Clients.Office.Excel.Functions.SPG($B10,"SP_EBITDA_EST",AI$7,$F$2,"Options:Curr="&$F$3&", Mag=Millions, NA=--"))} | AJ10: {=IF($B10="","",_xll.SNL.Clients.Office.Excel.Functions.SPG($B10,"SP_EBITDA_EST",AJ$7,$F$2,"Options:Curr="&$F$3&", Mag=Millions, NA=--"))} | AK10: {=IF($B10="","",_xll.SNL.Clients.Office.Excel.Functions.SPG($B10,"SP_EBITDA_EST",AK$7,$F$2,"Options:Curr="&$F$3&", Mag=Millions, NA=--"))} | AM10: {=IF($B10="","",_xll.SNL.Clients.Office.Excel.Functions.SPG($B10,"IQ_BASIC_EPS_BEFORE_EXTRA",AM$7,$F$2,"Options:Curr="&$F$3&", NA=--"))} | AN10: {=IF($B10="","",_xll.SNL.Clients.Office.Excel.Functions.SPG($B10,"SP_EPS_EST",AN$7,$F$2,"Options:Curr="&$F$3&", NA=--"))} | AO10: {=IF($B10="","",_xll.SNL.Clients.Office.Excel.Functions.SPG($B10,"SP_EPS_EST",AO$7,$F$2,"Options:Curr="&$F$3&", NA=--"))} | AP10: {=IF($B10="","",_xll.SNL.Clients.Office.Excel.Functions.SPG($B10,"SP_EPS_EST",AP$7,$F$2,"Options:Curr="&$F$3&", NA=--"))} | AR10: {=IF($B10="","",_xll.SNL.Clients.Office.Excel.Functions.SPG($B10,"IQ_ROE",AR$7,$F$2,"Options:Curr="&$F$3&", NA=--"))} | AT10: {=IF($B10="","",_xll.SNL.Clients.Office.Excel.Functions.SPG($B10,"IQ_BVPS",AT$7,$F$2,"Options:Curr="&$F$3&", NA=--"))} | AV10: {=IF($B10="","",_xll.SNL.Clients.Office.Excel.Functions.SPG($B10,"IQ_TBVPS",AV$7,$F$2,"Options:Curr="&$F$3&", NA=--"))} | AX10: {=IF($B10="","",_xll.SNL.Clients.Office.Excel.Functions.SPG($B10,"SP_DIV_YIELD",WORKDAY($F$2+1,-1),"Options: NA=--"))} | AY10: {=IF($B10="","",_xll.SNL.Clients.Office.Excel.Functions.SPG($B10,"IQ_TOTAL_EQUITY","FQ0",$F$2,"Options:Curr="&$F$3&", Mag=Millions, NA=--"))} | AZ10: {=IF($B10="","",_xll.SNL.Clients.Office.Excel.Functions.SPG($B10,"IQ_TOTAL_DEBT","FQ0",$F$2,"Options:Curr="&$F$3&", Mag=Millions, NA=--"))} | BA10: {=IF($B10="","",_xll.SNL.Clients.Office.Excel.Functions.SPG($B10,"IQ_CASH_ST_INVEST","FQ0",$F$2,"Options:Curr="&$F$3&", Mag=Millions, NA=--"))} | BB10: =+AZ10-BA10 -> #VALUE! | BC10: {=IF($B10="","",_xll.SNL.Clients.Office.Excel.Functions.SPG($B10,"IQ_TOTAL_EQUITY","FQ0",$F$2,"Options:Curr="&$F$3&", Mag=Millions, NA=--"))} | BE10: =IF($B10="","",IFERROR(_xll.SNL.Clients.Office.Excel.Functions.SPG($B10,"SP_GROSS_MARGIN",BE$7,$F$2,"Options: NA=--")/100,"--")) | BF10: =IF($B10="","",IFERROR(_xll.SNL.Clients.Office.Excel.Functions.SPG($B10,"SP_GROSS_MARGIN_EST",BF$7,$F$2,"Options: NA=--")/100,"--")) | BG10: =IF($B10="","",IFERROR(_xll.SNL.Clients.Office.Excel.Functions.SPG($B10,"SP_GROSS_MARGIN_EST",BG$7,$F$2,"Options: NA=--")/100,"--")) | BH10: =IF($B10="","",IFERROR(_xll.SNL.Clients.Office.Excel.Functions.SPG($B10,"SP_GROSS_MARGIN_EST",BH$7,$F$2,"Options: NA=--")/100,"--"))
D11: {=IF($B11="","",_xll.SNL.Clients.Office.Excel.Functions.SPG($B11, "SP_COMPANY_NAME"))} | G11: {=IF($B11="","",_xll.SNL.Clients.Office.Excel.Functions.SPG($B11,"SP_LASTSALEPRICE",WORKDAY($F$2+1,-1),"Options:Curr="&I11&",NA=--"))} | H11: {=IF($B11="","",_xll.SNL.Clients.Office.Excel.Functions.SPG($B11,"SP_PRICE_CLOSE",WORKDAY($F$2+1,-1),"Options:Curr="&$F$3&", NA=--"))} | I11: {=IF($B11="","",_xll.SNL.Clients.Office.Excel.Functions.SPG($B11,"SP_TRADING_CURRENCY","Options: NA=--"))} | J11: {=IF($B11="","n/a ",_xll.SNL.Clients.Office.Excel.Functions.SPG($B11,"SP_MARKETCAP",WORKDAY($F$2+1,-1),"Options:Curr="&$F$3&", Mag=Millions, NA=--"))} -> n/a | K11: {=IF($B11="","n/a ",_xll.SNL.Clients.Office.Excel.Functions.SPG($B11,"IQ_TEV",WORKDAY($F$2+1,-1),"Options:Curr="&$F$3&", Mag=Millions, NA=--"))} -> n/a | L11: =IFERROR(IF(OR($K11/AC11>L$4,$K11/AC11<L$3),"nmf ",$K11/AC11),"n/a ") -> n/a | M11: =IFERROR(IF(OR($K11/AE11>M$4,$K11/AE11<M$3),"nmf ",$K11/AE11),"n/a ") -> n/a | N11: =IFERROR(IF(OR($K11/AF11>N$4,$K11/AF11<N$3),"nmf ",$K11/AF11),"n/a ") -> n/a | O11: =IFERROR(IF(OR($K11/AH11>O$4,$K11/AH11<O$3),"nmf ",$K11/AH11),"n/a ") -> n/a | P11: =IFERROR(IF(OR($K11/AJ11>P$4,$K11/AJ11<P$3),"nmf ",$K11/AJ11),"n/a ") -> n/a | Q11: =IFERROR(IF(OR($K11/AK11>Q$4,$K11/AK11<Q$3),"nmf ",$K11/AK11),"n/a ") -> n/a | R11: =IFERROR((AE11/AD11)-1,"n/a ") -> n/a | S11: =IFERROR((AF11/AE11)-1,"n/a ") -> n/a | U11: =IFERROR($H11/AM11,"n/a ") -> n/a | V11: =IFERROR($H11/AO11,"n/a ") -> n/a | W11: =IFERROR($H11/AP11,"n/a ") -> n/a | X11: =IFERROR(AR11/100,"n/a ") -> n/a | Y11: =IFERROR(H11/AT11,"n/a ") -> n/a | Z11: =IFERROR(H11/AV11,"n/a ") -> n/a | AC11: {=IF($B11="","",_xll.SNL.Clients.Office.Excel.Functions.SPG($B11,"IQ_REV",AC$7,$F$2,"Options:Curr="&$F$3&", Mag=Millions, NA=--"))} | AD11: {=IF($B11="","",_xll.SNL.Clients.Office.Excel.Functions.SPG($B11,"SP_REV_EST",AD$7,$F$2,"Options:Curr="&$F$3&", Mag=Millions, NA=--"))} | AE11: {=IF($B11="","",_xll.SNL.Clients.Office.Excel.Functions.SPG($B11,"SP_REV_EST",AE$7,$F$2,"Options:Curr="&$F$3&", Mag=Millions, NA=--"))} | AF11: {=IF($B11="","",_xll.SNL.Clients.Office.Excel.Functions.SPG($B11,"SP_REV_EST",AF$7,$F$2,"Options:Curr="&$F$3&", Mag=Millions, NA=--"))} | AH11: {=IF($B11="","",_xll.SNL.Clients.Office.Excel.Functions.SPG($B11,"SP_EBITDA",AH$7,$F$2,"Options:Curr="&$F$3&", Mag=Millions, NA=--"))} | AI11: {=IF($B11="","",_xll.SNL.Clients.Office.Excel.Functions.SPG($B11,"SP_EBITDA_EST",AI$7,$F$2,"Options:Curr="&$F$3&", Mag=Millions, NA=--"))} | AJ11: {=IF($B11="","",_xll.SNL.Clients.Office.Excel.Functions.SPG($B11,"SP_EBITDA_EST",AJ$7,$F$2,"Options:Curr="&$F$3&", Mag=Millions, NA=--"))} | AK11: {=IF($B11="","",_xll.SNL.Clients.Office.Excel.Functions.SPG($B11,"SP_EBITDA_EST",AK$7,$F$2,"Options:Curr="&$F$3&", Mag=Millions, NA=--"))} | AM11: {=IF($B11="","",_xll.SNL.Clients.Office.Excel.Functions.SPG($B11,"IQ_BASIC_EPS_BEFORE_EXTRA",AM$7,$F$2,"Options:Curr="&$F$3&", NA=--"))} | AN11: {=IF($B11="","",_xll.SNL.Clients.Office.Excel.Functions.SPG($B11,"SP_EPS_EST",AN$7,$F$2,"Options:Curr="&$F$3&", NA=--"))} | AO11: {=IF($B11="","",_xll.SNL.Clients.Office.Excel.Functions.SPG($B11,"SP_EPS_EST",AO$7,$F$2,"Options:Curr="&$F$3&", NA=--"))} | AP11: {=IF($B11="","",_xll.SNL.Clients.Office.Excel.Functions.SPG($B11,"SP_EPS_EST",AP$7,$F$2,"Options:Curr="&$F$3&", NA=--"))} | AR11: {=IF($B11="","",_xll.SNL.Clients.Office.Excel.Functions.SPG($B11,"IQ_ROE",AR$7,$F$2,"Options:Curr="&$F$3&", NA=--"))} | AT11: {=IF($B11="","",_xll.SNL.Clients.Office.Excel.Functions.SPG($B11,"IQ_BVPS",AT$7,$F$2,"Options:Curr="&$F$3&", NA=--"))} | AV11: {=IF($B11="","",_xll.SNL.Clients.Office.Excel.Functions.SPG($B11,"IQ_TBVPS",AV$7,$F$2,"Options:Curr="&$F$3&", NA=--"))} | AX11: {=IF($B11="","",_xll.SNL.Clients.Office.Excel.Functions.SPG($B11,"SP_DIV_YIELD",WORKDAY($F$2+1,-1),"Options: NA=--"))} | AY11: {=IF($B11="","",_xll.SNL.Clients.Office.Excel.Functions.SPG($B11,"IQ_TOTAL_EQUITY","FQ0",$F$2,"Options:Curr="&$F$3&", Mag=Millions, NA=--"))} | AZ11: {=IF($B11="","",_xll.SNL.Clients.Office.Excel.Functions.SPG($B11,"IQ_TOTAL_DEBT","FQ0",$F$2,"Options:Curr="&$F$3&", Mag=Millions, NA=--"))} | BA11: {=IF($B11="","",_xll.SNL.Clients.Office.Excel.Functions.SPG($B11,"IQ_CASH_ST_INVEST","FQ0",$F$2,"Options:Curr="&$F$3&", Mag=Millions, NA=--"))} | BB11: =+AZ11-BA11 -> #VALUE! | BC11: {=IF($B11="","",_xll.SNL.Clients.Office.Excel.Functions.SPG($B11,"IQ_TOTAL_EQUITY","FQ0",$F$2,"Options:Curr="&$F$3&", Mag=Millions, NA=--"))} | BE11: =IF($B11="","",IFERROR(_xll.SNL.Clients.Office.Excel.Functions.SPG($B11,"SP_GROSS_MARGIN",BE$7,$F$2,"Options: NA=--")/100,"--")) | BF11: =IF($B11="","",IFERROR(_xll.SNL.Clients.Office.Excel.Functions.SPG($B11,"SP_GROSS_MARGIN_EST",BF$7,$F$2,"Options: NA=--")/100,"--")) | BG11: =IF($B11="","",IFERROR(_xll.SNL.Clients.Office.Excel.Functions.SPG($B11,"SP_GROSS_MARGIN_EST",BG$7,$F$2,"Options: NA=--")/100,"--")) | BH11: =IF($B11="","",IFERROR(_xll.SNL.Clients.Office.Excel.Functions.SPG($B11,"SP_GROSS_MARGIN_EST",BH$7,$F$2,"Options: NA=--")/100,"--"))
D12: {=IF($B12="","",_xll.SNL.Clients.Office.Excel.Functions.SPG($B12, "SP_COMPANY_NAME"))} | G12: {=IF($B12="","",_xll.SNL.Clients.Office.Excel.Functions.SPG($B12,"SP_LASTSALEPRICE",WORKDAY($F$2+1,-1),"Options:Curr="&I12&",NA=--"))} | H12: {=IF($B12="","",_xll.SNL.Clients.Office.Excel.Functions.SPG($B12,"SP_PRICE_CLOSE",WORKDAY($F$2+1,-1),"Options:Curr="&$F$3&", NA=--"))} | I12: {=IF($B12="","",_xll.SNL.Clients.Office.Excel.Functions.SPG($B12,"SP_TRADING_CURRENCY","Options: NA=--"))} | J12: {=IF($B12="","n/a ",_xll.SNL.Clients.Office.Excel.Functions.SPG($B12,"SP_MARKETCAP",WORKDAY($F$2+1,-1),"Options:Curr="&$F$3&", Mag=Millions, NA=--"))} -> n/a | K12: {=IF($B12="","n/a ",_xll.SNL.Clients.Office.Excel.Functions.SPG($B12,"IQ_TEV",WORKDAY($F$2+1,-1),"Options:Curr="&$F$3&", Mag=Millions, NA=--"))} -> n/a | L12: =IFERROR(IF(OR($K12/AC12>L$4,$K12/AC12<L$3),"nmf ",$K12/AC12),"n/a ") -> n/a | M12: =IFERROR(IF(OR($K12/AE12>M$4,$K12/AE12<M$3),"nmf ",$K12/AE12),"n/a ") -> n/a | N12: =IFERROR(IF(OR($K12/AF12>N$4,$K12/AF12<N$3),"nmf ",$K12/AF12),"n/a ") -> n/a | O12: =IFERROR(IF(OR($K12/AH12>O$4,$K12/AH12<O$3),"nmf ",$K12/AH12),"n/a ") -> n/a | P12: =IFERROR(IF(OR($K12/AJ12>P$4,$K12/AJ12<P$3),"nmf ",$K12/AJ12),"n/a ") -> n/a | Q12: =IFERROR(IF(OR($K12/AK12>Q$4,$K12/AK12<Q$3),"nmf ",$K12/AK12),"n/a ") -> n/a | R12: =IFERROR((AE12/AD12)-1,"n/a ") -> n/a | S12: =IFERROR((AF12/AE12)-1,"n/a ") -> n/a | U12: =IFERROR($H12/AM12,"n/a ") -> n/a | V12: =IFERROR($H12/AO12,"n/a ") -> n/a | W12: =IFERROR($H12/AP12,"n/a ") -> n/a | X12: =IFERROR(AR12/100,"n/a ") -> n/a | Y12: =IFERROR(H12/AT12,"n/a ") -> n/a | Z12: =IFERROR(H12/AV12,"n/a ") -> n/a | AC12: {=IF($B12="","",_xll.SNL.Clients.Office.Excel.Functions.SPG($B12,"IQ_REV",AC$7,$F$2,"Options:Curr="&$F$3&", Mag=Millions, NA=--"))} | AD12: {=IF($B12="","",_xll.SNL.Clients.Office.Excel.Functions.SPG($B12,"SP_REV_EST",AD$7,$F$2,"Options:Curr="&$F$3&", Mag=Millions, NA=--"))} | AE12: {=IF($B12="","",_xll.SNL.Clients.Office.Excel.Functions.SPG($B12,"SP_REV_EST",AE$7,$F$2,"Options:Curr="&$F$3&", Mag=Millions, NA=--"))} | AF12: {=IF($B12="","",_xll.SNL.Clients.Office.Excel.Functions.SPG($B12,"SP_REV_EST",AF$7,$F$2,"Options:Curr="&$F$3&", Mag=Millions, NA=--"))} | AH12: {=IF($B12="","",_xll.SNL.Clients.Office.Excel.Functions.SPG($B12,"SP_EBITDA",AH$7,$F$2,"Options:Curr="&$F$3&", Mag=Millions, NA=--"))} | AI12: {=IF($B12="","",_xll.SNL.Clients.Office.Excel.Functions.SPG($B12,"SP_EBITDA_EST",AI$7,$F$2,"Options:Curr="&$F$3&", Mag=Millions, NA=--"))} | AJ12: {=IF($B12="","",_xll.SNL.Clients.Office.Excel.Functions.SPG($B12,"SP_EBITDA_EST",AJ$7,$F$2,"Options:Curr="&$F$3&", Mag=Millions, NA=--"))} | AK12: {=IF($B12="","",_xll.SNL.Clients.Office.Excel.Functions.SPG($B12,"SP_EBITDA_EST",AK$7,$F$2,"Options:Curr="&$F$3&", Mag=Millions, NA=--"))} | AM12: {=IF($B12="","",_xll.SNL.Clients.Office.Excel.Functions.SPG($B12,"IQ_BASIC_EPS_BEFORE_EXTRA",AM$7,$F$2,"Options:Curr="&$F$3&", NA=--"))} | AN12: {=IF($B12="","",_xll.SNL.Clients.Office.Excel.Functions.SPG($B12,"SP_EPS_EST",AN$7,$F$2,"Options:Curr="&$F$3&", NA=--"))} | AO12: {=IF($B12="","",_xll.SNL.Clients.Office.Excel.Functions.SPG($B12,"SP_EPS_EST",AO$7,$F$2,"Options:Curr="&$F$3&", NA=--"))} | AP12: {=IF($B12="","",_xll.SNL.Clients.Office.Excel.Functions.SPG($B12,"SP_EPS_EST",AP$7,$F$2,"Options:Curr="&$F$3&", NA=--"))} | AR12: {=IF($B12="","",_xll.SNL.Clients.Office.Excel.Functions.SPG($B12,"IQ_ROE",AR$7,$F$2,"Options:Curr="&$F$3&", NA=--"))} | AT12: {=IF($B12="","",_xll.SNL.Clients.Office.Excel.Functions.SPG($B12,"IQ_BVPS",AT$7,$F$2,"Options:Curr="&$F$3&", NA=--"))} | AV12: {=IF($B12="","",_xll.SNL.Clients.Office.Excel.Functions.SPG($B12,"IQ_TBVPS",AV$7,$F$2,"Options:Curr="&$F$3&", NA=--"))} | AX12: {=IF($B12="","",_xll.SNL.Clients.Office.Excel.Functions.SPG($B12,"SP_DIV_YIELD",WORKDAY($F$2+1,-1),"Options: NA=--"))} | AY12: {=IF($B12="","",_xll.SNL.Clients.Office.Excel.Functions.SPG($B12,"IQ_TOTAL_EQUITY","FQ0",$F$2,"Options:Curr="&$F$3&", Mag=Millions, NA=--"))} | AZ12: {=IF($B12="","",_xll.SNL.Clients.Office.Excel.Functions.SPG($B12,"IQ_TOTAL_DEBT","FQ0",$F$2,"Options:Curr="&$F$3&", Mag=Millions, NA=--"))} | BA12: {=IF($B12="","",_xll.SNL.Clients.Office.Excel.Functions.SPG($B12,"IQ_CASH_ST_INVEST","FQ0",$F$2,"Options:Curr="&$F$3&", Mag=Millions, NA=--"))} | BB12: =+AZ12-BA12 -> #VALUE! | BC12: {=IF($B12="","",_xll.SNL.Clients.Office.Excel.Functions.SPG($B12,"IQ_TOTAL_EQUITY","FQ0",$F$2,"Options:Curr="&$F$3&", Mag=Millions, NA=--"))} | BE12: =IF($B12="","",IFERROR(_xll.SNL.Clients.Office.Excel.Functions.SPG($B12,"SP_GROSS_MARGIN",BE$7,$F$2,"Options: NA=--")/100,"--")) | BF12: =IF($B12="","",IFERROR(_xll.SNL.Clients.Office.Excel.Functions.SPG($B12,"SP_GROSS_MARGIN_EST",BF$7,$F$2,"Options: NA=--")/100,"--")) | BG12: =IF($B12="","",IFERROR(_xll.SNL.Clients.Office.Excel.Functions.SPG($B12,"SP_GROSS_MARGIN_EST",BG$7,$F$2,"Options: NA=--")/100,"--")) | BH12: =IF($B12="","",IFERROR(_xll.SNL.Clients.Office.Excel.Functions.SPG($B12,"SP_GROSS_MARGIN_EST",BH$7,$F$2,"Options: NA=--")/100,"--"))
D13: {=IF($B13="","",_xll.SNL.Clients.Office.Excel.Functions.SPG($B13, "SP_COMPANY_NAME"))} | G13: {=IF($B13="","",_xll.SNL.Clients.Office.Excel.Functions.SPG($B13,"SP_LASTSALEPRICE",WORKDAY($F$2+1,-1),"Options:Curr="&I13&",NA=--"))} | H13: {=IF($B13="","",_xll.SNL.Clients.Office.Excel.Functions.SPG($B13,"SP_PRICE_CLOSE",WORKDAY($F$2+1,-1),"Options:Curr="&$F$3&", NA=--"))} | I13: {=IF($B13="","",_xll.SNL.Clients.Office.Excel.Functions.SPG($B13,"SP_TRADING_CURRENCY","Options: NA=--"))} | J13: {=IF($B13="","n/a ",_xll.SNL.Clients.Office.Excel.Functions.SPG($B13,"SP_MARKETCAP",WORKDAY($F$2+1,-1),"Options:Curr="&$F$3&", Mag=Millions, NA=--"))} -> n/a | K13: {=IF($B13="","n/a ",_xll.SNL.Clients.Office.Excel.Functions.SPG($B13,"IQ_TEV",WORKDAY($F$2+1,-1),"Options:Curr="&$F$3&", Mag=Millions, NA=--"))} -> n/a | L13: =IFERROR(IF(OR($K13/AC13>L$4,$K13/AC13<L$3),"nmf ",$K13/AC13),"n/a ") -> n/a | M13: =IFERROR(IF(OR($K13/AE13>M$4,$K13/AE13<M$3),"nmf ",$K13/AE13),"n/a ") -> n/a | N13: =IFERROR(IF(OR($K13/AF13>N$4,$K13/AF13<N$3),"nmf ",$K13/AF13),"n/a ") -> n/a | O13: =IFERROR(IF(OR($K13/AH13>O$4,$K13/AH13<O$3),"nmf ",$K13/AH13),"n/a ") -> n/a | P13: =IFERROR(IF(OR($K13/AJ13>P$4,$K13/AJ13<P$3),"nmf ",$K13/AJ13),"n/a ") -> n/a | Q13: =IFERROR(IF(OR($K13/AK13>Q$4,$K13/AK13<Q$3),"nmf ",$K13/AK13),"n/a ") -> n/a | R13: =IFERROR((AE13/AD13)-1,"n/a ") -> n/a | S13: =IFERROR((AF13/AE13)-1,"n/a ") -> n/a | U13: =IFERROR($H13/AM13,"n/a ") -> n/a | V13: =IFERROR($H13/AO13,"n/a ") -> n/a | W13: =IFERROR($H13/AP13,"n/a ") -> n/a | X13: =IFERROR(AR13/100,"n/a ") -> n/a | Y13: =IFERROR(H13/AT13,"n/a ") -> n/a | Z13: =IFERROR(H13/AV13,"n/a ") -> n/a | AC13: {=IF($B13="","",_xll.SNL.Clients.Office.Excel.Functions.SPG($B13,"IQ_REV",AC$7,$F$2,"Options:Curr="&$F$3&", Mag=Millions, NA=--"))} | AD13: {=IF($B13="","",_xll.SNL.Clients.Office.Excel.Functions.SPG($B13,"SP_REV_EST",AD$7,$F$2,"Options:Curr="&$F$3&", Mag=Millions, NA=--"))} | AE13: {=IF($B13="","",_xll.SNL.Clients.Office.Excel.Functions.SPG($B13,"SP_REV_EST",AE$7,$F$2,"Options:Curr="&$F$3&", Mag=Millions, NA=--"))} | AF13: {=IF($B13="","",_xll.SNL.Clients.Office.Excel.Functions.SPG($B13,"SP_REV_EST",AF$7,$F$2,"Options:Curr="&$F$3&", Mag=Millions, NA=--"))} | AH13: {=IF($B13="","",_xll.SNL.Clients.Office.Excel.Functions.SPG($B13,"SP_EBITDA",AH$7,$F$2,"Options:Curr="&$F$3&", Mag=Millions, NA=--"))} | AI13: {=IF($B13="","",_xll.SNL.Clients.Office.Excel.Functions.SPG($B13,"SP_EBITDA_EST",AI$7,$F$2,"Options:Curr="&$F$3&", Mag=Millions, NA=--"))} | AJ13: {=IF($B13="","",_xll.SNL.Clients.Office.Excel.Functions.SPG($B13,"SP_EBITDA_EST",AJ$7,$F$2,"Options:Curr="&$F$3&", Mag=Millions, NA=--"))} | AK13: {=IF($B13="","",_xll.SNL.Clients.Office.Excel.Functions.SPG($B13,"SP_EBITDA_EST",AK$7,$F$2,"Options:Curr="&$F$3&", Mag=Millions, NA=--"))} | AM13: {=IF($B13="","",_xll.SNL.Clients.Office.Excel.Functions.SPG($B13,"IQ_BASIC_EPS_BEFORE_EXTRA",AM$7,$F$2,"Options:Curr="&$F$3&", NA=--"))} | AN13: {=IF($B13="","",_xll.SNL.Clients.Office.Excel.Functions.SPG($B13,"SP_EPS_EST",AN$7,$F$2,"Options:Curr="&$F$3&", NA=--"))} | AO13: {=IF($B13="","",_xll.SNL.Clients.Office.Excel.Functions.SPG($B13,"SP_EPS_EST",AO$7,$F$2,"Options:Curr="&$F$3&", NA=--"))} | AP13: {=IF($B13="","",_xll.SNL.Clients.Office.Excel.Functions.SPG($B13,"SP_EPS_EST",AP$7,$F$2,"Options:Curr="&$F$3&", NA=--"))} | AR13: {=IF($B13="","",_xll.SNL.Clients.Office.Excel.Functions.SPG($B13,"IQ_ROE",AR$7,$F$2,"Options:Curr="&$F$3&", NA=--"))} | AT13: {=IF($B13="","",_xll.SNL.Clients.Office.Excel.Functions.SPG($B13,"IQ_BVPS",AT$7,$F$2,"Options:Curr="&$F$3&", NA=--"))} | AV13: {=IF($B13="","",_xll.SNL.Clients.Office.Excel.Functions.SPG($B13,"IQ_TBVPS",AV$7,$F$2,"Options:Curr="&$F$3&", NA=--"))} | AX13: {=IF($B13="","",_xll.SNL.Clients.Office.Excel.Functions.SPG($B13,"SP_DIV_YIELD",WORKDAY($F$2+1,-1),"Options: NA=--"))} | AY13: {=IF($B13="","",_xll.SNL.Clients.Office.Excel.Functions.SPG($B13,"IQ_TOTAL_EQUITY","FQ0",$F$2,"Options:Curr="&$F$3&", Mag=Millions, NA=--"))} | AZ13: {=IF($B13="","",_xll.SNL.Clients.Office.Excel.Functions.SPG($B13,"IQ_TOTAL_DEBT","FQ0",$F$2,"Options:Curr="&$F$3&", Mag=Millions, NA=--"))} | BA13: {=IF($B13="","",_xll.SNL.Clients.Office.Excel.Functions.SPG($B13,"IQ_CASH_ST_INVEST","FQ0",$F$2,"Options:Curr="&$F$3&", Mag=Millions, NA=--"))} | BB13: =+AZ13-BA13 -> #VALUE! | BC13: {=IF($B13="","",_xll.SNL.Clients.Office.Excel.Functions.SPG($B13,"IQ_TOTAL_EQUITY","FQ0",$F$2,"Options:Curr="&$F$3&", Mag=Millions, NA=--"))} | BE13: =IF($B13="","",IFERROR(_xll.SNL.Clients.Office.Excel.Functions.SPG($B13,"SP_GROSS_MARGIN",BE$7,$F$2,"Options: NA=--")/100,"--")) | BF13: =IF($B13="","",IFERROR(_xll.SNL.Clients.Office.Excel.Functions.SPG($B13,"SP_GROSS_MARGIN_EST",BF$7,$F$2,"Options: NA=--")/100,"--")) | BG13: =IF($B13="","",IFERROR(_xll.SNL.Clients.Office.Excel.Functions.SPG($B13,"SP_GROSS_MARGIN_EST",BG$7,$F$2,"Options: NA=--")/100,"--")) | BH13: =IF($B13="","",IFERROR(_xll.SNL.Clients.Office.Excel.Functions.SPG($B13,"SP_GROSS_MARGIN_EST",BH$7,$F$2,"Options: NA=--")/100,"--"))
D14: {=IF($B14="","",_xll.SNL.Clients.Office.Excel.Functions.SPG($B14, "SP_COMPANY_NAME"))} | G14: {=IF($B14="","",_xll.SNL.Clients.Office.Excel.Functions.SPG($B14,"SP_LASTSALEPRICE",WORKDAY($F$2+1,-1),"Options:Curr="&I14&",NA=--"))} | H14: {=IF($B14="","",_xll.SNL.Clients.Office.Excel.Functions.SPG($B14,"SP_PRICE_CLOSE",WORKDAY($F$2+1,-1),"Options:Curr="&$F$3&", NA=--"))} | I14: {=IF($B14="","",_xll.SNL.Clients.Office.Excel.Functions.SPG($B14,"SP_TRADING_CURRENCY","Options: NA=--"))} | J14: {=IF($B14="","n/a ",_xll.SNL.Clients.Office.Excel.Functions.SPG($B14,"SP_MARKETCAP",WORKDAY($F$2+1,-1),"Options:Curr="&$F$3&", Mag=Millions, NA=--"))} -> n/a | K14: {=IF($B14="","n/a ",_xll.SNL.Clients.Office.Excel.Functions.SPG($B14,"IQ_TEV",WORKDAY($F$2+1,-1),"Options:Curr="&$F$3&", Mag=Millions, NA=--"))} -> n/a | L14: =IFERROR(IF(OR($K14/AC14>L$4,$K14/AC14<L$3),"nmf ",$K14/AC14),"n/a ") -> n/a | M14: =IFERROR(IF(OR($K14/AE14>M$4,$K14/AE14<M$3),"nmf ",$K14/AE14),"n/a ") -> n/a | N14: =IFERROR(IF(OR($K14/AF14>N$4,$K14/AF14<N$3),"nmf ",$K14/AF14),"n/a ") -> n/a | O14: =IFERROR(IF(OR($K14/AH14>O$4,$K14/AH14<O$3),"nmf ",$K14/AH14),"n/a ") -> n/a | P14: =IFERROR(IF(OR($K14/AJ14>P$4,$K14/AJ14<P$3),"nmf ",$K14/AJ14),"n/a ") -> n/a | Q14: =IFERROR(IF(OR($K14/AK14>Q$4,$K14/AK14<Q$3),"nmf ",$K14/AK14),"n/a ") -> n/a | R14: =IFERROR((AE14/AD14)-1,"n/a ") -> n/a | S14: =IFERROR((AF14/AE14)-1,"n/a ") -> n/a | U14: =IFERROR($H14/AM14,"n/a ") -> n/a | V14: =IFERROR($H14/AO14,"n/a ") -> n/a | W14: =IFERROR($H14/AP14,"n/a ") -> n/a | X14: =IFERROR(AR14/100,"n/a ") -> n/a | Y14: =IFERROR(H14/AT14,"n/a ") -> n/a | Z14: =IFERROR(H14/AV14,"n/a ") -> n/a | AC14: {=IF($B14="","",_xll.SNL.Clients.Office.Excel.Functions.SPG($B14,"IQ_REV",AC$7,$F$2,"Options:Curr="&$F$3&", Mag=Millions, NA=--"))} | AD14: {=IF($B14="","",_xll.SNL.Clients.Office.Excel.Functions.SPG($B14,"SP_REV_EST",AD$7,$F$2,"Options:Curr="&$F$3&", Mag=Millions, NA=--"))} | AE14: {=IF($B14="","",_xll.SNL.Clients.Office.Excel.Functions.SPG($B14,"SP_REV_EST",AE$7,$F$2,"Options:Curr="&$F$3&", Mag=Millions, NA=--"))} | AF14: {=IF($B14="","",_xll.SNL.Clients.Office.Excel.Functions.SPG($B14,"SP_REV_EST",AF$7,$F$2,"Options:Curr="&$F$3&", Mag=Millions, NA=--"))} | AH14: {=IF($B14="","",_xll.SNL.Clients.Office.Excel.Functions.SPG($B14,"SP_EBITDA",AH$7,$F$2,"Options:Curr="&$F$3&", Mag=Millions, NA=--"))} | AI14: {=IF($B14="","",_xll.SNL.Clients.Office.Excel.Functions.SPG($B14,"SP_EBITDA_EST",AI$7,$F$2,"Options:Curr="&$F$3&", Mag=Millions, NA=--"))} | AJ14: {=IF($B14="","",_xll.SNL.Clients.Office.Excel.Functions.SPG($B14,"SP_EBITDA_EST",AJ$7,$F$2,"Options:Curr="&$F$3&", Mag=Millions, NA=--"))} | AK14: {=IF($B14="","",_xll.SNL.Clients.Office.Excel.Functions.SPG($B14,"SP_EBITDA_EST",AK$7,$F$2,"Options:Curr="&$F$3&", Mag=Millions, NA=--"))} | AM14: {=IF($B14="","",_xll.SNL.Clients.Office.Excel.Functions.SPG($B14,"IQ_BASIC_EPS_BEFORE_EXTRA",AM$7,$F$2,"Options:Curr="&$F$3&", NA=--"))} | AN14: {=IF($B14="","",_xll.SNL.Clients.Office.Excel.Functions.SPG($B14,"SP_EPS_EST",AN$7,$F$2,"Options:Curr="&$F$3&", NA=--"))} | AO14: {=IF($B14="","",_xll.SNL.Clients.Office.Excel.Functions.SPG($B14,"SP_EPS_EST",AO$7,$F$2,"Options:Curr="&$F$3&", NA=--"))} | AP14: {=IF($B14="","",_xll.SNL.Clients.Office.Excel.Functions.SPG($B14,"SP_EPS_EST",AP$7,$F$2,"Options:Curr="&$F$3&", NA=--"))} | AR14: {=IF($B14="","",_xll.SNL.Clients.Office.Excel.Functions.SPG($B14,"IQ_ROE",AR$7,$F$2,"Options:Curr="&$F$3&", NA=--"))} | AT14: {=IF($B14="","",_xll.SNL.Clients.Office.Excel.Functions.SPG($B14,"IQ_BVPS",AT$7,$F$2,"Options:Curr="&$F$3&", NA=--"))} | AV14: {=IF($B14="","",_xll.SNL.Clients.Office.Excel.Functions.SPG($B14,"IQ_TBVPS",AV$7,$F$2,"Options:Curr="&$F$3&", NA=--"))} | AX14: {=IF($B14="","",_xll.SNL.Clients.Office.Excel.Functions.SPG($B14,"SP_DIV_YIELD",WORKDAY($F$2+1,-1),"Options: NA=--"))} | AY14: {=IF($B14="","",_xll.SNL.Clients.Office.Excel.Functions.SPG($B14,"IQ_TOTAL_EQUITY","FQ0",$F$2,"Options:Curr="&$F$3&", Mag=Millions, NA=--"))} | AZ14: {=IF($B14="","",_xll.SNL.Clients.Office.Excel.Functions.SPG($B14,"IQ_TOTAL_DEBT","FQ0",$F$2,"Options:Curr="&$F$3&", Mag=Millions, NA=--"))} | BA14: {=IF($B14="","",_xll.SNL.Clients.Office.Excel.Functions.SPG($B14,"IQ_CASH_ST_INVEST","FQ0",$F$2,"Options:Curr="&$F$3&", Mag=Millions, NA=--"))} | BB14: =+AZ14-BA14 -> #VALUE! | BC14: {=IF($B14="","",_xll.SNL.Clients.Office.Excel.Functions.SPG($B14,"IQ_TOTAL_EQUITY","FQ0",$F$2,"Options:Curr="&$F$3&", Mag=Millions, NA=--"))} | BE14: =IF($B14="","",IFERROR(_xll.SNL.Clients.Office.Excel.Functions.SPG($B14,"SP_GROSS_MARGIN",BE$7,$F$2,"Options: NA=--")/100,"--")) | BF14: =IF($B14="","",IFERROR(_xll.SNL.Clients.Office.Excel.Functions.SPG($B14,"SP_GROSS_MARGIN_EST",BF$7,$F$2,"Options: NA=--")/100,"--")) | BG14: =IF($B14="","",IFERROR(_xll.SNL.Clients.Office.Excel.Functions.SPG($B14,"SP_GROSS_MARGIN_EST",BG$7,$F$2,"Options: NA=--")/100,"--")) | BH14: =IF($B14="","",IFERROR(_xll.SNL.Clients.Office.Excel.Functions.SPG($B14,"SP_GROSS_MARGIN_EST",BH$7,$F$2,"Options: NA=--")/100,"--"))
D15: {=IF($B15="","",_xll.SNL.Clients.Office.Excel.Functions.SPG($B15, "SP_COMPANY_NAME"))} | G15: {=IF($B15="","",_xll.SNL.Clients.Office.Excel.Functions.SPG($B15,"SP_LASTSALEPRICE",WORKDAY($F$2+1,-1),"Options:Curr="&I15&",NA=--"))} | H15: {=IF($B15="","",_xll.SNL.Clients.Office.Excel.Functions.SPG($B15,"SP_PRICE_CLOSE",WORKDAY($F$2+1,-1),"Options:Curr="&$F$3&", NA=--"))} | I15: {=IF($B15="","",_xll.SNL.Clients.Office.Excel.Functions.SPG($B15,"SP_TRADING_CURRENCY","Options: NA=--"))} | J15: {=IF($B15="","n/a ",_xll.SNL.Clients.Office.Excel.Functions.SPG($B15,"SP_MARKETCAP",WORKDAY($F$2+1,-1),"Options:Curr="&$F$3&", Mag=Millions, NA=--"))} -> n/a | K15: {=IF($B15="","n/a ",_xll.SNL.Clients.Office.Excel.Functions.SPG($B15,"IQ_TEV",WORKDAY($F$2+1,-1),"Options:Curr="&$F$3&", Mag=Millions, NA=--"))} -> n/a | L15: =IFERROR(IF(OR($K15/AC15>L$4,$K15/AC15<L$3),"nmf ",$K15/AC15),"n/a ") -> n/a | M15: =IFERROR(IF(OR($K15/AE15>M$4,$K15/AE15<M$3),"nmf ",$K15/AE15),"n/a ") -> n/a | N15: =IFERROR(IF(OR($K15/AF15>N$4,$K15/AF15<N$3),"nmf ",$K15/AF15),"n/a ") -> n/a | O15: =IFERROR(IF(OR($K15/AH15>O$4,$K15/AH15<O$3),"nmf ",$K15/AH15),"n/a ") -> n/a | P15: =IFERROR(IF(OR($K15/AJ15>P$4,$K15/AJ15<P$3),"nmf ",$K15/AJ15),"n/a ") -> n/a | Q15: =IFERROR(IF(OR($K15/AK15>Q$4,$K15/AK15<Q$3),"nmf ",$K15/AK15),"n/a ") -> n/a | R15: =IFERROR((AE15/AD15)-1,"n/a ") -> n/a | S15: =IFERROR((AF15/AE15)-1,"n/a ") -> n/a | U15: =IFERROR($H15/AM15,"n/a ") -> n/a | V15: =IFERROR($H15/AO15,"n/a ") -> n/a | W15: =IFERROR($H15/AP15,"n/a ") -> n/a | X15: =IFERROR(AR15/100,"n/a ") -> n/a | Y15: =IFERROR(H15/AT15,"n/a ") -> n/a | Z15: =IFERROR(H15/AV15,"n/a ") -> n/a | AC15: {=IF($B15="","",_xll.SNL.Clients.Office.Excel.Functions.SPG($B15,"IQ_REV",AC$7,$F$2,"Options:Curr="&$F$3&", Mag=Millions, NA=--"))} | AD15: {=IF($B15="","",_xll.SNL.Clients.Office.Excel.Functions.SPG($B15,"SP_REV_EST",AD$7,$F$2,"Options:Curr="&$F$3&", Mag=Millions, NA=--"))} | AE15: {=IF($B15="","",_xll.SNL.Clients.Office.Excel.Functions.SPG($B15,"SP_REV_EST",AE$7,$F$2,"Options:Curr="&$F$3&", Mag=Millions, NA=--"))} | AF15: {=IF($B15="","",_xll.SNL.Clients.Office.Excel.Functions.SPG($B15,"SP_REV_EST",AF$7,$F$2,"Options:Curr="&$F$3&", Mag=Millions, NA=--"))} | AH15: {=IF($B15="","",_xll.SNL.Clients.Office.Excel.Functions.SPG($B15,"SP_EBITDA",AH$7,$F$2,"Options:Curr="&$F$3&", Mag=Millions, NA=--"))} | AI15: {=IF($B15="","",_xll.SNL.Clients.Office.Excel.Functions.SPG($B15,"SP_EBITDA_EST",AI$7,$F$2,"Options:Curr="&$F$3&", Mag=Millions, NA=--"))} | AJ15: {=IF($B15="","",_xll.SNL.Clients.Office.Excel.Functions.SPG($B15,"SP_EBITDA_EST",AJ$7,$F$2,"Options:Curr="&$F$3&", Mag=Millions, NA=--"))} | AK15: {=IF($B15="","",_xll.SNL.Clients.Office.Excel.Functions.SPG($B15,"SP_EBITDA_EST",AK$7,$F$2,"Options:Curr="&$F$3&", Mag=Millions, NA=--"))} | AM15: {=IF($B15="","",_xll.SNL.Clients.Office.Excel.Functions.SPG($B15,"IQ_BASIC_EPS_BEFORE_EXTRA",AM$7,$F$2,"Options:Curr="&$F$3&", NA=--"))} | AN15: {=IF($B15="","",_xll.SNL.Clients.Office.Excel.Functions.SPG($B15,"SP_EPS_EST",AN$7,$F$2,"Options:Curr="&$F$3&", NA=--"))} | AO15: {=IF($B15="","",_xll.SNL.Clients.Office.Excel.Functions.SPG($B15,"SP_EPS_EST",AO$7,$F$2,"Options:Curr="&$F$3&", NA=--"))} | AP15: {=IF($B15="","",_xll.SNL.Clients.Office.Excel.Functions.SPG($B15,"SP_EPS_EST",AP$7,$F$2,"Options:Curr="&$F$3&", NA=--"))} | AR15: {=IF($B15="","",_xll.SNL.Clients.Office.Excel.Functions.SPG($B15,"IQ_ROE",AR$7,$F$2,"Options:Curr="&$F$3&", NA=--"))} | AT15: {=IF($B15="","",_xll.SNL.Clients.Office.Excel.Functions.SPG($B15,"IQ_BVPS",AT$7,$F$2,"Options:Curr="&$F$3&", NA=--"))} | AV15: {=IF($B15="","",_xll.SNL.Clients.Office.Excel.Functions.SPG($B15,"IQ_TBVPS",AV$7,$F$2,"Options:Curr="&$F$3&", NA=--"))} | AX15: {=IF($B15="","",_xll.SNL.Clients.Office.Excel.Functions.SPG($B15,"SP_DIV_YIELD",WORKDAY($F$2+1,-1),"Options: NA=--"))} | AY15: {=IF($B15="","",_xll.SNL.Clients.Office.Excel.Functions.SPG($B15,"IQ_TOTAL_EQUITY","FQ0",$F$2,"Options:Curr="&$F$3&", Mag=Millions, NA=--"))} | AZ15: {=IF($B15="","",_xll.SNL.Clients.Office.Excel.Functions.SPG($B15,"IQ_TOTAL_DEBT","FQ0",$F$2,"Options:Curr="&$F$3&", Mag=Millions, NA=--"))} | BA15: {=IF($B15="","",_xll.SNL.Clients.Office.Excel.Functions.SPG($B15,"IQ_CASH_ST_INVEST","FQ0",$F$2,"Options:Curr="&$F$3&", Mag=Millions, NA=--"))} | BB15: =+AZ15-BA15 -> #VALUE! | BC15: {=IF($B15="","",_xll.SNL.Clients.Office.Excel.Functions.SPG($B15,"IQ_TOTAL_EQUITY","FQ0",$F$2,"Options:Curr="&$F$3&", Mag=Millions, NA=--"))} | BE15: =IF($B15="","",IFERROR(_xll.SNL.Clients.Office.Excel.Functions.SPG($B15,"SP_GROSS_MARGIN",BE$7,$F$2,"Options: NA=--")/100,"--")) | BF15: =IF($B15="","",IFERROR(_xll.SNL.Clients.Office.Excel.Functions.SPG($B15,"SP_GROSS_MARGIN_EST",BF$7,$F$2,"Options: NA=--")/100,"--")) | BG15: =IF($B15="","",IFERROR(_xll.SNL.Clients.Office.Excel.Functions.SPG($B15,"SP_GROSS_MARGIN_EST",BG$7,$F$2,"Options: NA=--")/100,"--")) | BH15: =IF($B15="","",IFERROR(_xll.SNL.Clients.Office.Excel.Functions.SPG($B15,"SP_GROSS_MARGIN_EST",BH$7,$F$2,"Options: NA=--")/100,"--"))
D17: Group Average | L17: =IFERROR(AVERAGE(L10:L15),"n/a ") -> n/a | M17: =IFERROR(AVERAGE(M10:M15),"n/a ") -> n/a | N17: =IFERROR(AVERAGE(N10:N15),"n/a ") -> n/a | O17: =IFERROR(AVERAGE(O10:O15),"n/a ") -> n/a | P17: =IFERROR(AVERAGE(P10:P15),"n/a ") -> n/a | Q17: =IFERROR(AVERAGE(Q10:Q15),"n/a ") -> n/a | R17: =IFERROR(AVERAGE(R10:R15),"n/a ") -> n/a | S17: =IFERROR(AVERAGE(S10:S15),"n/a ") -> n/a | U17: =IFERROR(AVERAGE(U10:U15),"n/a ") -> n/a | V17: =IFERROR(AVERAGE(V10:V15),"n/a ") -> n/a | W17: =IFERROR(AVERAGE(W10:W15),"n/a ") -> n/a | X17: =IFERROR(AVERAGE(X10:X15),"n/a ") -> n/a | Y17: =IFERROR(AVERAGE(Y10:Y15),"n/a ") -> n/a | Z17: =IFERROR(AVERAGE(Z10:Z15),"n/a ") -> n/a
D19: [Group #2]
D20: {=IF($B20="","",_xll.SNL.Clients.Office.Excel.Functions.SPG($B20, "SP_COMPANY_NAME"))} | G20: {=IF($B20="","",_xll.SNL.Clients.Office.Excel.Functions.SPG($B20,"SP_LASTSALEPRICE",WORKDAY($F$2+1,-1),"Options:Curr="&I20&",NA=--"))} | H20: {=IF($B20="","",_xll.SNL.Clients.Office.Excel.Functions.SPG($B20,"SP_PRICE_CLOSE",WORKDAY($F$2+1,-1),"Options:Curr="&$F$3&", NA=--"))} | I20: {=IF($B20="","",_xll.SNL.Clients.Office.Excel.Functions.SPG($B20,"SP_TRADING_CURRENCY","Options: NA=--"))} | J20: {=IF($B20="","n/a ",_xll.SNL.Clients.Office.Excel.Functions.SPG($B20,"SP_MARKETCAP",WORKDAY($F$2+1,-1),"Options:Curr="&$F$3&", Mag=Millions, NA=--"))} -> n/a | K20: {=IF($B20="","n/a ",_xll.SNL.Clients.Office.Excel.Functions.SPG($B20,"IQ_TEV",WORKDAY($F$2+1,-1),"Options:Curr="&$F$3&", Mag=Millions, NA=--"))} -> n/a | L20: =IFERROR(IF(OR($K20/AC20>L$4,$K20/AC20<L$3),"nmf ",$K20/AC20),"n/a ") -> n/a | M20: =IFERROR(IF(OR($K20/AD20>M$4,$K20/AD20<M$3),"nmf ",$K20/AD20),"n/a ") -> n/a | N20: =IFERROR(IF(OR($K20/AE20>N$4,$K20/AE20<N$3),"nmf ",$K20/AE20),"n/a ") -> n/a | O20: =IFERROR(IF(OR($K20/AH20>O$4,$K20/AH20<O$3),"nmf ",$K20/AH20),"n/a ") -> n/a | P20: =IFERROR(IF(OR($K20/AI20>P$4,$K20/AI20<P$3),"nmf ",$K20/AI20),"n/a ") -> n/a | Q20: =IFERROR(IF(OR($K20/AJ20>Q$4,$K20/AJ20<Q$3),"nmf ",$K20/AJ20),"n/a ") -> n/a | R20: =IFERROR((AE20/AD20)-1,"n/a ") -> n/a | S20: =IFERROR((AF20/AE20)-1,"n/a ") -> n/a | U20: =IFERROR($H20/AM20,"n/a ") -> n/a | V20: =IFERROR($H20/AO20,"n/a ") -> n/a | W20: =IFERROR($H20/AP20,"n/a ") -> n/a | X20: =IFERROR(AR20/100,"n/a ") -> n/a | Y20: =IFERROR(H20/AT20,"n/a ") -> n/a | Z20: =IFERROR(H20/AV20,"n/a ") -> n/a | AC20: {=IF($B20="","",_xll.SNL.Clients.Office.Excel.Functions.SPG($B20,"IQ_REV",AC$7,$F$2,"Options:Curr="&$F$3&", Mag=Millions, NA=--"))} | AD20: {=IF($B20="","",_xll.SNL.Clients.Office.Excel.Functions.SPG($B20,"SP_REV_EST",AD$7,$F$2,"Options:Curr="&$F$3&", Mag=Millions, NA=--"))} | AE20: {=IF($B20="","",_xll.SNL.Clients.Office.Excel.Functions.SPG($B20,"SP_REV_EST",AE$7,$F$2,"Options:Curr="&$F$3&", Mag=Millions, NA=--"))} | AF20: {=IF($B20="","",_xll.SNL.Clients.Office.Excel.Functions.SPG($B20,"SP_REV_EST",AF$7,$F$2,"Options:Curr="&$F$3&", Mag=Millions, NA=--"))} | AH20: {=IF($B20="","",_xll.SNL.Clients.Office.Excel.Functions.SPG($B20,"SP_EBITDA",AH$7,$F$2,"Options:Curr="&$F$3&", Mag=Millions, NA=--"))} | AI20: {=IF($B20="","",_xll.SNL.Clients.Office.Excel.Functions.SPG($B20,"SP_EBITDA_EST",AI$7,$F$2,"Options:Curr="&$F$3&", Mag=Millions, NA=--"))} | AJ20: {=IF($B20="","",_xll.SNL.Clients.Office.Excel.Functions.SPG($B20,"SP_EBITDA_EST",AJ$7,$F$2,"Options:Curr="&$F$3&", Mag=Millions, NA=--"))} | AK20: {=IF($B20="","",_xll.SNL.Clients.Office.Excel.Functions.SPG($B20,"SP_EBITDA_EST",AK$7,$F$2,"Options:Curr="&$F$3&", Mag=Millions, NA=--"))} | AM20: {=IF($B20="","",_xll.SNL.Clients.Office.Excel.Functions.SPG($B20,"IQ_BASIC_EPS_BEFORE_EXTRA",AM$7,$F$2,"Options:Curr="&$F$3&", NA=--"))} | AN20: {=IF($B20="","",_xll.SNL.Clients.Office.Excel.Functions.SPG($B20,"SP_EPS_EST",AN$7,$F$2,"Options:Curr="&$F$3&", NA=--"))} | AO20: {=IF($B20="","",_xll.SNL.Clients.Office.Excel.Functions.SPG($B20,"SP_EPS_EST",AO$7,$F$2,"Options:Curr="&$F$3&", NA=--"))} | AP20: {=IF($B20="","",_xll.SNL.Clients.Office.Excel.Functions.SPG($B20,"SP_EPS_EST",AP$7,$F$2,"Options:Curr="&$F$3&", NA=--"))} | AR20: {=IF($B20="","",_xll.SNL.Clients.Office.Excel.Functions.SPG($B20,"IQ_ROE",AR$7,$F$2,"Options:Curr="&$F$3&", NA=--"))} | AT20: {=IF($B20="","",_xll.SNL.Clients.Office.Excel.Functions.SPG($B20,"IQ_BVPS",AT$7,$F$2,"Options:Curr="&$F$3&", NA=--"))} | AV20: {=IF($B20="","",_xll.SNL.Clients.Office.Excel.Functions.SPG($B20,"IQ_TBVPS",AV$7,$F$2,"Options:Curr="&$F$3&", NA=--"))} | AX20: {=IF($B20="","",_xll.SNL.Clients.Office.Excel.Functions.SPG($B20,"SP_DIV_YIELD",WORKDAY($F$2+1,-1),"Options: NA=--"))} | AY20: {=IF($B20="","",_xll.SNL.Clients.Office.Excel.Functions.SPG($B20,"IQ_TOTAL_EQUITY","FQ0",$F$2,"Options:Curr="&$F$3&", Mag=Millions, NA=--"))} | AZ20: {=IF($B20="","",_xll.SNL.Clients.Office.Excel.Functions.SPG($B20,"IQ_TOTAL_DEBT","FQ0",$F$2,"Options:Curr="&$F$3&", Mag=Millions, NA=--"))} | BA20: {=IF($B20="","",_xll.SNL.Clients.Office.Excel.Functions.SPG($B20,"IQ_CASH_ST_INVEST","FQ0",$F$2,"Options:Curr="&$F$3&", Mag=Millions, NA=--"))} | BB20: =+AZ20-BA20 -> #VALUE! | BC20: {=IF($B20="","",_xll.SNL.Clients.Office.Excel.Functions.SPG($B20,"IQ_TOTAL_EQUITY","FQ0",$F$2,"Options:Curr="&$F$3&", Mag=Millions, NA=--"))} | BE20: =IF($B20="","",IFERROR(_xll.SNL.Clients.Office.Excel.Functions.SPG($B20,"SP_GROSS_MARGIN",BE$7,$F$2,"Options: NA=--")/100,"--")) | BF20: =IF($B20="","",IFERROR(_xll.SNL.Clients.Office.Excel.Functions.SPG($B20,"SP_GROSS_MARGIN_EST",BF$7,$F$2,"Options: NA=--")/100,"--")) | BG20: =IF($B20="","",IFERROR(_xll.SNL.Clients.Office.Excel.Functions.SPG($B20,"SP_GROSS_MARGIN_EST",BG$7,$F$2,"Options: NA=--")/100,"--")) | BH20: =IF($B20="","",IFERROR(_xll.SNL.Clients.Office.Excel.Functions.SPG($B20,"SP_GROSS_MARGIN_EST",BH$7,$F$2,"Options: NA=--")/100,"--"))
D21: {=IF($B21="","",_xll.SNL.Clients.Office.Excel.Functions.SPG($B21, "SP_COMPANY_NAME"))} | G21: {=IF($B21="","",_xll.SNL.Clients.Office.Excel.Functions.SPG($B21,"SP_LASTSALEPRICE",WORKDAY($F$2+1,-1),"Options:Curr="&I21&",NA=--"))} | H21: {=IF($B21="","",_xll.SNL.Clients.Office.Excel.Functions.SPG($B21,"SP_PRICE_CLOSE",WORKDAY($F$2+1,-1),"Options:Curr="&$F$3&", NA=--"))} | I21: {=IF($B21="","",_xll.SNL.Clients.Office.Excel.Functions.SPG($B21,"SP_TRADING_CURRENCY","Options: NA=--"))} | J21: {=IF($B21="","n/a ",_xll.SNL.Clients.Office.Excel.Functions.SPG($B21,"SP_MARKETCAP",WORKDAY($F$2+1,-1),"Options:Curr="&$F$3&", Mag=Millions, NA=--"))} -> n/a | K21: {=IF($B21="","n/a ",_xll.SNL.Clients.Office.Excel.Functions.SPG($B21,"IQ_TEV",WORKDAY($F$2+1,-1),"Options:Curr="&$F$3&", Mag=Millions, NA=--"))} -> n/a | L21: =IFERROR(IF(OR($K21/AC21>L$4,$K21/AC21<L$3),"nmf ",$K21/AC21),"n/a ") -> n/a | M21: =IFERROR(IF(OR($K21/AD21>M$4,$K21/AD21<M$3),"nmf ",$K21/AD21),"n/a ") -> n/a | N21: =IFERROR(IF(OR($K21/AE21>N$4,$K21/AE21<N$3),"nmf ",$K21/AE21),"n/a ") -> n/a | O21: =IFERROR(IF(OR($K21/AH21>O$4,$K21/AH21<O$3),"nmf ",$K21/AH21),"n/a ") -> n/a | P21: =IFERROR(IF(OR($K21/AI21>P$4,$K21/AI21<P$3),"nmf ",$K21/AI21),"n/a ") -> n/a | Q21: =IFERROR(IF(OR($K21/AJ21>Q$4,$K21/AJ21<Q$3),"nmf ",$K21/AJ21),"n/a ") -> n/a | R21: =IFERROR((AE21/AD21)-1,"n/a ") -> n/a | S21: =IFERROR((AF21/AE21)-1,"n/a ") -> n/a | U21: =IFERROR($H21/AM21,"n/a ") -> n/a | V21: =IFERROR($H21/AO21,"n/a ") -> n/a | W21: =IFERROR($H21/AP21,"n/a ") -> n/a | X21: =IFERROR(AR21/100,"n/a ") -> n/a | Y21: =IFERROR(H21/AT21,"n/a ") -> n/a | Z21: =IFERROR(H21/AV21,"n/a ") -> n/a | AC21: {=IF($B21="","",_xll.SNL.Clients.Office.Excel.Functions.SPG($B21,"IQ_REV",AC$7,$F$2,"Options:Curr="&$F$3&", Mag=Millions, NA=--"))} | AD21: {=IF($B21="","",_xll.SNL.Clients.Office.Excel.Functions.SPG($B21,"SP_REV_EST",AD$7,$F$2,"Options:Curr="&$F$3&", Mag=Millions, NA=--"))} | AE21: {=IF($B21="","",_xll.SNL.Clients.Office.Excel.Functions.SPG($B21,"SP_REV_EST",AE$7,$F$2,"Options:Curr="&$F$3&", Mag=Millions, NA=--"))} | AF21: {=IF($B21="","",_xll.SNL.Clients.Office.Excel.Functions.SPG($B21,"SP_REV_EST",AF$7,$F$2,"Options:Curr="&$F$3&", Mag=Millions, NA=--"))} | AH21: {=IF($B21="","",_xll.SNL.Clients.Office.Excel.Functions.SPG($B21,"SP_EBITDA",AH$7,$F$2,"Options:Curr="&$F$3&", Mag=Millions, NA=--"))} | AI21: {=IF($B21="","",_xll.SNL.Clients.Office.Excel.Functions.SPG($B21,"SP_EBITDA_EST",AI$7,$F$2,"Options:Curr="&$F$3&", Mag=Millions, NA=--"))} | AJ21: {=IF($B21="","",_xll.SNL.Clients.Office.Excel.Functions.SPG($B21,"SP_EBITDA_EST",AJ$7,$F$2,"Options:Curr="&$F$3&", Mag=Millions, NA=--"))} | AK21: {=IF($B21="","",_xll.SNL.Clients.Office.Excel.Functions.SPG($B21,"SP_EBITDA_EST",AK$7,$F$2,"Options:Curr="&$F$3&", Mag=Millions, NA=--"))} | AM21: {=IF($B21="","",_xll.SNL.Clients.Office.Excel.Functions.SPG($B21,"IQ_BASIC_EPS_BEFORE_EXTRA",AM$7,$F$2,"Options:Curr="&$F$3&", NA=--"))} | AN21: {=IF($B21="","",_xll.SNL.Clients.Office.Excel.Functions.SPG($B21,"SP_EPS_EST",AN$7,$F$2,"Options:Curr="&$F$3&", NA=--"))} | AO21: {=IF($B21="","",_xll.SNL.Clients.Office.Excel.Functions.SPG($B21,"SP_EPS_EST",AO$7,$F$2,"Options:Curr="&$F$3&", NA=--"))} | AP21: {=IF($B21="","",_xll.SNL.Clients.Office.Excel.Functions.SPG($B21,"SP_EPS_EST",AP$7,$F$2,"Options:Curr="&$F$3&", NA=--"))} | AR21: {=IF($B21="","",_xll.SNL.Clients.Office.Excel.Functions.SPG($B21,"IQ_ROE",AR$7,$F$2,"Options:Curr="&$F$3&", NA=--"))} | AT21: {=IF($B21="","",_xll.SNL.Clients.Office.Excel.Functions.SPG($B21,"IQ_BVPS",AT$7,$F$2,"Options:Curr="&$F$3&", NA=--"))} | AV21: {=IF($B21="","",_xll.SNL.Clients.Office.Excel.Functions.SPG($B21,"IQ_TBVPS",AV$7,$F$2,"Options:Curr="&$F$3&", NA=--"))} | AX21: {=IF($B21="","",_xll.SNL.Clients.Office.Excel.Functions.SPG($B21,"SP_DIV_YIELD",WORKDAY($F$2+1,-1),"Options: NA=--"))} | AY21: {=IF($B21="","",_xll.SNL.Clients.Office.Excel.Functions.SPG($B21,"IQ_TOTAL_EQUITY","FQ0",$F$2,"Options:Curr="&$F$3&", Mag=Millions, NA=--"))} | AZ21: {=IF($B21="","",_xll.SNL.Clients.Office.Excel.Functions.SPG($B21,"IQ_TOTAL_DEBT","FQ0",$F$2,"Options:Curr="&$F$3&", Mag=Millions, NA=--"))} | BA21: {=IF($B21="","",_xll.SNL.Clients.Office.Excel.Functions.SPG($B21,"IQ_CASH_ST_INVEST","FQ0",$F$2,"Options:Curr="&$F$3&", Mag=Millions, NA=--"))} | BB21: =+AZ21-BA21 -> #VALUE! | BC21: {=IF($B21="","",_xll.SNL.Clients.Office.Excel.Functions.SPG($B21,"IQ_TOTAL_EQUITY","FQ0",$F$2,"Options:Curr="&$F$3&", Mag=Millions, NA=--"))} | BE21: =IF($B21="","",IFERROR(_xll.SNL.Clients.Office.Excel.Functions.SPG($B21,"SP_GROSS_MARGIN",BE$7,$F$2,"Options: NA=--")/100,"--")) | BF21: =IF($B21="","",IFERROR(_xll.SNL.Clients.Office.Excel.Functions.SPG($B21,"SP_GROSS_MARGIN_EST",BF$7,$F$2,"Options: NA=--")/100,"--")) | BG21: =IF($B21="","",IFERROR(_xll.SNL.Clients.Office.Excel.Functions.SPG($B21,"SP_GROSS_MARGIN_EST",BG$7,$F$2,"Options: NA=--")/100,"--")) | BH21: =IF($B21="","",IFERROR(_xll.SNL.Clients.Office.Excel.Functions.SPG($B21,"SP_GROSS_MARGIN_EST",BH$7,$F$2,"Options: NA=--")/100,"--"))
D22: {=IF($B22="","",_xll.SNL.Clients.Office.Excel.Functions.SPG($B22, "SP_COMPANY_NAME"))} | G22: {=IF($B22="","",_xll.SNL.Clients.Office.Excel.Functions.SPG($B22,"SP_LASTSALEPRICE",WORKDAY($F$2+1,-1),"Options:Curr="&I22&",NA=--"))} | H22: {=IF($B22="","",_xll.SNL.Clients.Office.Excel.Functions.SPG($B22,"SP_PRICE_CLOSE",WORKDAY($F$2+1,-1),"Options:Curr="&$F$3&", NA=--"))} | I22: {=IF($B22="","",_xll.SNL.Clients.Office.Excel.Functions.SPG($B22,"SP_TRADING_CURRENCY","Options: NA=--"))} | J22: {=IF($B22="","n/a ",_xll.SNL.Clients.Office.Excel.Functions.SPG($B22,"SP_MARKETCAP",WORKDAY($F$2+1,-1),"Options:Curr="&$F$3&", Mag=Millions, NA=--"))} -> n/a | K22: {=IF($B22="","n/a ",_xll.SNL.Clients.Office.Excel.Functions.SPG($B22,"IQ_TEV",WORKDAY($F$2+1,-1),"Options:Curr="&$F$3&", Mag=Millions, NA=--"))} -> n/a | L22: =IFERROR(IF(OR($K22/AC22>L$4,$K22/AC22<L$3),"nmf ",$K22/AC22),"n/a ") -> n/a | M22: =IFERROR(IF(OR($K22/AD22>M$4,$K22/AD22<M$3),"nmf ",$K22/AD22),"n/a ") -> n/a | N22: =IFERROR(IF(OR($K22/AE22>N$4,$K22/AE22<N$3),"nmf ",$K22/AE22),"n/a ") -> n/a | O22: =IFERROR(IF(OR($K22/AH22>O$4,$K22/AH22<O$3),"nmf ",$K22/AH22),"n/a ") -> n/a | P22: =IFERROR(IF(OR($K22/AI22>P$4,$K22/AI22<P$3),"nmf ",$K22/AI22),"n/a ") -> n/a | Q22: =IFERROR(IF(OR($K22/AJ22>Q$4,$K22/AJ22<Q$3),"nmf ",$K22/AJ22),"n/a ") -> n/a | R22: =IFERROR((AE22/AD22)-1,"n/a ") -> n/a | S22: =IFERROR((AF22/AE22)-1,"n/a ") -> n/a | U22: =IFERROR($H22/AM22,"n/a ") -> n/a | V22: =IFERROR($H22/AO22,"n/a ") -> n/a | W22: =IFERROR($H22/AP22,"n/a ") -> n/a | X22: =IFERROR(AR22/100,"n/a ") -> n/a | Y22: =IFERROR(H22/AT22,"n/a ") -> n/a | Z22: =IFERROR(H22/AV22,"n/a ") -> n/a | AC22: {=IF($B22="","",_xll.SNL.Clients.Office.Excel.Functions.SPG($B22,"IQ_REV",AC$7,$F$2,"Options:Curr="&$F$3&", Mag=Millions, NA=--"))} | AD22: {=IF($B22="","",_xll.SNL.Clients.Office.Excel.Functions.SPG($B22,"SP_REV_EST",AD$7,$F$2,"Options:Curr="&$F$3&", Mag=Millions, NA=--"))} | AE22: {=IF($B22="","",_xll.SNL.Clients.Office.Excel.Functions.SPG($B22,"SP_REV_EST",AE$7,$F$2,"Options:Curr="&$F$3&", Mag=Millions, NA=--"))} | AF22: {=IF($B22="","",_xll.SNL.Clients.Office.Excel.Functions.SPG($B22,"SP_REV_EST",AF$7,$F$2,"Options:Curr="&$F$3&", Mag=Millions, NA=--"))} | AH22: {=IF($B22="","",_xll.SNL.Clients.Office.Excel.Functions.SPG($B22,"SP_EBITDA",AH$7,$F$2,"Options:Curr="&$F$3&", Mag=Millions, NA=--"))} | AI22: {=IF($B22="","",_xll.SNL.Clients.Office.Excel.Functions.SPG($B22,"SP_EBITDA_EST",AI$7,$F$2,"Options:Curr="&$F$3&", Mag=Millions, NA=--"))} | AJ22: {=IF($B22="","",_xll.SNL.Clients.Office.Excel.Functions.SPG($B22,"SP_EBITDA_EST",AJ$7,$F$2,"Options:Curr="&$F$3&", Mag=Millions, NA=--"))} | AK22: {=IF($B22="","",_xll.SNL.Clients.Office.Excel.Functions.SPG($B22,"SP_EBITDA_EST",AK$7,$F$2,"Options:Curr="&$F$3&", Mag=Millions, NA=--"))} | AM22: {=IF($B22="","",_xll.SNL.Clients.Office.Excel.Functions.SPG($B22,"IQ_BASIC_EPS_BEFORE_EXTRA",AM$7,$F$2,"Options:Curr="&$F$3&", NA=--"))} | AN22: {=IF($B22="","",_xll.SNL.Clients.Office.Excel.Functions.SPG($B22,"SP_EPS_EST",AN$7,$F$2,"Options:Curr="&$F$3&", NA=--"))} | AO22: {=IF($B22="","",_xll.SNL.Clients.Office.Excel.Functions.SPG($B22,"SP_EPS_EST",AO$7,$F$2,"Options:Curr="&$F$3&", NA=--"))} | AP22: {=IF($B22="","",_xll.SNL.Clients.Office.Excel.Functions.SPG($B22,"SP_EPS_EST",AP$7,$F$2,"Options:Curr="&$F$3&", NA=--"))} | AR22: {=IF($B22="","",_xll.SNL.Clients.Office.Excel.Functions.SPG($B22,"IQ_ROE",AR$7,$F$2,"Options:Curr="&$F$3&", NA=--"))} | AT22: {=IF($B22="","",_xll.SNL.Clients.Office.Excel.Functions.SPG($B22,"IQ_BVPS",AT$7,$F$2,"Options:Curr="&$F$3&", NA=--"))} | AV22: {=IF($B22="","",_xll.SNL.Clients.Office.Excel.Functions.SPG($B22,"IQ_TBVPS",AV$7,$F$2,"Options:Curr="&$F$3&", NA=--"))} | AX22: {=IF($B22="","",_xll.SNL.Clients.Office.Excel.Functions.SPG($B22,"SP_DIV_YIELD",WORKDAY($F$2+1,-1),"Options: NA=--"))} | AY22: {=IF($B22="","",_xll.SNL.Clients.Office.Excel.Functions.SPG($B22,"IQ_TOTAL_EQUITY","FQ0",$F$2,"Options:Curr="&$F$3&", Mag=Millions, NA=--"))} | AZ22: {=IF($B22="","",_xll.SNL.Clients.Office.Excel.Functions.SPG($B22,"IQ_TOTAL_DEBT","FQ0",$F$2,"Options:Curr="&$F$3&", Mag=Millions, NA=--"))} | BA22: {=IF($B22="","",_xll.SNL.Clients.Office.Excel.Functions.SPG($B22,"IQ_CASH_ST_INVEST","FQ0",$F$2,"Options:Curr="&$F$3&", Mag=Millions, NA=--"))} | BB22: =+AZ22-BA22 -> #VALUE! | BC22: {=IF($B22="","",_xll.SNL.Clients.Office.Excel.Functions.SPG($B22,"IQ_TOTAL_EQUITY","FQ0",$F$2,"Options:Curr="&$F$3&", Mag=Millions, NA=--"))} | BE22: =IF($B22="","",IFERROR(_xll.SNL.Clients.Office.Excel.Functions.SPG($B22,"SP_GROSS_MARGIN",BE$7,$F$2,"Options: NA=--")/100,"--")) | BF22: =IF($B22="","",IFERROR(_xll.SNL.Clients.Office.Excel.Functions.SPG($B22,"SP_GROSS_MARGIN_EST",BF$7,$F$2,"Options: NA=--")/100,"--")) | BG22: =IF($B22="","",IFERROR(_xll.SNL.Clients.Office.Excel.Functions.SPG($B22,"SP_GROSS_MARGIN_EST",BG$7,$F$2,"Options: NA=--")/100,"--")) | BH22: =IF($B22="","",IFERROR(_xll.SNL.Clients.Office.Excel.Functions.SPG($B22,"SP_GROSS_MARGIN_EST",BH$7,$F$2,"Options: NA=--")/100,"--"))
D23: {=IF($B23="","",_xll.SNL.Clients.Office.Excel.Functions.SPG($B23, "SP_COMPANY_NAME"))} | G23: {=IF($B23="","",_xll.SNL.Clients.Office.Excel.Functions.SPG($B23,"SP_LASTSALEPRICE",WORKDAY($F$2+1,-1),"Options:Curr="&I23&",NA=--"))} | H23: {=IF($B23="","",_xll.SNL.Clients.Office.Excel.Functions.SPG($B23,"SP_PRICE_CLOSE",WORKDAY($F$2+1,-1),"Options:Curr="&$F$3&", NA=--"))} | I23: {=IF($B23="","",_xll.SNL.Clients.Office.Excel.Functions.SPG($B23,"SP_TRADING_CURRENCY","Options: NA=--"))} | J23: {=IF($B23="","n/a ",_xll.SNL.Clients.Office.Excel.Functions.SPG($B23,"SP_MARKETCAP",WORKDAY($F$2+1,-1),"Options:Curr="&$F$3&", Mag=Millions, NA=--"))} -> n/a | K23: {=IF($B23="","n/a ",_xll.SNL.Clients.Office.Excel.Functions.SPG($B23,"IQ_TEV",WORKDAY($F$2+1,-1),"Options:Curr="&$F$3&", Mag=Millions, NA=--"))} -> n/a | L23: =IFERROR(IF(OR($K23/AC23>L$4,$K23/AC23<L$3),"nmf ",$K23/AC23),"n/a ") -> n/a | M23: =IFERROR(IF(OR($K23/AD23>M$4,$K23/AD23<M$3),"nmf ",$K23/AD23),"n/a ") -> n/a | N23: =IFERROR(IF(OR($K23/AE23>N$4,$K23/AE23<N$3),"nmf ",$K23/AE23),"n/a ") -> n/a | O23: =IFERROR(IF(OR($K23/AH23>O$4,$K23/AH23<O$3),"nmf ",$K23/AH23),"n/a ") -> n/a | P23: =IFERROR(IF(OR($K23/AI23>P$4,$K23/AI23<P$3),"nmf ",$K23/AI23),"n/a ") -> n/a | Q23: =IFERROR(IF(OR($K23/AJ23>Q$4,$K23/AJ23<Q$3),"nmf ",$K23/AJ23),"n/a ") -> n/a | R23: =IFERROR((AE23/AD23)-1,"n/a ") -> n/a | S23: =IFERROR((AF23/AE23)-1,"n/a ") -> n/a | U23: =IFERROR($H23/AM23,"n/a ") -> n/a | V23: =IFERROR($H23/AO23,"n/a ") -> n/a | W23: =IFERROR($H23/AP23,"n/a ") -> n/a | X23: =IFERROR(AR23/100,"n/a ") -> n/a | Y23: =IFERROR(H23/AT23,"n/a ") -> n/a | Z23: =IFERROR(H23/AV23,"n/a ") -> n/a | AC23: {=IF($B23="","",_xll.SNL.Clients.Office.Excel.Functions.SPG($B23,"IQ_REV",AC$7,$F$2,"Options:Curr="&$F$3&", Mag=Millions, NA=--"))} | AD23: {=IF($B23="","",_xll.SNL.Clients.Office.Excel.Functions.SPG($B23,"SP_REV_EST",AD$7,$F$2,"Options:Curr="&$F$3&", Mag=Millions, NA=--"))} | AE23: {=IF($B23="","",_xll.SNL.Clients.Office.Excel.Functions.SPG($B23,"SP_REV_EST",AE$7,$F$2,"Options:Curr="&$F$3&", Mag=Millions, NA=--"))} | AF23: {=IF($B23="","",_xll.SNL.Clients.Office.Excel.Functions.SPG($B23,"SP_REV_EST",AF$7,$F$2,"Options:Curr="&$F$3&", Mag=Millions, NA=--"))} | AH23: {=IF($B23="","",_xll.SNL.Clients.Office.Excel.Functions.SPG($B23,"SP_EBITDA",AH$7,$F$2,"Options:Curr="&$F$3&", Mag=Millions, NA=--"))} | AI23: {=IF($B23="","",_xll.SNL.Clients.Office.Excel.Functions.SPG($B23,"SP_EBITDA_EST",AI$7,$F$2,"Options:Curr="&$F$3&", Mag=Millions, NA=--"))} | AJ23: {=IF($B23="","",_xll.SNL.Clients.Office.Excel.Functions.SPG($B23,"SP_EBITDA_EST",AJ$7,$F$2,"Options:Curr="&$F$3&", Mag=Millions, NA=--"))} | AK23: {=IF($B23="","",_xll.SNL.Clients.Office.Excel.Functions.SPG($B23,"SP_EBITDA_EST",AK$7,$F$2,"Options:Curr="&$F$3&", Mag=Millions, NA=--"))} | AM23: {=IF($B23="","",_xll.SNL.Clients.Office.Excel.Functions.SPG($B23,"IQ_BASIC_EPS_BEFORE_EXTRA",AM$7,$F$2,"Options:Curr="&$F$3&", NA=--"))} | AN23: {=IF($B23="","",_xll.SNL.Clients.Office.Excel.Functions.SPG($B23,"SP_EPS_EST",AN$7,$F$2,"Options:Curr="&$F$3&", NA=--"))} | AO23: {=IF($B23="","",_xll.SNL.Clients.Office.Excel.Functions.SPG($B23,"SP_EPS_EST",AO$7,$F$2,"Options:Curr="&$F$3&", NA=--"))} | AP23: {=IF($B23="","",_xll.SNL.Clients.Office.Excel.Functions.SPG($B23,"SP_EPS_EST",AP$7,$F$2,"Options:Curr="&$F$3&", NA=--"))} | AR23: {=IF($B23="","",_xll.SNL.Clients.Office.Excel.Functions.SPG($B23,"IQ_ROE",AR$7,$F$2,"Options:Curr="&$F$3&", NA=--"))} | AT23: {=IF($B23="","",_xll.SNL.Clients.Office.Excel.Functions.SPG($B23,"IQ_BVPS",AT$7,$F$2,"Options:Curr="&$F$3&", NA=--"))} | AV23: {=IF($B23="","",_xll.SNL.Clients.Office.Excel.Functions.SPG($B23,"IQ_TBVPS",AV$7,$F$2,"Options:Curr="&$F$3&", NA=--"))} | AX23: {=IF($B23="","",_xll.SNL.Clients.Office.Excel.Functions.SPG($B23,"SP_DIV_YIELD",WORKDAY($F$2+1,-1),"Options: NA=--"))} | AY23: {=IF($B23="","",_xll.SNL.Clients.Office.Excel.Functions.SPG($B23,"IQ_TOTAL_EQUITY","FQ0",$F$2,"Options:Curr="&$F$3&", Mag=Millions, NA=--"))} | AZ23: {=IF($B23="","",_xll.SNL.Clients.Office.Excel.Functions.SPG($B23,"IQ_TOTAL_DEBT","FQ0",$F$2,"Options:Curr="&$F$3&", Mag=Millions, NA=--"))} | BA23: {=IF($B23="","",_xll.SNL.Clients.Office.Excel.Functions.SPG($B23,"IQ_CASH_ST_INVEST","FQ0",$F$2,"Options:Curr="&$F$3&", Mag=Millions, NA=--"))} | BB23: =+AZ23-BA23 -> #VALUE! | BC23: {=IF($B23="","",_xll.SNL.Clients.Office.Excel.Functions.SPG($B23,"IQ_TOTAL_EQUITY","FQ0",$F$2,"Options:Curr="&$F$3&", Mag=Millions, NA=--"))} | BE23: =IF($B23="","",IFERROR(_xll.SNL.Clients.Office.Excel.Functions.SPG($B23,"SP_GROSS_MARGIN",BE$7,$F$2,"Options: NA=--")/100,"--")) | BF23: =IF($B23="","",IFERROR(_xll.SNL.Clients.Office.Excel.Functions.SPG($B23,"SP_GROSS_MARGIN_EST",BF$7,$F$2,"Options: NA=--")/100,"--")) | BG23: =IF($B23="","",IFERROR(_xll.SNL.Clients.Office.Excel.Functions.SPG($B23,"SP_GROSS_MARGIN_EST",BG$7,$F$2,"Options: NA=--")/100,"--")) | BH23: =IF($B23="","",IFERROR(_xll.SNL.Clients.Office.Excel.Functions.SPG($B23,"SP_GROSS_MARGIN_EST",BH$7,$F$2,"Options: NA=--")/100,"--"))
D24: {=IF($B24="","",_xll.SNL.Clients.Office.Excel.Functions.SPG($B24, "SP_COMPANY_NAME"))} | G24: {=IF($B24="","",_xll.SNL.Clients.Office.Excel.Functions.SPG($B24,"SP_LASTSALEPRICE",WORKDAY($F$2+1,-1),"Options:Curr="&I24&",NA=--"))} | H24: {=IF($B24="","",_xll.SNL.Clients.Office.Excel.Functions.SPG($B24,"SP_PRICE_CLOSE",WORKDAY($F$2+1,-1),"Options:Curr="&$F$3&", NA=--"))} | I24: {=IF($B24="","",_xll.SNL.Clients.Office.Excel.Functions.SPG($B24,"SP_TRADING_CURRENCY","Options: NA=--"))} | J24: {=IF($B24="","n/a ",_xll.SNL.Clients.Office.Excel.Functions.SPG($B24,"SP_MARKETCAP",WORKDAY($F$2+1,-1),"Options:Curr="&$F$3&", Mag=Millions, NA=--"))} -> n/a | K24: {=IF($B24="","n/a ",_xll.SNL.Clients.Office.Excel.Functions.SPG($B24,"IQ_TEV",WORKDAY($F$2+1,-1),"Options:Curr="&$F$3&", Mag=Millions, NA=--"))} -> n/a | L24: =IFERROR(IF(OR($K24/AC24>L$4,$K24/AC24<L$3),"nmf ",$K24/AC24),"n/a ") -> n/a | M24: =IFERROR(IF(OR($K24/AD24>M$4,$K24/AD24<M$3),"nmf ",$K24/AD24),"n/a ") -> n/a | N24: =IFERROR(IF(OR($K24/AE24>N$4,$K24/AE24<N$3),"nmf ",$K24/AE24),"n/a ") -> n/a | O24: =IFERROR(IF(OR($K24/AH24>O$4,$K24/AH24<O$3),"nmf ",$K24/AH24),"n/a ") -> n/a | P24: =IFERROR(IF(OR($K24/AI24>P$4,$K24/AI24<P$3),"nmf ",$K24/AI24),"n/a ") -> n/a | Q24: =IFERROR(IF(OR($K24/AJ24>Q$4,$K24/AJ24<Q$3),"nmf ",$K24/AJ24),"n/a ") -> n/a | R24: =IFERROR((AE24/AD24)-1,"n/a ") -> n/a | S24: =IFERROR((AF24/AE24)-1,"n/a ") -> n/a | U24: =IFERROR($H24/AM24,"n/a ") -> n/a | V24: =IFERROR($H24/AO24,"n/a ") -> n/a | W24: =IFERROR($H24/AP24,"n/a ") -> n/a | X24: =IFERROR(AR24/100,"n/a ") -> n/a | Y24: =IFERROR(H24/AT24,"n/a ") -> n/a | Z24: =IFERROR(H24/AV24,"n/a ") -> n/a | AC24: {=IF($B24="","",_xll.SNL.Clients.Office.Excel.Functions.SPG($B24,"IQ_REV",AC$7,$F$2,"Options:Curr="&$F$3&", Mag=Millions, NA=--"))} | AD24: {=IF($B24="","",_xll.SNL.Clients.Office.Excel.Functions.SPG($B24,"SP_REV_EST",AD$7,$F$2,"Options:Curr="&$F$3&", Mag=Millions, NA=--"))} | AE24: {=IF($B24="","",_xll.SNL.Clients.Office.Excel.Functions.SPG($B24,"SP_REV_EST",AE$7,$F$2,"Options:Curr="&$F$3&", Mag=Millions, NA=--"))} | AF24: {=IF($B24="","",_xll.SNL.Clients.Office.Excel.Functions.SPG($B24,"SP_REV_EST",AF$7,$F$2,"Options:Curr="&$F$3&", Mag=Millions, NA=--"))} | AH24: {=IF($B24="","",_xll.SNL.Clients.Office.Excel.Functions.SPG($B24,"SP_EBITDA",AH$7,$F$2,"Options:Curr="&$F$3&", Mag=Millions, NA=--"))} | AI24: {=IF($B24="","",_xll.SNL.Clients.Office.Excel.Functions.SPG($B24,"SP_EBITDA_EST",AI$7,$F$2,"Options:Curr="&$F$3&", Mag=Millions, NA=--"))} | AJ24: {=IF($B24="","",_xll.SNL.Clients.Office.Excel.Functions.SPG($B24,"SP_EBITDA_EST",AJ$7,$F$2,"Options:Curr="&$F$3&", Mag=Millions, NA=--"))} | AK24: {=IF($B24="","",_xll.SNL.Clients.Office.Excel.Functions.SPG($B24,"SP_EBITDA_EST",AK$7,$F$2,"Options:Curr="&$F$3&", Mag=Millions, NA=--"))} | AM24: {=IF($B24="","",_xll.SNL.Clients.Office.Excel.Functions.SPG($B24,"IQ_BASIC_EPS_BEFORE_EXTRA",AM$7,$F$2,"Options:Curr="&$F$3&", NA=--"))} | AN24: {=IF($B24="","",_xll.SNL.Clients.Office.Excel.Functions.SPG($B24,"SP_EPS_EST",AN$7,$F$2,"Options:Curr="&$F$3&", NA=--"))} | AO24: {=IF($B24="","",_xll.SNL.Clients.Office.Excel.Functions.SPG($B24,"SP_EPS_EST",AO$7,$F$2,"Options:Curr="&$F$3&", NA=--"))} | AP24: {=IF($B24="","",_xll.SNL.Clients.Office.Excel.Functions.SPG($B24,"SP_EPS_EST",AP$7,$F$2,"Options:Curr="&$F$3&", NA=--"))} | AR24: {=IF($B24="","",_xll.SNL.Clients.Office.Excel.Functions.SPG($B24,"IQ_ROE",AR$7,$F$2,"Options:Curr="&$F$3&", NA=--"))} | AT24: {=IF($B24="","",_xll.SNL.Clients.Office.Excel.Functions.SPG($B24,"IQ_BVPS",AT$7,$F$2,"Options:Curr="&$F$3&", NA=--"))} | AV24: {=IF($B24="","",_xll.SNL.Clients.Office.Excel.Functions.SPG($B24,"IQ_TBVPS",AV$7,$F$2,"Options:Curr="&$F$3&", NA=--"))} | AX24: {=IF($B24="","",_xll.SNL.Clients.Office.Excel.Functions.SPG($B24,"SP_DIV_YIELD",WORKDAY($F$2+1,-1),"Options: NA=--"))} | AY24: {=IF($B24="","",_xll.SNL.Clients.Office.Excel.Functions.SPG($B24,"IQ_TOTAL_EQUITY","FQ0",$F$2,"Options:Curr="&$F$3&", Mag=Millions, NA=--"))} | AZ24: {=IF($B24="","",_xll.SNL.Clients.Office.Excel.Functions.SPG($B24,"IQ_TOTAL_DEBT","FQ0",$F$2,"Options:Curr="&$F$3&", Mag=Millions, NA=--"))} | BA24: {=IF($B24="","",_xll.SNL.Clients.Office.Excel.Functions.SPG($B24,"IQ_CASH_ST_INVEST","FQ0",$F$2,"Options:Curr="&$F$3&", Mag=Millions, NA=--"))} | BB24: =+AZ24-BA24 -> #VALUE! | BC24: {=IF($B24="","",_xll.SNL.Clients.Office.Excel.Functions.SPG($B24,"IQ_TOTAL_EQUITY","FQ0",$F$2,"Options:Curr="&$F$3&", Mag=Millions, NA=--"))} | BE24: =IF($B24="","",IFERROR(_xll.SNL.Clients.Office.Excel.Functions.SPG($B24,"SP_GROSS_MARGIN",BE$7,$F$2,"Options: NA=--")/100,"--")) | BF24: =IF($B24="","",IFERROR(_xll.SNL.Clients.Office.Excel.Functions.SPG($B24,"SP_GROSS_MARGIN_EST",BF$7,$F$2,"Options: NA=--")/100,"--")) | BG24: =IF($B24="","",IFERROR(_xll.SNL.Clients.Office.Excel.Functions.SPG($B24,"SP_GROSS_MARGIN_EST",BG$7,$F$2,"Options: NA=--")/100,"--")) | BH24: =IF($B24="","",IFERROR(_xll.SNL.Clients.Office.Excel.Functions.SPG($B24,"SP_GROSS_MARGIN_EST",BH$7,$F$2,"Options: NA=--")/100,"--"))
D25: {=IF($B25="","",_xll.SNL.Clients.Office.Excel.Functions.SPG($B25, "SP_COMPANY_NAME"))} | G25: {=IF($B25="","",_xll.SNL.Clients.Office.Excel.Functions.SPG($B25,"SP_LASTSALEPRICE",WORKDAY($F$2+1,-1),"Options:Curr="&I25&",NA=--"))} | H25: {=IF($B25="","",_xll.SNL.Clients.Office.Excel.Functions.SPG($B25,"SP_PRICE_CLOSE",WORKDAY($F$2+1,-1),"Options:Curr="&$F$3&", NA=--"))} | I25: {=IF($B25="","",_xll.SNL.Clients.Office.Excel.Functions.SPG($B25,"SP_TRADING_CURRENCY","Options: NA=--"))} | J25: {=IF($B25="","n/a ",_xll.SNL.Clients.Office.Excel.Functions.SPG($B25,"SP_MARKETCAP",WORKDAY($F$2+1,-1),"Options:Curr="&$F$3&", Mag=Millions, NA=--"))} -> n/a | K25: {=IF($B25="","n/a ",_xll.SNL.Clients.Office.Excel.Functions.SPG($B25,"IQ_TEV",WORKDAY($F$2+1,-1),"Options:Curr="&$F$3&", Mag=Millions, NA=--"))} -> n/a | L25: =IFERROR(IF(OR($K25/AC25>L$4,$K25/AC25<L$3),"nmf ",$K25/AC25),"n/a ") -> n/a | M25: =IFERROR(IF(OR($K25/AD25>M$4,$K25/AD25<M$3),"nmf ",$K25/AD25),"n/a ") -> n/a | N25: =IFERROR(IF(OR($K25/AE25>N$4,$K25/AE25<N$3),"nmf ",$K25/AE25),"n/a ") -> n/a | O25: =IFERROR(IF(OR($K25/AH25>O$4,$K25/AH25<O$3),"nmf ",$K25/AH25),"n/a ") -> n/a | P25: =IFERROR(IF(OR($K25/AI25>P$4,$K25/AI25<P$3),"nmf ",$K25/AI25),"n/a ") -> n/a | Q25: =IFERROR(IF(OR($K25/AJ25>Q$4,$K25/AJ25<Q$3),"nmf ",$K25/AJ25),"n/a ") -> n/a | R25: =IFERROR((AE25/AD25)-1,"n/a ") -> n/a | S25: =IFERROR((AF25/AE25)-1,"n/a ") -> n/a | U25: =IFERROR($H25/AM25,"n/a ") -> n/a | V25: =IFERROR($H25/AO25,"n/a ") -> n/a | W25: =IFERROR($H25/AP25,"n/a ") -> n/a | X25: =IFERROR(AR25/100,"n/a ") -> n/a | Y25: =IFERROR(H25/AT25,"n/a ") -> n/a | Z25: =IFERROR(H25/AV25,"n/a ") -> n/a | AC25: {=IF($B25="","",_xll.SNL.Clients.Office.Excel.Functions.SPG($B25,"IQ_REV",AC$7,$F$2,"Options:Curr="&$F$3&", Mag=Millions, NA=--"))} | AD25: {=IF($B25="","",_xll.SNL.Clients.Office.Excel.Functions.SPG($B25,"SP_REV_EST",AD$7,$F$2,"Options:Curr="&$F$3&", Mag=Millions, NA=--"))} | AE25: {=IF($B25="","",_xll.SNL.Clients.Office.Excel.Functions.SPG($B25,"SP_REV_EST",AE$7,$F$2,"Options:Curr="&$F$3&", Mag=Millions, NA=--"))} | AF25: {=IF($B25="","",_xll.SNL.Clients.Office.Excel.Functions.SPG($B25,"SP_REV_EST",AF$7,$F$2,"Options:Curr="&$F$3&", Mag=Millions, NA=--"))} | AH25: {=IF($B25="","",_xll.SNL.Clients.Office.Excel.Functions.SPG($B25,"SP_EBITDA",AH$7,$F$2,"Options:Curr="&$F$3&", Mag=Millions, NA=--"))} | AI25: {=IF($B25="","",_xll.SNL.Clients.Office.Excel.Functions.SPG($B25,"SP_EBITDA_EST",AI$7,$F$2,"Options:Curr="&$F$3&", Mag=Millions, NA=--"))} | AJ25: {=IF($B25="","",_xll.SNL.Clients.Office.Excel.Functions.SPG($B25,"SP_EBITDA_EST",AJ$7,$F$2,"Options:Curr="&$F$3&", Mag=Millions, NA=--"))} | AK25: {=IF($B25="","",_xll.SNL.Clients.Office.Excel.Functions.SPG($B25,"SP_EBITDA_EST",AK$7,$F$2,"Options:Curr="&$F$3&", Mag=Millions, NA=--"))} | AM25: {=IF($B25="","",_xll.SNL.Clients.Office.Excel.Functions.SPG($B25,"IQ_BASIC_EPS_BEFORE_EXTRA",AM$7,$F$2,"Options:Curr="&$F$3&", NA=--"))} | AN25: {=IF($B25="","",_xll.SNL.Clients.Office.Excel.Functions.SPG($B25,"SP_EPS_EST",AN$7,$F$2,"Options:Curr="&$F$3&", NA=--"))} | AO25: {=IF($B25="","",_xll.SNL.Clients.Office.Excel.Functions.SPG($B25,"SP_EPS_EST",AO$7,$F$2,"Options:Curr="&$F$3&", NA=--"))} | AP25: {=IF($B25="","",_xll.SNL.Clients.Office.Excel.Functions.SPG($B25,"SP_EPS_EST",AP$7,$F$2,"Options:Curr="&$F$3&", NA=--"))} | AR25: {=IF($B25="","",_xll.SNL.Clients.Office.Excel.Functions.SPG($B25,"IQ_ROE",AR$7,$F$2,"Options:Curr="&$F$3&", NA=--"))} | AT25: {=IF($B25="","",_xll.SNL.Clients.Office.Excel.Functions.SPG($B25,"IQ_BVPS",AT$7,$F$2,"Options:Curr="&$F$3&", NA=--"))} | AV25: {=IF($B25="","",_xll.SNL.Clients.Office.Excel.Functions.SPG($B25,"IQ_TBVPS",AV$7,$F$2,"Options:Curr="&$F$3&", NA=--"))} | AX25: {=IF($B25="","",_xll.SNL.Clients.Office.Excel.Functions.SPG($B25,"SP_DIV_YIELD",WORKDAY($F$2+1,-1),"Options: NA=--"))} | AY25: {=IF($B25="","",_xll.SNL.Clients.Office.Excel.Functions.SPG($B25,"IQ_TOTAL_EQUITY","FQ0",$F$2,"Options:Curr="&$F$3&", Mag=Millions, NA=--"))} | AZ25: {=IF($B25="","",_xll.SNL.Clients.Office.Excel.Functions.SPG($B25,"IQ_TOTAL_DEBT","FQ0",$F$2,"Options:Curr="&$F$3&", Mag=Millions, NA=--"))} | BA25: {=IF($B25="","",_xll.SNL.Clients.Office.Excel.Functions.SPG($B25,"IQ_CASH_ST_INVEST","FQ0",$F$2,"Options:Curr="&$F$3&", Mag=Millions, NA=--"))} | BB25: =+AZ25-BA25 -> #VALUE! | BC25: {=IF($B25="","",_xll.SNL.Clients.Office.Excel.Functions.SPG($B25,"IQ_TOTAL_EQUITY","FQ0",$F$2,"Options:Curr="&$F$3&", Mag=Millions, NA=--"))} | BE25: =IF($B25="","",IFERROR(_xll.SNL.Clients.Office.Excel.Functions.SPG($B25,"SP_GROSS_MARGIN",BE$7,$F$2,"Options: NA=--")/100,"--")) | BF25: =IF($B25="","",IFERROR(_xll.SNL.Clients.Office.Excel.Functions.SPG($B25,"SP_GROSS_MARGIN_EST",BF$7,$F$2,"Options: NA=--")/100,"--")) | BG25: =IF($B25="","",IFERROR(_xll.SNL.Clients.Office.Excel.Functions.SPG($B25,"SP_GROSS_MARGIN_EST",BG$7,$F$2,"Options: NA=--")/100,"--")) | BH25: =IF($B25="","",IFERROR(_xll.SNL.Clients.Office.Excel.Functions.SPG($B25,"SP_GROSS_MARGIN_EST",BH$7,$F$2,"Options: NA=--")/100,"--"))
D27: Group Average | L27: =IFERROR(AVERAGE(L20:L25),"n/a ") -> n/a | M27: =IFERROR(AVERAGE(M20:M25),"n/a ") -> n/a | N27: =IFERROR(AVERAGE(N20:N25),"n/a ") -> n/a | O27: =IFERROR(AVERAGE(O20:O25),"n/a ") -> n/a | P27: =IFERROR(AVERAGE(P20:P25),"n/a ") -> n/a | Q27: =IFERROR(AVERAGE(Q20:Q25),"n/a ") -> n/a | R27: =IFERROR(AVERAGE(R20:R25),"n/a ") -> n/a | S27: =IFERROR(AVERAGE(S20:S25),"n/a ") -> n/a | U27: =IFERROR(AVERAGE(U20:U25),"n/a ") -> n/a | V27: =IFERROR(AVERAGE(V20:V25),"n/a ") -> n/a | W27: =IFERROR(AVERAGE(W20:W25),"n/a ") -> n/a | X27: =IFERROR(AVERAGE(X20:X25),"n/a ") -> n/a | Y27: =IFERROR(AVERAGE(Y20:Y25),"n/a ") -> n/a | Z27: =IFERROR(AVERAGE(Z20:Z25),"n/a ") -> n/a
D29: [Group #3]
D30: {=IF($B30="","",_xll.SNL.Clients.Office.Excel.Functions.SPG($B30, "SP_COMPANY_NAME"))} | G30: {=IF($B30="","",_xll.SNL.Clients.Office.Excel.Functions.SPG($B30,"SP_LASTSALEPRICE",WORKDAY($F$2+1,-1),"Options:Curr="&I30&",NA=--"))} | H30: {=IF($B30="","",_xll.SNL.Clients.Office.Excel.Functions.SPG($B30,"SP_PRICE_CLOSE",WORKDAY($F$2+1,-1),"Options:Curr="&$F$3&", NA=--"))} | I30: {=IF($B30="","",_xll.SNL.Clients.Office.Excel.Functions.SPG($B30,"SP_TRADING_CURRENCY","Options: NA=--"))} | J30: {=IF($B30="","n/a ",_xll.SNL.Clients.Office.Excel.Functions.SPG($B30,"SP_MARKETCAP",WORKDAY($F$2+1,-1),"Options:Curr="&$F$3&", Mag=Millions, NA=--"))} -> n/a | K30: {=IF($B30="","n/a ",_xll.SNL.Clients.Office.Excel.Functions.SPG($B30,"IQ_TEV",WORKDAY($F$2+1,-1),"Options:Curr="&$F$3&", Mag=Millions, NA=--"))} -> n/a | L30: =IFERROR(IF(OR($K30/AC30>L$4,$K30/AC30<L$3),"nmf ",$K30/AC30),"n/a ") -> n/a | M30: =IFERROR(IF(OR($K30/AD30>M$4,$K30/AD30<M$3),"nmf ",$K30/AD30),"n/a ") -> n/a | N30: =IFERROR(IF(OR($K30/AE30>N$4,$K30/AE30<N$3),"nmf ",$K30/AE30),"n/a ") -> n/a | O30: =IFERROR(IF(OR($K30/AH30>O$4,$K30/AH30<O$3),"nmf ",$K30/AH30),"n/a ") -> n/a | P30: =IFERROR(IF(OR($K30/AI30>P$4,$K30/AI30<P$3),"nmf ",$K30/AI30),"n/a ") -> n/a | Q30: =IFERROR(IF(OR($K30/AJ30>Q$4,$K30/AJ30<Q$3),"nmf ",$K30/AJ30),"n/a ") -> n/a | R30: =IFERROR((AE30/AD30)-1,"n/a ") -> n/a | S30: =IFERROR((AF30/AE30)-1,"n/a ") -> n/a | U30: =IFERROR($H30/AM30,"n/a ") -> n/a | V30: =IFERROR($H30/AO30,"n/a ") -> n/a | W30: =IFERROR($H30/AP30,"n/a ") -> n/a | X30: =IFERROR(AR30/100,"n/a ") -> n/a | Y30: =IFERROR(H30/AT30,"n/a ") -> n/a | Z30: =IFERROR(H30/AV30,"n/a ") -> n/a | AC30: {=IF($B30="","",_xll.SNL.Clients.Office.Excel.Functions.SPG($B30,"IQ_REV",AC$7,$F$2,"Options:Curr="&$F$3&", Mag=Millions, NA=--"))} | AD30: {=IF($B30="","",_xll.SNL.Clients.Office.Excel.Functions.SPG($B30,"SP_REV_EST",AD$7,$F$2,"Options:Curr="&$F$3&", Mag=Millions, NA=--"))} | AE30: {=IF($B30="","",_xll.SNL.Clients.Office.Excel.Functions.SPG($B30,"SP_REV_EST",AE$7,$F$2,"Options:Curr="&$F$3&", Mag=Millions, NA=--"))} | AF30: {=IF($B30="","",_xll.SNL.Clients.Office.Excel.Functions.SPG($B30,"SP_REV_EST",AF$7,$F$2,"Options:Curr="&$F$3&", Mag=Millions, NA=--"))} | AH30: {=IF($B30="","",_xll.SNL.Clients.Office.Excel.Functions.SPG($B30,"SP_EBITDA",AH$7,$F$2,"Options:Curr="&$F$3&", Mag=Millions, NA=--"))} | AI30: {=IF($B30="","",_xll.SNL.Clients.Office.Excel.Functions.SPG($B30,"SP_EBITDA_EST",AI$7,$F$2,"Options:Curr="&$F$3&", Mag=Millions, NA=--"))} | AJ30: {=IF($B30="","",_xll.SNL.Clients.Office.Excel.Functions.SPG($B30,"SP_EBITDA_EST",AJ$7,$F$2,"Options:Curr="&$F$3&", Mag=Millions, NA=--"))} | AK30: {=IF($B30="","",_xll.SNL.Clients.Office.Excel.Functions.SPG($B30,"SP_EBITDA_EST",AK$7,$F$2,"Options:Curr="&$F$3&", Mag=Millions, NA=--"))} | AM30: {=IF($B30="","",_xll.SNL.Clients.Office.Excel.Functions.SPG($B30,"IQ_BASIC_EPS_BEFORE_EXTRA",AM$7,$F$2,"Options:Curr="&$F$3&", NA=--"))} | AN30: {=IF($B30="","",_xll.SNL.Clients.Office.Excel.Functions.SPG($B30,"SP_EPS_EST",AN$7,$F$2,"Options:Curr="&$F$3&", NA=--"))} | AO30: {=IF($B30="","",_xll.SNL.Clients.Office.Excel.Functions.SPG($B30,"SP_EPS_EST",AO$7,$F$2,"Options:Curr="&$F$3&", NA=--"))} | AP30: {=IF($B30="","",_xll.SNL.Clients.Office.Excel.Functions.SPG($B30,"SP_EPS_EST",AP$7,$F$2,"Options:Curr="&$F$3&", NA=--"))} | AR30: {=IF($B30="","",_xll.SNL.Clients.Office.Excel.Functions.SPG($B30,"IQ_ROE",AR$7,$F$2,"Options:Curr="&$F$3&", NA=--"))} | AT30: {=IF($B30="","",_xll.SNL.Clients.Office.Excel.Functions.SPG($B30,"IQ_BVPS",AT$7,$F$2,"Options:Curr="&$F$3&", NA=--"))} | AV30: {=IF($B30="","",_xll.SNL.Clients.Office.Excel.Functions.SPG($B30,"IQ_TBVPS",AV$7,$F$2,"Options:Curr="&$F$3&", NA=--"))} | AX30: {=IF($B30="","",_xll.SNL.Clients.Office.Excel.Functions.SPG($B30,"SP_DIV_YIELD",WORKDAY($F$2+1,-1),"Options: NA=--"))} | AY30: {=IF($B30="","",_xll.SNL.Clients.Office.Excel.Functions.SPG($B30,"IQ_TOTAL_EQUITY","FQ0",$F$2,"Options:Curr="&$F$3&", Mag=Millions, NA=--"))} | AZ30: {=IF($B30="","",_xll.SNL.Clients.Office.Excel.Functions.SPG($B30,"IQ_TOTAL_DEBT","FQ0",$F$2,"Options:Curr="&$F$3&", Mag=Millions, NA=--"))} | BA30: {=IF($B30="","",_xll.SNL.Clients.Office.Excel.Functions.SPG($B30,"IQ_CASH_ST_INVEST","FQ0",$F$2,"Options:Curr="&$F$3&", Mag=Millions, NA=--"))} | BB30: =+AZ30-BA30 -> #VALUE! | BC30: {=IF($B30="","",_xll.SNL.Clients.Office.Excel.Functions.SPG($B30,"IQ_TOTAL_EQUITY","FQ0",$F$2,"Options:Curr="&$F$3&", Mag=Millions, NA=--"))} | BE30: =IF($B30="","",IFERROR(_xll.SNL.Clients.Office.Excel.Functions.SPG($B30,"SP_GROSS_MARGIN",BE$7,$F$2,"Options: NA=--")/100,"--")) | BF30: =IF($B30="","",IFERROR(_xll.SNL.Clients.Office.Excel.Functions.SPG($B30,"SP_GROSS_MARGIN_EST",BF$7,$F$2,"Options: NA=--")/100,"--")) | BG30: =IF($B30="","",IFERROR(_xll.SNL.Clients.Office.Excel.Functions.SPG($B30,"SP_GROSS_MARGIN_EST",BG$7,$F$2,"Options: NA=--")/100,"--")) | BH30: =IF($B30="","",IFERROR(_xll.SNL.Clients.Office.Excel.Functions.SPG($B30,"SP_GROSS_MARGIN_EST",BH$7,$F$2,"Options: NA=--")/100,"--"))
D31: {=IF($B31="","",_xll.SNL.Clients.Office.Excel.Functions.SPG($B31, "SP_COMPANY_NAME"))} | G31: {=IF($B31="","",_xll.SNL.Clients.Office.Excel.Functions.SPG($B31,"SP_LASTSALEPRICE",WORKDAY($F$2+1,-1),"Options:Curr="&I31&",NA=--"))} | H31: {=IF($B31="","",_xll.SNL.Clients.Office.Excel.Functions.SPG($B31,"SP_PRICE_CLOSE",WORKDAY($F$2+1,-1),"Options:Curr="&$F$3&", NA=--"))} | I31: {=IF($B31="","",_xll.SNL.Clients.Office.Excel.Functions.SPG($B31,"SP_TRADING_CURRENCY","Options: NA=--"))} | J31: {=IF($B31="","n/a ",_xll.SNL.Clients.Office.Excel.Functions.SPG($B31,"SP_MARKETCAP",WORKDAY($F$2+1,-1),"Options:Curr="&$F$3&", Mag=Millions, NA=--"))} -> n/a | K31: {=IF($B31="","n/a ",_xll.SNL.Clients.Office.Excel.Functions.SPG($B31,"IQ_TEV",WORKDAY($F$2+1,-1),"Options:Curr="&$F$3&", Mag=Millions, NA=--"))} -> n/a | L31: =IFERROR(IF(OR($K31/AC31>L$4,$K31/AC31<L$3),"nmf ",$K31/AC31),"n/a ") -> n/a | M31: =IFERROR(IF(OR($K31/AD31>M$4,$K31/AD31<M$3),"nmf ",$K31/AD31),"n/a ") -> n/a | N31: =IFERROR(IF(OR($K31/AE31>N$4,$K31/AE31<N$3),"nmf ",$K31/AE31),"n/a ") -> n/a | O31: =IFERROR(IF(OR($K31/AH31>O$4,$K31/AH31<O$3),"nmf ",$K31/AH31),"n/a ") -> n/a | P31: =IFERROR(IF(OR($K31/AI31>P$4,$K31/AI31<P$3),"nmf ",$K31/AI31),"n/a ") -> n/a | Q31: =IFERROR(IF(OR($K31/AJ31>Q$4,$K31/AJ31<Q$3),"nmf ",$K31/AJ31),"n/a ") -> n/a | R31: =IFERROR((AE31/AD31)-1,"n/a ") -> n/a | S31: =IFERROR((AF31/AE31)-1,"n/a ") -> n/a | U31: =IFERROR($H31/AM31,"n/a ") -> n/a | V31: =IFERROR($H31/AO31,"n/a ") -> n/a | W31: =IFERROR($H31/AP31,"n/a ") -> n/a | X31: =IFERROR(AR31/100,"n/a ") -> n/a | Y31: =IFERROR(H31/AT31,"n/a ") -> n/a | Z31: =IFERROR(H31/AV31,"n/a ") -> n/a | AC31: {=IF($B31="","",_xll.SNL.Clients.Office.Excel.Functions.SPG($B31,"IQ_REV",AC$7,$F$2,"Options:Curr="&$F$3&", Mag=Millions, NA=--"))} | AD31: {=IF($B31="","",_xll.SNL.Clients.Office.Excel.Functions.SPG($B31,"SP_REV_EST",AD$7,$F$2,"Options:Curr="&$F$3&", Mag=Millions, NA=--"))} | AE31: {=IF($B31="","",_xll.SNL.Clients.Office.Excel.Functions.SPG($B31,"SP_REV_EST",AE$7,$F$2,"Options:Curr="&$F$3&", Mag=Millions, NA=--"))} | AF31: {=IF($B31="","",_xll.SNL.Clients.Office.Excel.Functions.SPG($B31,"SP_REV_EST",AF$7,$F$2,"Options:Curr="&$F$3&", Mag=Millions, NA=--"))} | AH31: {=IF($B31="","",_xll.SNL.Clients.Office.Excel.Functions.SPG($B31,"SP_EBITDA",AH$7,$F$2,"Options:Curr="&$F$3&", Mag=Millions, NA=--"))} | AI31: {=IF($B31="","",_xll.SNL.Clients.Office.Excel.Functions.SPG($B31,"SP_EBITDA_EST",AI$7,$F$2,"Options:Curr="&$F$3&", Mag=Millions, NA=--"))} | AJ31: {=IF($B31="","",_xll.SNL.Clients.Office.Excel.Functions.SPG($B31,"SP_EBITDA_EST",AJ$7,$F$2,"Options:Curr="&$F$3&", Mag=Millions, NA=--"))} | AK31: {=IF($B31="","",_xll.SNL.Clients.Office.Excel.Functions.SPG($B31,"SP_EBITDA_EST",AK$7,$F$2,"Options:Curr="&$F$3&", Mag=Millions, NA=--"))} | AM31: {=IF($B31="","",_xll.SNL.Clients.Office.Excel.Functions.SPG($B31,"IQ_BASIC_EPS_BEFORE_EXTRA",AM$7,$F$2,"Options:Curr="&$F$3&", NA=--"))} | AN31: {=IF($B31="","",_xll.SNL.Clients.Office.Excel.Functions.SPG($B31,"SP_EPS_EST",AN$7,$F$2,"Options:Curr="&$F$3&", NA=--"))} | AO31: {=IF($B31="","",_xll.SNL.Clients.Office.Excel.Functions.SPG($B31,"SP_EPS_EST",AO$7,$F$2,"Options:Curr="&$F$3&", NA=--"))} | AP31: {=IF($B31="","",_xll.SNL.Clients.Office.Excel.Functions.SPG($B31,"SP_EPS_EST",AP$7,$F$2,"Options:Curr="&$F$3&", NA=--"))} | AR31: {=IF($B31="","",_xll.SNL.Clients.Office.Excel.Functions.SPG($B31,"IQ_ROE",AR$7,$F$2,"Options:Curr="&$F$3&", NA=--"))} | AT31: {=IF($B31="","",_xll.SNL.Clients.Office.Excel.Functions.SPG($B31,"IQ_BVPS",AT$7,$F$2,"Options:Curr="&$F$3&", NA=--"))} | AV31: {=IF($B31="","",_xll.SNL.Clients.Office.Excel.Functions.SPG($B31,"IQ_TBVPS",AV$7,$F$2,"Options:Curr="&$F$3&", NA=--"))} | AX31: {=IF($B31="","",_xll.SNL.Clients.Office.Excel.Functions.SPG($B31,"SP_DIV_YIELD",WORKDAY($F$2+1,-1),"Options: NA=--"))} | AY31: {=IF($B31="","",_xll.SNL.Clients.Office.Excel.Functions.SPG($B31,"IQ_TOTAL_EQUITY","FQ0",$F$2,"Options:Curr="&$F$3&", Mag=Millions, NA=--"))} | AZ31: {=IF($B31="","",_xll.SNL.Clients.Office.Excel.Functions.SPG($B31,"IQ_TOTAL_DEBT","FQ0",$F$2,"Options:Curr="&$F$3&", Mag=Millions, NA=--"))} | BA31: {=IF($B31="","",_xll.SNL.Clients.Office.Excel.Functions.SPG($B31,"IQ_CASH_ST_INVEST","FQ0",$F$2,"Options:Curr="&$F$3&", Mag=Millions, NA=--"))} | BB31: =+AZ31-BA31 -> #VALUE! | BC31: {=IF($B31="","",_xll.SNL.Clients.Office.Excel.Functions.SPG($B31,"IQ_TOTAL_EQUITY","FQ0",$F$2,"Options:Curr="&$F$3&", Mag=Millions, NA=--"))} | BE31: =IF($B31="","",IFERROR(_xll.SNL.Clients.Office.Excel.Functions.SPG($B31,"SP_GROSS_MARGIN",BE$7,$F$2,"Options: NA=--")/100,"--")) | BF31: =IF($B31="","",IFERROR(_xll.SNL.Clients.Office.Excel.Functions.SPG($B31,"SP_GROSS_MARGIN_EST",BF$7,$F$2,"Options: NA=--")/100,"--")) | BG31: =IF($B31="","",IFERROR(_xll.SNL.Clients.Office.Excel.Functions.SPG($B31,"SP_GROSS_MARGIN_EST",BG$7,$F$2,"Options: NA=--")/100,"--")) | BH31: =IF($B31="","",IFERROR(_xll.SNL.Clients.Office.Excel.Functions.SPG($B31,"SP_GROSS_MARGIN_EST",BH$7,$F$2,"Options: NA=--")/100,"--"))
D32: {=IF($B32="","",_xll.SNL.Clients.Office.Excel.Functions.SPG($B32, "SP_COMPANY_NAME"))} | G32: {=IF($B32="","",_xll.SNL.Clients.Office.Excel.Functions.SPG($B32,"SP_LASTSALEPRICE",WORKDAY($F$2+1,-1),"Options:Curr="&I32&",NA=--"))} | H32: {=IF($B32="","",_xll.SNL.Clients.Office.Excel.Functions.SPG($B32,"SP_PRICE_CLOSE",WORKDAY($F$2+1,-1),"Options:Curr="&$F$3&", NA=--"))} | I32: {=IF($B32="","",_xll.SNL.Clients.Office.Excel.Functions.SPG($B32,"SP_TRADING_CURRENCY","Options: NA=--"))} | J32: {=IF($B32="","n/a ",_xll.SNL.Clients.Office.Excel.Functions.SPG($B32,"SP_MARKETCAP",WORKDAY($F$2+1,-1),"Options:Curr="&$F$3&", Mag=Millions, NA=--"))} -> n/a | K32: {=IF($B32="","n/a ",_xll.SNL.Clients.Office.Excel.Functions.SPG($B32,"IQ_TEV",WORKDAY($F$2+1,-1),"Options:Curr="&$F$3&", Mag=Millions, NA=--"))} -> n/a | L32: =IFERROR(IF(OR($K32/AC32>L$4,$K32/AC32<L$3),"nmf ",$K32/AC32),"n/a ") -> n/a | M32: =IFERROR(IF(OR($K32/AD32>M$4,$K32/AD32<M$3),"nmf ",$K32/AD32),"n/a ") -> n/a | N32: =IFERROR(IF(OR($K32/AE32>N$4,$K32/AE32<N$3),"nmf ",$K32/AE32),"n/a ") -> n/a | O32: =IFERROR(IF(OR($K32/AH32>O$4,$K32/AH32<O$3),"nmf ",$K32/AH32),"n/a ") -> n/a | P32: =IFERROR(IF(OR($K32/AI32>P$4,$K32/AI32<P$3),"nmf ",$K32/AI32),"n/a ") -> n/a | Q32: =IFERROR(IF(OR($K32/AJ32>Q$4,$K32/AJ32<Q$3),"nmf ",$K32/AJ32),"n/a ") -> n/a | R32: =IFERROR((AE32/AD32)-1,"n/a ") -> n/a | S32: =IFERROR((AF32/AE32)-1,"n/a ") -> n/a | U32: =IFERROR($H32/AM32,"n/a ") -> n/a | V32: =IFERROR($H32/AO32,"n/a ") -> n/a | W32: =IFERROR($H32/AP32,"n/a ") -> n/a | X32: =IFERROR(AR32/100,"n/a ") -> n/a | Y32: =IFERROR(H32/AT32,"n/a ") -> n/a | Z32: =IFERROR(H32/AV32,"n/a ") -> n/a | AC32: {=IF($B32="","",_xll.SNL.Clients.Office.Excel.Functions.SPG($B32,"IQ_REV",AC$7,$F$2,"Options:Curr="&$F$3&", Mag=Millions, NA=--"))} | AD32: {=IF($B32="","",_xll.SNL.Clients.Office.Excel.Functions.SPG($B32,"SP_REV_EST",AD$7,$F$2,"Options:Curr="&$F$3&", Mag=Millions, NA=--"))} | AE32: {=IF($B32="","",_xll.SNL.Clients.Office.Excel.Functions.SPG($B32,"SP_REV_EST",AE$7,$F$2,"Options:Curr="&$F$3&", Mag=Millions, NA=--"))} | AF32: {=IF($B32="","",_xll.SNL.Clients.Office.Excel.Functions.SPG($B32,"SP_REV_EST",AF$7,$F$2,"Options:Curr="&$F$3&", Mag=Millions, NA=--"))} | AH32: {=IF($B32="","",_xll.SNL.Clients.Office.Excel.Functions.SPG($B32,"SP_EBITDA",AH$7,$F$2,"Options:Curr="&$F$3&", Mag=Millions, NA=--"))} | AI32: {=IF($B32="","",_xll.SNL.Clients.Office.Excel.Functions.SPG($B32,"SP_EBITDA_EST",AI$7,$F$2,"Options:Curr="&$F$3&", Mag=Millions, NA=--"))} | AJ32: {=IF($B32="","",_xll.SNL.Clients.Office.Excel.Functions.SPG($B32,"SP_EBITDA_EST",AJ$7,$F$2,"Options:Curr="&$F$3&", Mag=Millions, NA=--"))} | AK32: {=IF($B32="","",_xll.SNL.Clients.Office.Excel.Functions.SPG($B32,"SP_EBITDA_EST",AK$7,$F$2,"Options:Curr="&$F$3&", Mag=Millions, NA=--"))} | AM32: {=IF($B32="","",_xll.SNL.Clients.Office.Excel.Functions.SPG($B32,"IQ_BASIC_EPS_BEFORE_EXTRA",AM$7,$F$2,"Options:Curr="&$F$3&", NA=--"))} | AN32: {=IF($B32="","",_xll.SNL.Clients.Office.Excel.Functions.SPG($B32,"SP_EPS_EST",AN$7,$F$2,"Options:Curr="&$F$3&", NA=--"))} | AO32: {=IF($B32="","",_xll.SNL.Clients.Office.Excel.Functions.SPG($B32,"SP_EPS_EST",AO$7,$F$2,"Options:Curr="&$F$3&", NA=--"))} | AP32: {=IF($B32="","",_xll.SNL.Clients.Office.Excel.Functions.SPG($B32,"SP_EPS_EST",AP$7,$F$2,"Options:Curr="&$F$3&", NA=--"))} | AR32: {=IF($B32="","",_xll.SNL.Clients.Office.Excel.Functions.SPG($B32,"IQ_ROE",AR$7,$F$2,"Options:Curr="&$F$3&", NA=--"))} | AT32: {=IF($B32="","",_xll.SNL.Clients.Office.Excel.Functions.SPG($B32,"IQ_BVPS",AT$7,$F$2,"Options:Curr="&$F$3&", NA=--"))} | AV32: {=IF($B32="","",_xll.SNL.Clients.Office.Excel.Functions.SPG($B32,"IQ_TBVPS",AV$7,$F$2,"Options:Curr="&$F$3&", NA=--"))} | AX32: {=IF($B32="","",_xll.SNL.Clients.Office.Excel.Functions.SPG($B32,"SP_DIV_YIELD",WORKDAY($F$2+1,-1),"Options: NA=--"))} | AY32: {=IF($B32="","",_xll.SNL.Clients.Office.Excel.Functions.SPG($B32,"IQ_TOTAL_EQUITY","FQ0",$F$2,"Options:Curr="&$F$3&", Mag=Millions, NA=--"))} | AZ32: {=IF($B32="","",_xll.SNL.Clients.Office.Excel.Functions.SPG($B32,"IQ_TOTAL_DEBT","FQ0",$F$2,"Options:Curr="&$F$3&", Mag=Millions, NA=--"))} | BA32: {=IF($B32="","",_xll.SNL.Clients.Office.Excel.Functions.SPG($B32,"IQ_CASH_ST_INVEST","FQ0",$F$2,"Options:Curr="&$F$3&", Mag=Millions, NA=--"))} | BB32: =+AZ32-BA32 -> #VALUE! | BC32: {=IF($B32="","",_xll.SNL.Clients.Office.Excel.Functions.SPG($B32,"IQ_TOTAL_EQUITY","FQ0",$F$2,"Options:Curr="&$F$3&", Mag=Millions, NA=--"))} | BE32: =IF($B32="","",IFERROR(_xll.SNL.Clients.Office.Excel.Functions.SPG($B32,"SP_GROSS_MARGIN",BE$7,$F$2,"Options: NA=--")/100,"--")) | BF32: =IF($B32="","",IFERROR(_xll.SNL.Clients.Office.Excel.Functions.SPG($B32,"SP_GROSS_MARGIN_EST",BF$7,$F$2,"Options: NA=--")/100,"--")) | BG32: =IF($B32="","",IFERROR(_xll.SNL.Clients.Office.Excel.Functions.SPG($B32,"SP_GROSS_MARGIN_EST",BG$7,$F$2,"Options: NA=--")/100,"--")) | BH32: =IF($B32="","",IFERROR(_xll.SNL.Clients.Office.Excel.Functions.SPG($B32,"SP_GROSS_MARGIN_EST",BH$7,$F$2,"Options: NA=--")/100,"--"))
D33: {=IF($B33="","",_xll.SNL.Clients.Office.Excel.Functions.SPG($B33, "SP_COMPANY_NAME"))} | G33: {=IF($B33="","",_xll.SNL.Clients.Office.Excel.Functions.SPG($B33,"SP_LASTSALEPRICE",WORKDAY($F$2+1,-1),"Options:Curr="&I33&",NA=--"))} | H33: {=IF($B33="","",_xll.SNL.Clients.Office.Excel.Functions.SPG($B33,"SP_PRICE_CLOSE",WORKDAY($F$2+1,-1),"Options:Curr="&$F$3&", NA=--"))} | I33: {=IF($B33="","",_xll.SNL.Clients.Office.Excel.Functions.SPG($B33,"SP_TRADING_CURRENCY","Options: NA=--"))} | J33: {=IF($B33="","n/a ",_xll.SNL.Clients.Office.Excel.Functions.SPG($B33,"SP_MARKETCAP",WORKDAY($F$2+1,-1),"Options:Curr="&$F$3&", Mag=Millions, NA=--"))} -> n/a | K33: {=IF($B33="","n/a ",_xll.SNL.Clients.Office.Excel.Functions.SPG($B33,"IQ_TEV",WORKDAY($F$2+1,-1),"Options:Curr="&$F$3&", Mag=Millions, NA=--"))} -> n/a | L33: =IFERROR(IF(OR($K33/AC33>L$4,$K33/AC33<L$3),"nmf ",$K33/AC33),"n/a ") -> n/a | M33: =IFERROR(IF(OR($K33/AD33>M$4,$K33/AD33<M$3),"nmf ",$K33/AD33),"n/a ") -> n/a | N33: =IFERROR(IF(OR($K33/AE33>N$4,$K33/AE33<N$3),"nmf ",$K33/AE33),"n/a ") -> n/a | O33: =IFERROR(IF(OR($K33/AH33>O$4,$K33/AH33<O$3),"nmf ",$K33/AH33),"n/a ") -> n/a | P33: =IFERROR(IF(OR($K33/AI33>P$4,$K33/AI33<P$3),"nmf ",$K33/AI33),"n/a ") -> n/a | Q33: =IFERROR(IF(OR($K33/AJ33>Q$4,$K33/AJ33<Q$3),"nmf ",$K33/AJ33),"n/a ") -> n/a | R33: =IFERROR((AE33/AD33)-1,"n/a ") -> n/a | S33: =IFERROR((AF33/AE33)-1,"n/a ") -> n/a | U33: =IFERROR($H33/AM33,"n/a ") -> n/a | V33: =IFERROR($H33/AO33,"n/a ") -> n/a | W33: =IFERROR($H33/AP33,"n/a ") -> n/a | X33: =IFERROR(AR33/100,"n/a ") -> n/a | Y33: =IFERROR(H33/AT33,"n/a ") -> n/a | Z33: =IFERROR(H33/AV33,"n/a ") -> n/a | AC33: {=IF($B33="","",_xll.SNL.Clients.Office.Excel.Functions.SPG($B33,"IQ_REV",AC$7,$F$2,"Options:Curr="&$F$3&", Mag=Millions, NA=--"))} | AD33: {=IF($B33="","",_xll.SNL.Clients.Office.Excel.Functions.SPG($B33,"SP_REV_EST",AD$7,$F$2,"Options:Curr="&$F$3&", Mag=Millions, NA=--"))} | AE33: {=IF($B33="","",_xll.SNL.Clients.Office.Excel.Functions.SPG($B33,"SP_REV_EST",AE$7,$F$2,"Options:Curr="&$F$3&", Mag=Millions, NA=--"))} | AF33: {=IF($B33="","",_xll.SNL.Clients.Office.Excel.Functions.SPG($B33,"SP_REV_EST",AF$7,$F$2,"Options:Curr="&$F$3&", Mag=Millions, NA=--"))} | AH33: {=IF($B33="","",_xll.SNL.Clients.Office.Excel.Functions.SPG($B33,"SP_EBITDA",AH$7,$F$2,"Options:Curr="&$F$3&", Mag=Millions, NA=--"))} | AI33: {=IF($B33="","",_xll.SNL.Clients.Office.Excel.Functions.SPG($B33,"SP_EBITDA_EST",AI$7,$F$2,"Options:Curr="&$F$3&", Mag=Millions, NA=--"))} | AJ33: {=IF($B33="","",_xll.SNL.Clients.Office.Excel.Functions.SPG($B33,"SP_EBITDA_EST",AJ$7,$F$2,"Options:Curr="&$F$3&", Mag=Millions, NA=--"))} | AK33: {=IF($B33="","",_xll.SNL.Clients.Office.Excel.Functions.SPG($B33,"SP_EBITDA_EST",AK$7,$F$2,"Options:Curr="&$F$3&", Mag=Millions, NA=--"))} | AM33: {=IF($B33="","",_xll.SNL.Clients.Office.Excel.Functions.SPG($B33,"IQ_BASIC_EPS_BEFORE_EXTRA",AM$7,$F$2,"Options:Curr="&$F$3&", NA=--"))} | AN33: {=IF($B33="","",_xll.SNL.Clients.Office.Excel.Functions.SPG($B33,"SP_EPS_EST",AN$7,$F$2,"Options:Curr="&$F$3&", NA=--"))} | AO33: {=IF($B33="","",_xll.SNL.Clients.Office.Excel.Functions.SPG($B33,"SP_EPS_EST",AO$7,$F$2,"Options:Curr="&$F$3&", NA=--"))} | AP33: {=IF($B33="","",_xll.SNL.Clients.Office.Excel.Functions.SPG($B33,"SP_EPS_EST",AP$7,$F$2,"Options:Curr="&$F$3&", NA=--"))} | AR33: {=IF($B33="","",_xll.SNL.Clients.Office.Excel.Functions.SPG($B33,"IQ_ROE",AR$7,$F$2,"Options:Curr="&$F$3&", NA=--"))} | AT33: {=IF($B33="","",_xll.SNL.Clients.Office.Excel.Functions.SPG($B33,"IQ_BVPS",AT$7,$F$2,"Options:Curr="&$F$3&", NA=--"))} | AV33: {=IF($B33="","",_xll.SNL.Clients.Office.Excel.Functions.SPG($B33,"IQ_TBVPS",AV$7,$F$2,"Options:Curr="&$F$3&", NA=--"))} | AX33: {=IF($B33="","",_xll.SNL.Clients.Office.Excel.Functions.SPG($B33,"SP_DIV_YIELD",WORKDAY($F$2+1,-1),"Options: NA=--"))} | AY33: {=IF($B33="","",_xll.SNL.Clients.Office.Excel.Functions.SPG($B33,"IQ_TOTAL_EQUITY","FQ0",$F$2,"Options:Curr="&$F$3&", Mag=Millions, NA=--"))} | AZ33: {=IF($B33="","",_xll.SNL.Clients.Office.Excel.Functions.SPG($B33,"IQ_TOTAL_DEBT","FQ0",$F$2,"Options:Curr="&$F$3&", Mag=Millions, NA=--"))} | BA33: {=IF($B33="","",_xll.SNL.Clients.Office.Excel.Functions.SPG($B33,"IQ_CASH_ST_INVEST","FQ0",$F$2,"Options:Curr="&$F$3&", Mag=Millions, NA=--"))} | BB33: =+AZ33-BA33 -> #VALUE! | BC33: {=IF($B33="","",_xll.SNL.Clients.Office.Excel.Functions.SPG($B33,"IQ_TOTAL_EQUITY","FQ0",$F$2,"Options:Curr="&$F$3&", Mag=Millions, NA=--"))} | BE33: =IF($B33="","",IFERROR(_xll.SNL.Clients.Office.Excel.Functions.SPG($B33,"SP_GROSS_MARGIN",BE$7,$F$2,"Options: NA=--")/100,"--")) | BF33: =IF($B33="","",IFERROR(_xll.SNL.Clients.Office.Excel.Functions.SPG($B33,"SP_GROSS_MARGIN_EST",BF$7,$F$2,"Options: NA=--")/100,"--")) | BG33: =IF($B33="","",IFERROR(_xll.SNL.Clients.Office.Excel.Functions.SPG($B33,"SP_GROSS_MARGIN_EST",BG$7,$F$2,"Options: NA=--")/100,"--")) | BH33: =IF($B33="","",IFERROR(_xll.SNL.Clients.Office.Excel.Functions.SPG($B33,"SP_GROSS_MARGIN_EST",BH$7,$F$2,"Options: NA=--")/100,"--"))
D34: {=IF($B34="","",_xll.SNL.Clients.Office.Excel.Functions.SPG($B34, "SP_COMPANY_NAME"))} | G34: {=IF($B34="","",_xll.SNL.Clients.Office.Excel.Functions.SPG($B34,"SP_LASTSALEPRICE",WORKDAY($F$2+1,-1),"Options:Curr="&I34&",NA=--"))} | H34: {=IF($B34="","",_xll.SNL.Clients.Office.Excel.Functions.SPG($B34,"SP_PRICE_CLOSE",WORKDAY($F$2+1,-1),"Options:Curr="&$F$3&", NA=--"))} | I34: {=IF($B34="","",_xll.SNL.Clients.Office.Excel.Functions.SPG($B34,"SP_TRADING_CURRENCY","Options: NA=--"))} | J34: {=IF($B34="","n/a ",_xll.SNL.Clients.Office.Excel.Functions.SPG($B34,"SP_MARKETCAP",WORKDAY($F$2+1,-1),"Options:Curr="&$F$3&", Mag=Millions, NA=--"))} -> n/a | K34: {=IF($B34="","n/a ",_xll.SNL.Clients.Office.Excel.Functions.SPG($B34,"IQ_TEV",WORKDAY($F$2+1,-1),"Options:Curr="&$F$3&", Mag=Millions, NA=--"))} -> n/a | L34: =IFERROR(IF(OR($K34/AC34>L$4,$K34/AC34<L$3),"nmf ",$K34/AC34),"n/a ") -> n/a | M34: =IFERROR(IF(OR($K34/AD34>M$4,$K34/AD34<M$3),"nmf ",$K34/AD34),"n/a ") -> n/a | N34: =IFERROR(IF(OR($K34/AE34>N$4,$K34/AE34<N$3),"nmf ",$K34/AE34),"n/a ") -> n/a | O34: =IFERROR(IF(OR($K34/AH34>O$4,$K34/AH34<O$3),"nmf ",$K34/AH34),"n/a ") -> n/a | P34: =IFERROR(IF(OR($K34/AI34>P$4,$K34/AI34<P$3),"nmf ",$K34/AI34),"n/a ") -> n/a | Q34: =IFERROR(IF(OR($K34/AJ34>Q$4,$K34/AJ34<Q$3),"nmf ",$K34/AJ34),"n/a ") -> n/a | R34: =IFERROR((AE34/AD34)-1,"n/a ") -> n/a | S34: =IFERROR((AF34/AE34)-1,"n/a ") -> n/a | U34: =IFERROR($H34/AM34,"n/a ") -> n/a | V34: =IFERROR($H34/AO34,"n/a ") -> n/a | W34: =IFERROR($H34/AP34,"n/a ") -> n/a | X34: =IFERROR(AR34/100,"n/a ") -> n/a | Y34: =IFERROR(H34/AT34,"n/a ") -> n/a | Z34: =IFERROR(H34/AV34,"n/a ") -> n/a | AC34: {=IF($B34="","",_xll.SNL.Clients.Office.Excel.Functions.SPG($B34,"IQ_REV",AC$7,$F$2,"Options:Curr="&$F$3&", Mag=Millions, NA=--"))} | AD34: {=IF($B34="","",_xll.SNL.Clients.Office.Excel.Functions.SPG($B34,"SP_REV_EST",AD$7,$F$2,"Options:Curr="&$F$3&", Mag=Millions, NA=--"))} | AE34: {=IF($B34="","",_xll.SNL.Clients.Office.Excel.Functions.SPG($B34,"SP_REV_EST",AE$7,$F$2,"Options:Curr="&$F$3&", Mag=Millions, NA=--"))} | AF34: {=IF($B34="","",_xll.SNL.Clients.Office.Excel.Functions.SPG($B34,"SP_REV_EST",AF$7,$F$2,"Options:Curr="&$F$3&", Mag=Millions, NA=--"))} | AH34: {=IF($B34="","",_xll.SNL.Clients.Office.Excel.Functions.SPG($B34,"SP_EBITDA",AH$7,$F$2,"Options:Curr="&$F$3&", Mag=Millions, NA=--"))} | AI34: {=IF($B34="","",_xll.SNL.Clients.Office.Excel.Functions.SPG($B34,"SP_EBITDA_EST",AI$7,$F$2,"Options:Curr="&$F$3&", Mag=Millions, NA=--"))} | AJ34: {=IF($B34="","",_xll.SNL.Clients.Office.Excel.Functions.SPG($B34,"SP_EBITDA_EST",AJ$7,$F$2,"Options:Curr="&$F$3&", Mag=Millions, NA=--"))} | AK34: {=IF($B34="","",_xll.SNL.Clients.Office.Excel.Functions.SPG($B34,"SP_EBITDA_EST",AK$7,$F$2,"Options:Curr="&$F$3&", Mag=Millions, NA=--"))} | AM34: {=IF($B34="","",_xll.SNL.Clients.Office.Excel.Functions.SPG($B34,"IQ_BASIC_EPS_BEFORE_EXTRA",AM$7,$F$2,"Options:Curr="&$F$3&", NA=--"))} | AN34: {=IF($B34="","",_xll.SNL.Clients.Office.Excel.Functions.SPG($B34,"SP_EPS_EST",AN$7,$F$2,"Options:Curr="&$F$3&", NA=--"))} | AO34: {=IF($B34="","",_xll.SNL.Clients.Office.Excel.Functions.SPG($B34,"SP_EPS_EST",AO$7,$F$2,"Options:Curr="&$F$3&", NA=--"))} | AP34: {=IF($B34="","",_xll.SNL.Clients.Office.Excel.Functions.SPG($B34,"SP_EPS_EST",AP$7,$F$2,"Options:Curr="&$F$3&", NA=--"))} | AR34: {=IF($B34="","",_xll.SNL.Clients.Office.Excel.Functions.SPG($B34,"IQ_ROE",AR$7,$F$2,"Options:Curr="&$F$3&", NA=--"))} | AT34: {=IF($B34="","",_xll.SNL.Clients.Office.Excel.Functions.SPG($B34,"IQ_BVPS",AT$7,$F$2,"Options:Curr="&$F$3&", NA=--"))} | AV34: {=IF($B34="","",_xll.SNL.Clients.Office.Excel.Functions.SPG($B34,"IQ_TBVPS",AV$7,$F$2,"Options:Curr="&$F$3&", NA=--"))} | AX34: {=IF($B34="","",_xll.SNL.Clients.Office.Excel.Functions.SPG($B34,"SP_DIV_YIELD",WORKDAY($F$2+1,-1),"Options: NA=--"))} | AY34: {=IF($B34="","",_xll.SNL.Clients.Office.Excel.Functions.SPG($B34,"IQ_TOTAL_EQUITY","FQ0",$F$2,"Options:Curr="&$F$3&", Mag=Millions, NA=--"))} | AZ34: {=IF($B34="","",_xll.SNL.Clients.Office.Excel.Functions.SPG($B34,"IQ_TOTAL_DEBT","FQ0",$F$2,"Options:Curr="&$F$3&", Mag=Millions, NA=--"))} | BA34: {=IF($B34="","",_xll.SNL.Clients.Office.Excel.Functions.SPG($B34,"IQ_CASH_ST_INVEST","FQ0",$F$2,"Options:Curr="&$F$3&", Mag=Millions, NA=--"))} | BB34: =+AZ34-BA34 -> #VALUE! | BC34: {=IF($B34="","",_xll.SNL.Clients.Office.Excel.Functions.SPG($B34,"IQ_TOTAL_EQUITY","FQ0",$F$2,"Options:Curr="&$F$3&", Mag=Millions, NA=--"))} | BE34: =IF($B34="","",IFERROR(_xll.SNL.Clients.Office.Excel.Functions.SPG($B34,"SP_GROSS_MARGIN",BE$7,$F$2,"Options: NA=--")/100,"--")) | BF34: =IF($B34="","",IFERROR(_xll.SNL.Clients.Office.Excel.Functions.SPG($B34,"SP_GROSS_MARGIN_EST",BF$7,$F$2,"Options: NA=--")/100,"--")) | BG34: =IF($B34="","",IFERROR(_xll.SNL.Clients.Office.Excel.Functions.SPG($B34,"SP_GROSS_MARGIN_EST",BG$7,$F$2,"Options: NA=--")/100,"--")) | BH34: =IF($B34="","",IFERROR(_xll.SNL.Clients.Office.Excel.Functions.SPG($B34,"SP_GROSS_MARGIN_EST",BH$7,$F$2,"Options: NA=--")/100,"--"))
D35: {=IF($B35="","",_xll.SNL.Clients.Office.Excel.Functions.SPG($B35, "SP_COMPANY_NAME"))} | G35: {=IF($B35="","",_xll.SNL.Clients.Office.Excel.Functions.SPG($B35,"SP_LASTSALEPRICE",WORKDAY($F$2+1,-1),"Options:Curr="&I35&",NA=--"))} | H35: {=IF($B35="","",_xll.SNL.Clients.Office.Excel.Functions.SPG($B35,"SP_PRICE_CLOSE",WORKDAY($F$2+1,-1),"Options:Curr="&$F$3&", NA=--"))} | I35: {=IF($B35="","",_xll.SNL.Clients.Office.Excel.Functions.SPG($B35,"SP_TRADING_CURRENCY","Options: NA=--"))} | J35: {=IF($B35="","n/a ",_xll.SNL.Clients.Office.Excel.Functions.SPG($B35,"SP_MARKETCAP",WORKDAY($F$2+1,-1),"Options:Curr="&$F$3&", Mag=Millions, NA=--"))} -> n/a | K35: {=IF($B35="","n/a ",_xll.SNL.Clients.Office.Excel.Functions.SPG($B35,"IQ_TEV",WORKDAY($F$2+1,-1),"Options:Curr="&$F$3&", Mag=Millions, NA=--"))} -> n/a | L35: =IFERROR(IF(OR($K35/AC35>L$4,$K35/AC35<L$3),"nmf ",$K35/AC35),"n/a ") -> n/a | M35: =IFERROR(IF(OR($K35/AD35>M$4,$K35/AD35<M$3),"nmf ",$K35/AD35),"n/a ") -> n/a | N35: =IFERROR(IF(OR($K35/AE35>N$4,$K35/AE35<N$3),"nmf ",$K35/AE35),"n/a ") -> n/a | O35: =IFERROR(IF(OR($K35/AH35>O$4,$K35/AH35<O$3),"nmf ",$K35/AH35),"n/a ") -> n/a | P35: =IFERROR(IF(OR($K35/AI35>P$4,$K35/AI35<P$3),"nmf ",$K35/AI35),"n/a ") -> n/a | Q35: =IFERROR(IF(OR($K35/AJ35>Q$4,$K35/AJ35<Q$3),"nmf ",$K35/AJ35),"n/a ") -> n/a | R35: =IFERROR((AE35/AD35)-1,"n/a ") -> n/a | S35: =IFERROR((AF35/AE35)-1,"n/a ") -> n/a | U35: =IFERROR($H35/AM35,"n/a ") -> n/a | V35: =IFERROR($H35/AO35,"n/a ") -> n/a | W35: =IFERROR($H35/AP35,"n/a ") -> n/a | X35: =IFERROR(AR35/100,"n/a ") -> n/a | Y35: =IFERROR(H35/AT35,"n/a ") -> n/a | Z35: =IFERROR(H35/AV35,"n/a ") -> n/a | AC35: {=IF($B35="","",_xll.SNL.Clients.Office.Excel.Functions.SPG($B35,"IQ_REV",AC$7,$F$2,"Options:Curr="&$F$3&", Mag=Millions, NA=--"))} | AD35: {=IF($B35="","",_xll.SNL.Clients.Office.Excel.Functions.SPG($B35,"SP_REV_EST",AD$7,$F$2,"Options:Curr="&$F$3&", Mag=Millions, NA=--"))} | AE35: {=IF($B35="","",_xll.SNL.Clients.Office.Excel.Functions.SPG($B35,"SP_REV_EST",AE$7,$F$2,"Options:Curr="&$F$3&", Mag=Millions, NA=--"))} | AF35: {=IF($B35="","",_xll.SNL.Clients.Office.Excel.Functions.SPG($B35,"SP_REV_EST",AF$7,$F$2,"Options:Curr="&$F$3&", Mag=Millions, NA=--"))} | AH35: {=IF($B35="","",_xll.SNL.Clients.Office.Excel.Functions.SPG($B35,"SP_EBITDA",AH$7,$F$2,"Options:Curr="&$F$3&", Mag=Millions, NA=--"))} | AI35: {=IF($B35="","",_xll.SNL.Clients.Office.Excel.Functions.SPG($B35,"SP_EBITDA_EST",AI$7,$F$2,"Options:Curr="&$F$3&", Mag=Millions, NA=--"))} | AJ35: {=IF($B35="","",_xll.SNL.Clients.Office.Excel.Functions.SPG($B35,"SP_EBITDA_EST",AJ$7,$F$2,"Options:Curr="&$F$3&", Mag=Millions, NA=--"))} | AK35: {=IF($B35="","",_xll.SNL.Clients.Office.Excel.Functions.SPG($B35,"SP_EBITDA_EST",AK$7,$F$2,"Options:Curr="&$F$3&", Mag=Millions, NA=--"))} | AM35: {=IF($B35="","",_xll.SNL.Clients.Office.Excel.Functions.SPG($B35,"IQ_BASIC_EPS_BEFORE_EXTRA",AM$7,$F$2,"Options:Curr="&$F$3&", NA=--"))} | AN35: {=IF($B35="","",_xll.SNL.Clients.Office.Excel.Functions.SPG($B35,"SP_EPS_EST",AN$7,$F$2,"Options:Curr="&$F$3&", NA=--"))} | AO35: {=IF($B35="","",_xll.SNL.Clients.Office.Excel.Functions.SPG($B35,"SP_EPS_EST",AO$7,$F$2,"Options:Curr="&$F$3&", NA=--"))} | AP35: {=IF($B35="","",_xll.SNL.Clients.Office.Excel.Functions.SPG($B35,"SP_EPS_EST",AP$7,$F$2,"Options:Curr="&$F$3&", NA=--"))} | AR35: {=IF($B35="","",_xll.SNL.Clients.Office.Excel.Functions.SPG($B35,"IQ_ROE",AR$7,$F$2,"Options:Curr="&$F$3&", NA=--"))} | AT35: {=IF($B35="","",_xll.SNL.Clients.Office.Excel.Functions.SPG($B35,"IQ_BVPS",AT$7,$F$2,"Options:Curr="&$F$3&", NA=--"))} | AV35: {=IF($B35="","",_xll.SNL.Clients.Office.Excel.Functions.SPG($B35,"IQ_TBVPS",AV$7,$F$2,"Options:Curr="&$F$3&", NA=--"))} | AX35: {=IF($B35="","",_xll.SNL.Clients.Office.Excel.Functions.SPG($B35,"SP_DIV_YIELD",WORKDAY($F$2+1,-1),"Options: NA=--"))} | AY35: {=IF($B35="","",_xll.SNL.Clients.Office.Excel.Functions.SPG($B35,"IQ_TOTAL_EQUITY","FQ0",$F$2,"Options:Curr="&$F$3&", Mag=Millions, NA=--"))} | AZ35: {=IF($B35="","",_xll.SNL.Clients.Office.Excel.Functions.SPG($B35,"IQ_TOTAL_DEBT","FQ0",$F$2,"Options:Curr="&$F$3&", Mag=Millions, NA=--"))} | BA35: {=IF($B35="","",_xll.SNL.Clients.Office.Excel.Functions.SPG($B35,"IQ_CASH_ST_INVEST","FQ0",$F$2,"Options:Curr="&$F$3&", Mag=Millions, NA=--"))} | BB35: =+AZ35-BA35 -> #VALUE! | BC35: {=IF($B35="","",_xll.SNL.Clients.Office.Excel.Functions.SPG($B35,"IQ_TOTAL_EQUITY","FQ0",$F$2,"Options:Curr="&$F$3&", Mag=Millions, NA=--"))} | BE35: =IF($B35="","",IFERROR(_xll.SNL.Clients.Office.Excel.Functions.SPG($B35,"SP_GROSS_MARGIN",BE$7,$F$2,"Options: NA=--")/100,"--")) | BF35: =IF($B35="","",IFERROR(_xll.SNL.Clients.Office.Excel.Functions.SPG($B35,"SP_GROSS_MARGIN_EST",BF$7,$F$2,"Options: NA=--")/100,"--")) | BG35: =IF($B35="","",IFERROR(_xll.SNL.Clients.Office.Excel.Functions.SPG($B35,"SP_GROSS_MARGIN_EST",BG$7,$F$2,"Options: NA=--")/100,"--")) | BH35: =IF($B35="","",IFERROR(_xll.SNL.Clients.Office.Excel.Functions.SPG($B35,"SP_GROSS_MARGIN_EST",BH$7,$F$2,"Options: NA=--")/100,"--"))
D37: Group Average | L37: =IFERROR(AVERAGE(L30:L35),"n/a ") -> n/a | M37: =IFERROR(AVERAGE(M30:M35),"n/a ") -> n/a | N37: =IFERROR(AVERAGE(N30:N35),"n/a ") -> n/a | O37: =IFERROR(AVERAGE(O30:O35),"n/a ") -> n/a | P37: =IFERROR(AVERAGE(P30:P35),"n/a ") -> n/a | Q37: =IFERROR(AVERAGE(Q30:Q35),"n/a ") -> n/a | R37: =IFERROR(AVERAGE(R30:R35),"n/a ") -> n/a | S37: =IFERROR(AVERAGE(S30:S35),"n/a ") -> n/a | U37: =IFERROR(AVERAGE(U30:U35),"n/a ") -> n/a | V37: =IFERROR(AVERAGE(V30:V35),"n/a ") -> n/a | W37: =IFERROR(AVERAGE(W30:W35),"n/a ") -> n/a | X37: =IFERROR(AVERAGE(X30:X35),"n/a ") -> n/a | Y37: =IFERROR(AVERAGE(Y30:Y35),"n/a ") -> n/a | Z37: =IFERROR(AVERAGE(Z30:Z35),"n/a ") -> n/a
D39: Global Average | L39: =IFERROR(AVERAGE(L10:L15,L20:L25,L30:L35),"n/a ") -> n/a | M39: =IFERROR(AVERAGE(M10:M15,M20:M25,M30:M35),"n/a ") -> n/a | N39: =IFERROR(AVERAGE(N10:N15,N20:N25,N30:N35),"n/a ") -> n/a | O39: =IFERROR(AVERAGE(O10:O15,O20:O25,O30:O35),"n/a ") -> n/a | P39: =IFERROR(AVERAGE(P10:P15,P20:P25,P30:P35),"n/a ") -> n/a | Q39: =IFERROR(AVERAGE(Q10:Q15,Q20:Q25,Q30:Q35),"n/a ") -> n/a | R39: =IFERROR(AVERAGE(R10:R15,R20:R25,R30:R35),"n/a ") -> n/a | S39: =IFERROR(AVERAGE(S10:S15,S20:S25,S30:S35),"n/a ") -> n/a | U39: =IFERROR(AVERAGE(U10:U15,U20:U25,U30:U35),"n/a ") -> n/a | V39: =IFERROR(AVERAGE(V10:V15,V20:V25,V30:V35),"n/a ") -> n/a | W39: =IFERROR(AVERAGE(W10:W15,W20:W25,W30:W35),"n/a ") -> n/a | X39: =IFERROR(AVERAGE(X10:X15,X20:X25,X30:X35),"n/a ") -> n/a | Y39: =IFERROR(AVERAGE(Y10:Y15,Y20:Y25,Y30:Y35),"n/a ") -> n/a | Z39: =IFERROR(AVERAGE(Z10:Z15,Z20:Z25,Z30:Z35),"n/a ") -> n/a
D40: Global Average (Excl. High / Low) | L40: =+IFERROR((SUM(L20:L25,L10:L15)-MAX(L10:L15,L20:L25)-MIN(L10:L15,L20:L25))/(COUNT(L20:L25,L10:L15)-2),"n/a ") -> 0 | M40: =+IFERROR((SUM(M20:M25,M10:M15)-MAX(M10:M15,M20:M25)-MIN(M10:M15,M20:M25))/(COUNT(M20:M25,M10:M15)-2),"n/a ") -> 0 | N40: =+IFERROR((SUM(N20:N25,N10:N15)-MAX(N10:N15,N20:N25)-MIN(N10:N15,N20:N25))/(COUNT(N20:N25,N10:N15)-2),"n/a ") -> 0 | O40: =+IFERROR((SUM(O20:O25,O10:O15)-MAX(O10:O15,O20:O25)-MIN(O10:O15,O20:O25))/(COUNT(O20:O25,O10:O15)-2),"n/a ") -> 0 | P40: =+IFERROR((SUM(P20:P25,P10:P15)-MAX(P10:P15,P20:P25)-MIN(P10:P15,P20:P25))/(COUNT(P20:P25,P10:P15)-2),"n/a ") -> 0 | Q40: =+IFERROR((SUM(Q20:Q25,Q10:Q15)-MAX(Q10:Q15,Q20:Q25)-MIN(Q10:Q15,Q20:Q25))/(COUNT(Q20:Q25,Q10:Q15)-2),"n/a ") -> 0 | R40: =+IFERROR((SUM(R20:R25,R10:R15)-MAX(R10:R15,R20:R25)-MIN(R10:R15,R20:R25))/(COUNT(R20:R25,R10:R15)-2),"n/a ") -> 0 | S40: =+IFERROR((SUM(S20:S25,S10:S15)-MAX(S10:S15,S20:S25)-MIN(S10:S15,S20:S25))/(COUNT(S20:S25,S10:S15)-2),"n/a ") -> 0 | U40: =+IFERROR((SUM(U20:U25,U10:U15)-MAX(U10:U15,U20:U25)-MIN(U10:U15,U20:U25))/(COUNT(U20:U25,U10:U15)-2),"n/a ") -> 0 | V40: =+IFERROR((SUM(V20:V25,V10:V15)-MAX(V10:V15,V20:V25)-MIN(V10:V15,V20:V25))/(COUNT(V20:V25,V10:V15)-2),"n/a ") -> 0 | W40: =+IFERROR((SUM(W20:W25,W10:W15)-MAX(W10:W15,W20:W25)-MIN(W10:W15,W20:W25))/(COUNT(W20:W25,W10:W15)-2),"n/a ") -> 0 | X40: =+IFERROR((SUM(X20:X25,X10:X15)-MAX(X10:X15,X20:X25)-MIN(X10:X15,X20:X25))/(COUNT(X20:X25,X10:X15)-2),"n/a ") -> 0 | Y40: =+IFERROR((SUM(Y20:Y25,Y10:Y15)-MAX(Y10:Y15,Y20:Y25)-MIN(Y10:Y15,Y20:Y25))/(COUNT(Y20:Y25,Y10:Y15)-2),"n/a ") -> 0 | Z40: =+IFERROR((SUM(Z20:Z25,Z10:Z15)-MAX(Z10:Z15,Z20:Z25)-MIN(Z10:Z15,Z20:Z25))/(COUNT(Z20:Z25,Z10:Z15)-2),"n/a ") -> 0
D41: Global Median | L41: =IFERROR(MEDIAN(L20:L25,L10:L15,L30:L35),"n/a ") -> n/a | M41: =IFERROR(MEDIAN(M20:M25,M10:M15,M30:M35),"n/a ") -> n/a | N41: =IFERROR(MEDIAN(N20:N25,N10:N15,N30:N35),"n/a ") -> n/a | O41: =IFERROR(MEDIAN(O20:O25,O10:O15,O30:O35),"n/a ") -> n/a | P41: =IFERROR(MEDIAN(P20:P25,P10:P15,P30:P35),"n/a ") -> n/a | Q41: =IFERROR(MEDIAN(Q20:Q25,Q10:Q15,Q30:Q35),"n/a ") -> n/a | R41: =IFERROR(MEDIAN(R20:R25,R10:R15,R30:R35),"n/a ") -> n/a | S41: =IFERROR(MEDIAN(S20:S25,S10:S15,S30:S35),"n/a ") -> n/a | U41: =IFERROR(MEDIAN(U20:U25,U10:U15,U30:U35),"n/a ") -> n/a | V41: =IFERROR(MEDIAN(V20:V25,V10:V15,V30:V35),"n/a ") -> n/a | W41: =IFERROR(MEDIAN(W20:W25,W10:W15,W30:W35),"n/a ") -> n/a | X41: =IFERROR(MEDIAN(X20:X25,X10:X15,X30:X35),"n/a ") -> n/a | Y41: =IFERROR(MEDIAN(Y20:Y25,Y10:Y15,Y30:Y35),"n/a ") -> n/a | Z41: =IFERROR(MEDIAN(Z20:Z25,Z10:Z15,Z30:Z35),"n/a ") -> n/a
D43: 25th Percentile | L43: =_xlfn.PERCENTILE.INC((L10:L15,L20:L25,L30:L35),0.25) -> #NUM! | M43: =_xlfn.PERCENTILE.INC((M10:M15,M20:M25,M30:M35),0.25) -> #NUM! | N43: =_xlfn.PERCENTILE.INC((N10:N15,N20:N25,N30:N35),0.25) -> #NUM! | O43: =_xlfn.PERCENTILE.INC((O10:O15,O20:O25,O30:O35),0.25) -> #NUM! | P43: =_xlfn.PERCENTILE.INC((P10:P15,P20:P25,P30:P35),0.25) -> #NUM! | Q43: =_xlfn.PERCENTILE.INC((Q10:Q15,Q20:Q25,Q30:Q35),0.25) -> #NUM! | R43: =_xlfn.PERCENTILE.INC((R10:R15,R20:R25,R30:R35),0.25) -> #NUM! | S43: =_xlfn.PERCENTILE.INC((S10:S15,S20:S25,S30:S35),0.25) -> #NUM! | U43: =_xlfn.PERCENTILE.INC((U10:U15,U20:U25,U30:U35),0.25) -> #NUM! | V43: =_xlfn.PERCENTILE.INC((V10:V15,V20:V25,V30:V35),0.25) -> #NUM! | W43: =_xlfn.PERCENTILE.INC((W10:W15,W20:W25,W30:W35),0.25) -> #NUM! | X43: =_xlfn.PERCENTILE.INC((X10:X15,X20:X25,X30:X35),0.25) -> #NUM! | Y43: =_xlfn.PERCENTILE.INC((Y10:Y15,Y20:Y25,Y30:Y35),0.25) -> #NUM! | Z43: =_xlfn.PERCENTILE.INC((Z10:Z15,Z20:Z25,Z30:Z35),0.25) -> #NUM!
D44: 75th Percentile | L44: =_xlfn.PERCENTILE.INC((L10:L15,L20:L25,L30:L35),0.75) -> #NUM! | M44: =_xlfn.PERCENTILE.INC((M10:M15,M20:M25,M30:M35),0.75) -> #NUM! | N44: =_xlfn.PERCENTILE.INC((N10:N15,N20:N25,N30:N35),0.75) -> #NUM! | O44: =_xlfn.PERCENTILE.INC((O10:O15,O20:O25,O30:O35),0.75) -> #NUM! | P44: =_xlfn.PERCENTILE.INC((P10:P15,P20:P25,P30:P35),0.75) -> #NUM! | Q44: =_xlfn.PERCENTILE.INC((Q10:Q15,Q20:Q25,Q30:Q35),0.75) -> #NUM! | R44: =_xlfn.PERCENTILE.INC((R10:R15,R20:R25,R30:R35),0.75) -> #NUM! | S44: =_xlfn.PERCENTILE.INC((S10:S15,S20:S25,S30:S35),0.75) -> #NUM! | U44: =_xlfn.PERCENTILE.INC((U10:U15,U20:U25,U30:U35),0.75) -> #NUM! | V44: =_xlfn.PERCENTILE.INC((V10:V15,V20:V25,V30:V35),0.75) -> #NUM! | W44: =_xlfn.PERCENTILE.INC((W10:W15,W20:W25,W30:W35),0.75) -> #NUM! | X44: =_xlfn.PERCENTILE.INC((X10:X15,X20:X25,X30:X35),0.75) -> #NUM! | Y44: =_xlfn.PERCENTILE.INC((Y10:Y15,Y20:Y25,Y30:Y35),0.75) -> #NUM! | Z44: =_xlfn.PERCENTILE.INC((Z10:Z15,Z20:Z25,Z30:Z35),0.75) -> #NUM!

Sheet Ownership
B2: Ownership
B4: Select Insiders | F4: (000s) | G4: %
A5: 1 | B5: =_xlfn.XLOOKUP(F5,$I$39:$I$178,$J$39:$J$178) -> 0 | F5: =LARGE($I$39:$I$65,A5) -> 0 | G5: =F5/$F$35 -> #DIV/0!
A6: 2 | B6: =_xlfn.XLOOKUP(F6,$I$39:$I$178,$J$39:$J$178) -> 0 | F6: =LARGE($I$39:$I$65,A6) -> 0 | G6: =F6/$F$35 -> #DIV/0!
A7: 3 | B7: =_xlfn.XLOOKUP(F7,$I$39:$I$178,$J$39:$J$178) -> 0 | F7: =LARGE($I$39:$I$65,A7) -> 0 | G7: =F7/$F$35 -> #DIV/0!
A8: 4 | B8: =_xlfn.XLOOKUP(F8,$I$39:$I$178,$J$39:$J$178) -> 0 | F8: =LARGE($I$39:$I$65,A8) -> 0 | G8: =F8/$F$35 -> #DIV/0!
A9: 5 | B9: =_xlfn.XLOOKUP(F9,$I$39:$I$178,$J$39:$J$178) -> 0 | F9: =LARGE($I$39:$I$65,A9) -> 0 | G9: =F9/$F$35 -> #DIV/0!
A10: 6 | B10: =_xlfn.XLOOKUP(F10,$I$39:$I$178,$J$39:$J$178) -> 0 | F10: =LARGE($I$39:$I$65,A10) -> 0 | G10: =F10/$F$35 -> #DIV/0!
A11: 7 | B11: =_xlfn.XLOOKUP(F11,$I$39:$I$178,$J$39:$J$178) -> 0 | F11: =LARGE($I$39:$I$65,A11) -> 0 | G11: =F11/$F$35 -> #DIV/0!
A12: 8 | B12: =_xlfn.XLOOKUP(F12,$I$39:$I$178,$J$39:$J$178) -> 0 | F12: =LARGE($I$39:$I$65,A12) -> 0 | G12: =F12/$F$35 -> #DIV/0!
A13: 9 | B13: =_xlfn.XLOOKUP(F13,$I$39:$I$178,$J$39:$J$178) -> 0 | F13: =LARGE($I$39:$I$65,A13) -> 0 | G13: =F13/$F$35 -> #DIV/0!
A14: 10 | B14: =_xlfn.XLOOKUP(F14,$I$39:$I$178,$J$39:$J$178) -> 0 | F14: =LARGE($I$39:$I$65,A14) -> 0 | G14: =F14/$F$35 -> #DIV/0!
A15: 11 | B15: =_xlfn.XLOOKUP(F15,$I$39:$I$178,$J$39:$J$178) -> 0 | F15: =LARGE($I$39:$I$65,A15) -> 0 | G15: =F15/$F$35 -> #DIV/0!
A16: 12 | B16: =_xlfn.XLOOKUP(F16,$I$39:$I$178,$J$39:$J$178) -> 0 | F16: =LARGE($I$39:$I$65,A16) -> 0 | G16: =F16/$F$35 -> #DIV/0!
B17: Subtotal | F17: =SUM(F5:F16) -> 0 | G17: =F17/$F$35 -> #DIV/0!
B19: Select Institutions | F19: (000s) | G19: %
A20: 1 | B20: =_xlfn.XLOOKUP(F20,$I$39:$I$185,$J$39:$J$185) -> #N/A | F20: =LARGE($I$68:$I$185,A20) -> #N/A | G20: =F20/$F$35 -> #N/A
A21: 2 | B21: =_xlfn.XLOOKUP(F21,$I$39:$I$185,$J$39:$J$185) -> #N/A | F21: =LARGE($I$68:$I$185,A21) -> #N/A | G21: =F21/$F$35 -> #N/A
A22: 3 | B22: =_xlfn.XLOOKUP(F22,$I$39:$I$185,$J$39:$J$185) -> #N/A | F22: =LARGE($I$68:$I$185,A22) -> #N/A | G22: =F22/$F$35 -> #N/A
A23: 4 | B23: =_xlfn.XLOOKUP(F23,$I$39:$I$185,$J$39:$J$185) -> #N/A | F23: =LARGE($I$68:$I$185,A23) -> #N/A | G23: =F23/$F$35 -> #N/A
A24: 5 | B24: =_xlfn.XLOOKUP(F24,$I$39:$I$185,$J$39:$J$185) -> #N/A | F24: =LARGE($I$68:$I$185,A24) -> #N/A | G24: =F24/$F$35 -> #N/A
A25: 6 | B25: =_xlfn.XLOOKUP(F25,$I$39:$I$185,$J$39:$J$185) -> #N/A | F25: =LARGE($I$68:$I$185,A25) -> #N/A | G25: =F25/$F$35 -> #N/A
A26: 7 | B26: =_xlfn.XLOOKUP(F26,$I$39:$I$185,$J$39:$J$185) -> #N/A | F26: =LARGE($I$68:$I$185,A26) -> #N/A | G26: =F26/$F$35 -> #N/A
A27: 8 | B27: =_xlfn.XLOOKUP(F27,$I$39:$I$185,$J$39:$J$185) -> #N/A | F27: =LARGE($I$68:$I$185,A27) -> #N/A | G27: =F27/$F$35 -> #N/A
A28: 9 | B28: =_xlfn.XLOOKUP(F28,$I$39:$I$185,$J$39:$J$185) -> #N/A | F28: =LARGE($I$68:$I$185,A28) -> #N/A | G28: =F28/$F$35 -> #N/A
A29: 10 | B29: =_xlfn.XLOOKUP(F29,$I$39:$I$185,$J$39:$J$185) -> #N/A | F29: =LARGE($I$68:$I$185,A29) -> #N/A | G29: =F29/$F$35 -> #N/A
A30: 11 | B30: =_xlfn.XLOOKUP(F30,$I$39:$I$185,$J$39:$J$185) -> #N/A | F30: =LARGE($I$68:$I$185,A30) -> #N/A | G30: =F30/$F$35 -> #N/A
A31: 12 | B31: =_xlfn.XLOOKUP(F31,$I$39:$I$185,$J$39:$J$185) -> #N/A | F31: =LARGE($I$68:$I$185,A31) -> #N/A | G31: =F31/$F$35 -> #N/A
B32: Subtotal | F32: =SUM(F20:F31) -> #N/A | G32: =F32/$F$35 -> #N/A
B33: Other Shareholders | F33: =+F35-F32-F17 -> #N/A | G33: =F33/$F$35 -> #N/A
B35: Total Basic Shares Outstanding | G35: =F35/$F$35 -> #DIV/0!
B38: SEDI Name | F38: Basic | G38: Date | H38: Include | I38: Adj. # | J38: Adj. Name
H39: 1 | I39: =H39*F39 -> 0
H40: 1 | I40: =H40*F40 -> 0
H41: 1 | I41: =H41*F41 -> 0
H42: 1 | I42: =H42*F42 -> 0
H43: 1 | I43: =H43*F43 -> 0
H44: 1 | I44: =H44*F44 -> 0
H45: 1 | I45: =H45*F45 -> 0
H46: 1 | I46: =H46*F46 -> 0
H47: 1 | I47: =H47*F47 -> 0
H48: 1 | I48: =H48*F48 -> 0
H49: 1 | I49: =H49*F49 -> 0
H50: 1 | I50: =H50*F50 -> 0
... H65: 1 | I65: =H65*F65 -> 0
B67: From Bloomberg | F67: Basic | G67: Date | H67: Include | I67: Adj. # | J67: Adj. Name
B68: ='Bloomberg Output'!C14 -> 0 | F68: =+_xlfn.XLOOKUP($B68,'Bloomberg Output'!$C$14:$C$131,'Bloomberg Output'!$L$14:$L$131) -> #N/A | G68: =+_xlfn.XLOOKUP($B68,'Bloomberg Output'!$C$14:$C$131,'Bloomberg Output'!$N$14:$N$131) -> #N/A | H68: 1 | I68: =H68*F68 -> #N/A
B69: ='Bloomberg Output'!C15 -> 0 | F69: =+_xlfn.XLOOKUP($B69,'Bloomberg Output'!$C$14:$C$131,'Bloomberg Output'!$L$14:$L$131) -> #N/A | G69: =+_xlfn.XLOOKUP($B69,'Bloomberg Output'!$C$14:$C$131,'Bloomberg Output'!$N$14:$N$131) -> #N/A | H69: 1 | I69: =H69*F69 -> #N/A
B70: ='Bloomberg Output'!C16 -> 0 | F70: =+_xlfn.XLOOKUP($B70,'Bloomberg Output'!$C$14:$C$131,'Bloomberg Output'!$L$14:$L$131) -> #N/A | G70: =+_xlfn.XLOOKUP($B70,'Bloomberg Output'!$C$14:$C$131,'Bloomberg Output'!$N$14:$N$131) -> #N/A | H70: 1 | I70: =H70*F70 -> #N/A
B71: ='Bloomberg Output'!C17 -> 0 | F71: =+_xlfn.XLOOKUP($B71,'Bloomberg Output'!$C$14:$C$131,'Bloomberg Output'!$L$14:$L$131) -> #N/A | G71: =+_xlfn.XLOOKUP($B71,'Bloomberg Output'!$C$14:$C$131,'Bloomberg Output'!$N$14:$N$131) -> #N/A | H71: 1 | I71: =H71*F71 -> #N/A
B72: ='Bloomberg Output'!C18 -> 0 | F72: =+_xlfn.XLOOKUP($B72,'Bloomberg Output'!$C$14:$C$131,'Bloomberg Output'!$L$14:$L$131) -> #N/A | G72: =+_xlfn.XLOOKUP($B72,'Bloomberg Output'!$C$14:$C$131,'Bloomberg Output'!$N$14:$N$131) -> #N/A | H72: 1 | I72: =H72*F72 -> #N/A
B73: ='Bloomberg Output'!C19 -> 0 | F73: =+_xlfn.XLOOKUP($B73,'Bloomberg Output'!$C$14:$C$131,'Bloomberg Output'!$L$14:$L$131) -> #N/A | G73: =+_xlfn.XLOOKUP($B73,'Bloomberg Output'!$C$14:$C$131,'Bloomberg Output'!$N$14:$N$131) -> #N/A | H73: 1 | I73: =H73*F73 -> #N/A
B74: ='Bloomberg Output'!C20 -> 0 | F74: =+_xlfn.XLOOKUP($B74,'Bloomberg Output'!$C$14:$C$131,'Bloomberg Output'!$L$14:$L$131) -> #N/A | G74: =+_xlfn.XLOOKUP($B74,'Bloomberg Output'!$C$14:$C$131,'Bloomberg Output'!$N$14:$N$131) -> #N/A | H74: 1 | I74: =H74*F74 -> #N/A
B75: ='Bloomberg Output'!C21 -> 0 | F75: =+_xlfn.XLOOKUP($B75,'Bloomberg Output'!$C$14:$C$131,'Bloomberg Output'!$L$14:$L$131) -> #N/A | G75: =+_xlfn.XLOOKUP($B75,'Bloomberg Output'!$C$14:$C$131,'Bloomberg Output'!$N$14:$N$131) -> #N/A | H75: 1 | I75: =H75*F75 -> #N/A
B76: ='Bloomberg Output'!C22 -> 0 | F76: =+_xlfn.XLOOKUP($B76,'Bloomberg Output'!$C$14:$C$131,'Bloomberg Output'!$L$14:$L$131) -> #N/A | G76: =+_xlfn.XLOOKUP($B76,'Bloomberg Output'!$C$14:$C$131,'Bloomberg Output'!$N$14:$N$131) -> #N/A | H76: 1 | I76: =H76*F76 -> #N/A
B77: ='Bloomberg Output'!C23 -> 0 | F77: =+_xlfn.XLOOKUP($B77,'Bloomberg Output'!$C$14:$C$131,'Bloomberg Output'!$L$14:$L$131) -> #N/A | G77: =+_xlfn.XLOOKUP($B77,'Bloomberg Output'!$C$14:$C$131,'Bloomberg Output'!$N$14:$N$131) -> #N/A | H77: 1 | I77: =H77*F77 -> #N/A
B78: ='Bloomberg Output'!C24 -> 0 | F78: =+_xlfn.XLOOKUP($B78,'Bloomberg Output'!$C$14:$C$131,'Bloomberg Output'!$L$14:$L$131) -> #N/A | G78: =+_xlfn.XLOOKUP($B78,'Bloomberg Output'!$C$14:$C$131,'Bloomberg Output'!$N$14:$N$131) -> #N/A | H78: 1 | I78: =H78*F78 -> #N/A
B79: ='Bloomberg Output'!C25 -> 0 | F79: =+_xlfn.XLOOKUP($B79,'Bloomberg Output'!$C$14:$C$131,'Bloomberg Output'!$L$14:$L$131) -> #N/A | G79: =+_xlfn.XLOOKUP($B79,'Bloomberg Output'!$C$14:$C$131,'Bloomberg Output'!$N$14:$N$131) -> #N/A | H79: 1 | I79: =H79*F79 -> #N/A
... B185: ='Bloomberg Output'!C131 -> 0 | F185: =+_xlfn.XLOOKUP($B185,'Bloomberg Output'!$C$14:$C$131,'Bloomberg Output'!$L$14:$L$131) -> #N/A | G185: =+_xlfn.XLOOKUP($B185,'Bloomberg Output'!$C$14:$C$131,'Bloomberg Output'!$N$14:$N$131) -> #N/A | H185: 1 | I185: =H185*F185 -> #N/A

Sheet Bloomberg Output
C7: Name
C9: Ticker | G9: View
C11: Sort By | G11: Order
C13: Holder Name | G13: Portfolio Name | L13: Position | M13: Latest Chg | N13: Filing Date | O13: Source | P13: % Out | Q13: % Portfolio | R13: Insider Status | S13: Institution Type | T13: Metro Area | U13: Country | V13: Market Value | W13: Hold Period | X13: Cost (FIFO) | Y13: Cost (LIFO) | Z13: Cost (Avg.) | AA13: Ret % (FIFO) | AB13: Ret % (LIFO) | AC13: Ret % (Avg)
B14: 1
B15: 2
B16: 3
B17: 4
B18: 5
B19: 6
B20: 7
B21: 8
B22: 9
B23: 10
B24: 11
B25: 12
... B131: 118

Sheet precedents
B2: Output: | C2: USD
B4: Input | E4: (In US$MM, unless otherwise noted) | I4: TEV | K4: Revenue - Source FX | M4: Net Income - Source FX | O4: Adj. EBITDA - Source FX | Q4: Book Value - Source FX | S4: EV / Revenue | U4: EV / EBITDA | W4: P/ E | Y4: P / B | Z4: P / TBV | AB4: TEV | AC4: Rev. | AD4: EBITDA | AE4: Net Inc. | AF4: P / B | AG4: P / TBV
B5: Currency | C5: FX | E5: Ann. Date | F5: Target | G5: Acquiror | H5: HQ | I5: Source FX | J5: TEV | K5: (LTM) | L5: (NTM) | M5: (LTM) | N5: (NTM) | O5: (LTM) | P5: (NTM) | Q5: BV | R5: TBV | S5: (LTM) | T5: (NTM) | U5: (LTM) | V5: (NTM) | W5: (LTM) | X5: (NTM) | Y5: (Current) | Z5: (Current) | AB5: Source | AC5: Source | AD5: Source | AE5: Source | AF5: Source | AG5: Source | AI5: HQ
E7: [Group #1]
C8: {=_xll.SNL.Clients.Office.Excel.Functions.SPG("$"&$C$2&B8,"SP_PRICE_CLOSE",WORKDAY(E8+1,-1),"Options: NA=NA")} -> #NAME? | J8: =+I8*C8 -> #NAME? | S8: =IF(K8="","n/a ",(K8*C8)/J8) -> n/a | T8: =IF(L8="","n/a ",(L8*C8)/J8) -> n/a | U8: =IF(O8="","n/a ",(O8*C8)/J8) -> n/a | V8: =IF(P8="","n/a ",(P8*C8)/J8) -> n/a | W8: =IF(M8="","n/a ",(M8*C8)/J8) -> n/a | X8: =IF(N8="","n/a ",(N8*C8)/J8) -> n/a | Y8: =IF(Q8="","n/a ",(Q8*C8)/J8) -> n/a | Z8: =IF(R8="","n/a ",(R8*C8)/J8) -> n/a | AB8: Link | AC8: Link | AD8: Link | AE8: Link | AF8: Link | AG8: Link
C9: {=_xll.SNL.Clients.Office.Excel.Functions.SPG("$"&$C$2&B9,"SP_PRICE_CLOSE",WORKDAY(E9+1,-1),"Options: NA=NA")} -> #NAME? | J9: =+I9*C9 -> #NAME? | S9: =IF(K9="","n/a ",(K9*C9)/J9) -> n/a | T9: =IF(L9="","n/a ",(L9*C9)/J9) -> n/a | U9: =IF(O9="","n/a ",(O9*C9)/J9) -> n/a | V9: =IF(P9="","n/a ",(P9*C9)/J9) -> n/a | W9: =IF(M9="","n/a ",(M9*C9)/J9) -> n/a | X9: =IF(N9="","n/a ",(N9*C9)/J9) -> n/a | Y9: =IF(Q9="","n/a ",(Q9*C9)/J9) -> n/a | Z9: =IF(R9="","n/a ",(R9*C9)/J9) -> n/a | AB9: Link | AC9: Link | AD9: Link | AE9: Link | AF9: Link | AG9: Link
C10: {=_xll.SNL.Clients.Office.Excel.Functions.SPG("$"&$C$2&B10,"SP_PRICE_CLOSE",WORKDAY(E10+1,-1),"Options: NA=NA")} -> #NAME? | J10: =+I10*C10 -> #NAME? | S10: =IF(K10="","n/a ",(K10*C10)/J10) -> n/a | T10: =IF(L10="","n/a ",(L10*C10)/J10) -> n/a | U10: =IF(O10="","n/a ",(O10*C10)/J10) -> n/a | V10: =IF(P10="","n/a ",(P10*C10)/J10) -> n/a | W10: =IF(M10="","n/a ",(M10*C10)/J10) -> n/a | X10: =IF(N10="","n/a ",(N10*C10)/J10) -> n/a | Y10: =IF(Q10="","n/a ",(Q10*C10)/J10) -> n/a | Z10: =IF(R10="","n/a ",(R10*C10)/J10) -> n/a | AB10: Link | AC10: Link | AD10: Link | AE10: Link | AF10: Link | AG10: Link
C11: {=_xll.SNL.Clients.Office.Excel.Functions.SPG("$"&$C$2&B11,"SP_PRICE_CLOSE",WORKDAY(E11+1,-1),"Options: NA=NA")} -> #NAME? | J11: =+I11*C11 -> #NAME? | S11: =IF(K11="","n/a ",(K11*C11)/J11) -> n/a | T11: =IF(L11="","n/a ",(L11*C11)/J11) -> n/a | U11: =IF(O11="","n/a ",(O11*C11)/J11) -> n/a | V11: =IF(P11="","n/a ",(P11*C11)/J11) -> n/a | W11: =IF(M11="","n/a ",(M11*C11)/J11) -> n/a | X11: =IF(N11="","n/a ",(N11*C11)/J11) -> n/a | Y11: =IF(Q11="","n/a ",(Q11*C11)/J11) -> n/a | Z11: =IF(R11="","n/a ",(R11*C11)/J11) -> n/a | AB11: Link | AC11: Link | AD11: Link | AE11: Link | AF11: Link | AG11: Link
C12: {=_xll.SNL.Clients.Office.Excel.Functions.SPG("$"&$C$2&B12,"SP_PRICE_CLOSE",WORKDAY(E12+1,-1),"Options: NA=NA")} -> #NAME? | J12: =+I12*C12 -> #NAME? | S12: =IF(K12="","n/a ",(K12*C12)/J12) -> n/a | T12: =IF(L12="","n/a ",(L12*C12)/J12) -> n/a | U12: =IF(O12="","n/a ",(O12*C12)/J12) -> n/a | V12: =IF(P12="","n/a ",(P12*C12)/J12) -> n/a | W12: =IF(M12="","n/a ",(M12*C12)/J12) -> n/a | X12: =IF(N12="","n/a ",(N12*C12)/J12) -> n/a | Y12: =IF(Q12="","n/a ",(Q12*C12)/J12) -> n/a | Z12: =IF(R12="","n/a ",(R12*C12)/J12) -> n/a | AB12: Link | AC12: Link | AD12: Link | AE12: Link | AF12: Link | AG12: Link
C13: {=_xll.SNL.Clients.Office.Excel.Functions.SPG("$"&$C$2&B13,"SP_PRICE_CLOSE",WORKDAY(E13+1,-1),"Options: NA=NA")} -> #NAME? | J13: =+I13*C13 -> #NAME? | S13: =IF(K13="","n/a ",(K13*C13)/J13) -> n/a | T13: =IF(L13="","n/a ",(L13*C13)/J13) -> n/a | U13: =IF(O13="","n/a ",(O13*C13)/J13) -> n/a | V13: =IF(P13="","n/a ",(P13*C13)/J13) -> n/a | W13: =IF(M13="","n/a ",(M13*C13)/J13) -> n/a | X13: =IF(N13="","n/a ",(N13*C13)/J13) -> n/a | Y13: =IF(Q13="","n/a ",(Q13*C13)/J13) -> n/a | Z13: =IF(R13="","n/a ",(R13*C13)/J13) -> n/a | AB13: Link | AC13: Link | AD13: Link | AE13: Link | AF13: Link | AG13: Link
E14: Group Average | S14: =IFERROR(AVERAGE(S8:S13),"n/a ") -> n/a | T14: =IFERROR(AVERAGE(T8:T13),"n/a ") -> n/a | U14: =IFERROR(AVERAGE(U8:U13),"n/a ") -> n/a | V14: =IFERROR(AVERAGE(V8:V13),"n/a ") -> n/a | W14: =IFERROR(AVERAGE(W8:W13),"n/a ") -> n/a | X14: =IFERROR(AVERAGE(X8:X13),"n/a ") -> n/a | Y14: =IFERROR(AVERAGE(Y8:Y13),"n/a ") -> n/a | Z14: =IFERROR(AVERAGE(Z8:Z13),"n/a ") -> n/a
E16: [Group #2]
C17: {=_xll.SNL.Clients.Office.Excel.Functions.SPG("$"&$C$2&B17,"SP_PRICE_CLOSE",WORKDAY(E17+1,-1),"Options: NA=NA")} -> #NAME? | J17: =+I17*C17 -> #NAME? | S17: =IF(K17="","n/a ",(K17*C17)/J17) -> n/a | T17: =IF(L17="","n/a ",(L17*C17)/J17) -> n/a | U17: =IF(O17="","n/a ",(O17*C17)/J17) -> n/a | V17: =IF(P17="","n/a ",(P17*C17)/J17) -> n/a | W17: =IF(M17="","n/a ",(M17*C17)/J17) -> n/a | X17: =IF(N17="","n/a ",(N17*C17)/J17) -> n/a | Y17: =IF(Q17="","n/a ",(Q17*C17)/J17) -> n/a | Z17: =IF(R17="","n/a ",(R17*C17)/J17) -> n/a | AB17: Link | AC17: Link | AD17: Link | AE17: Link | AF17: Link | AG17: Link
C18: {=_xll.SNL.Clients.Office.Excel.Functions.SPG("$"&$C$2&B18,"SP_PRICE_CLOSE",WORKDAY(E18+1,-1),"Options: NA=NA")} -> #NAME? | J18: =+I18*C18 -> #NAME? | S18: =IF(K18="","n/a ",(K18*C18)/J18) -> n/a | T18: =IF(L18="","n/a ",(L18*C18)/J18) -> n/a | U18: =IF(O18="","n/a ",(O18*C18)/J18) -> n/a | V18: =IF(P18="","n/a ",(P18*C18)/J18) -> n/a | W18: =IF(M18="","n/a ",(M18*C18)/J18) -> n/a | X18: =IF(N18="","n/a ",(N18*C18)/J18) -> n/a | Y18: =IF(Q18="","n/a ",(Q18*C18)/J18) -> n/a | Z18: =IF(R18="","n/a ",(R18*C18)/J18) -> n/a | AB18: Link | AC18: Link | AD18: Link | AE18: Link | AF18: Link | AG18: Link
C19: {=_xll.SNL.Clients.Office.Excel.Functions.SPG("$"&$C$2&B19,"SP_PRICE_CLOSE",WORKDAY(E19+1,-1),"Options: NA=NA")} -> #NAME? | J19: =+I19*C19 -> #NAME? | S19: =IF(K19="","n/a ",(K19*C19)/J19) -> n/a | T19: =IF(L19="","n/a ",(L19*C19)/J19) -> n/a | U19: =IF(O19="","n/a ",(O19*C19)/J19) -> n/a | V19: =IF(P19="","n/a ",(P19*C19)/J19) -> n/a | W19: =IF(M19="","n/a ",(M19*C19)/J19) -> n/a | X19: =IF(N19="","n/a ",(N19*C19)/J19) -> n/a | Y19: =IF(Q19="","n/a ",(Q19*C19)/J19) -> n/a | Z19: =IF(R19="","n/a ",(R19*C19)/J19) -> n/a | AB19: Link | AC19: Link | AD19: Link | AE19: Link | AF19: Link | AG19: Link
C20: {=_xll.SNL.Clients.Office.Excel.Functions.SPG("$"&$C$2&B20,"SP_PRICE_CLOSE",WORKDAY(E20+1,-1),"Options: NA=NA")} -> #NAME? | J20: =+I20*C20 -> #NAME? | S20: =IF(K20="","n/a ",(K20*C20)/J20) -> n/a | T20: =IF(L20="","n/a ",(L20*C20)/J20) -> n/a | U20: =IF(O20="","n/a ",(O20*C20)/J20) -> n/a | V20: =IF(P20="","n/a ",(P20*C20)/J20) -> n/a | W20: =IF(M20="","n/a ",(M20*C20)/J20) -> n/a | X20: =IF(N20="","n/a ",(N20*C20)/J20) -> n/a | Y20: =IF(Q20="","n/a ",(Q20*C20)/J20) -> n/a | Z20: =IF(R20="","n/a ",(R20*C20)/J20) -> n/a | AB20: Link | AC20: Link | AD20: Link | AE20: Link | AF20: Link | AG20: Link
C21: {=_xll.SNL.Clients.Office.Excel.Functions.SPG("$"&$C$2&B21,"SP_PRICE_CLOSE",WORKDAY(E21+1,-1),"Options: NA=NA")} -> #NAME? | J21: =+I21*C21 -> #NAME? | S21: =IF(K21="","n/a ",(K21*C21)/J21) -> n/a | T21: =IF(L21="","n/a ",(L21*C21)/J21) -> n/a | U21: =IF(O21="","n/a ",(O21*C21)/J21) -> n/a | V21: =IF(P21="","n/a ",(P21*C21)/J21) -> n/a | W21: =IF(M21="","n/a ",(M21*C21)/J21) -> n/a | X21: =IF(N21="","n/a ",(N21*C21)/J21) -> n/a | Y21: =IF(Q21="","n/a ",(Q21*C21)/J21) -> n/a | Z21: =IF(R21="","n/a ",(R21*C21)/J21) -> n/a | AB21: Link | AC21: Link | AD21: Link | AE21: Link | AF21: Link | AG21: Link
C22: {=_xll.SNL.Clients.Office.Excel.Functions.SPG("$"&$C$2&B22,"SP_PRICE_CLOSE",WORKDAY(E22+1,-1),"Options: NA=NA")} -> #NAME? | J22: =+I22*C22 -> #NAME? | S22: =IF(K22="","n/a ",(K22*C22)/J22) -> n/a | T22: =IF(L22="","n/a ",(L22*C22)/J22) -> n/a | U22: =IF(O22="","n/a ",(O22*C22)/J22) -> n/a | V22: =IF(P22="","n/a ",(P22*C22)/J22) -> n/a | W22: =IF(M22="","n/a ",(M22*C22)/J22) -> n/a | X22: =IF(N22="","n/a ",(N22*C22)/J22) -> n/a | Y22: =IF(Q22="","n/a ",(Q22*C22)/J22) -> n/a | Z22: =IF(R22="","n/a ",(R22*C22)/J22) -> n/a | AB22: Link | AC22: Link | AD22: Link | AE22: Link | AF22: Link | AG22: Link
E23: Group Average | S23: =IFERROR(AVERAGE(S17:S22),"n/a ") -> n/a | T23: =IFERROR(AVERAGE(T17:T22),"n/a ") -> n/a | U23: =IFERROR(AVERAGE(U17:U22),"n/a ") -> n/a | V23: =IFERROR(AVERAGE(V17:V22),"n/a ") -> n/a | W23: =IFERROR(AVERAGE(W17:W22),"n/a ") -> n/a | X23: =IFERROR(AVERAGE(X17:X22),"n/a ") -> n/a | Y23: =IFERROR(AVERAGE(Y17:Y22),"n/a ") -> n/a | Z23: =IFERROR(AVERAGE(Z17:Z22),"n/a ") -> n/a
E25: Global Average | S25: =IFERROR(AVERAGE(S17:S22,S8:S13),"n/a ") -> n/a | T25: =IFERROR(AVERAGE(T17:T22,T8:T13),"n/a ") -> n/a | U25: =IFERROR(AVERAGE(U17:U22,U8:U13),"n/a ") -> n/a | V25: =IFERROR(AVERAGE(V17:V22,V8:V13),"n/a ") -> n/a | W25: =IFERROR(AVERAGE(W17:W22,W8:W13),"n/a ") -> n/a | X25: =IFERROR(AVERAGE(X17:X22,X8:X13),"n/a ") -> n/a | Y25: =IFERROR(AVERAGE(Y17:Y22,Y8:Y13),"n/a ") -> n/a | Z25: =IFERROR(AVERAGE(Z17:Z22,Z8:Z13),"n/a ") -> n/a
E26: Global Median | S26: =IFERROR(MEDIAN(S17:S22,S8:S13),"n/a ") -> n/a | T26: =IFERROR(MEDIAN(T17:T22,T8:T13),"n/a ") -> n/a | U26: =IFERROR(MEDIAN(U17:U22,U8:U13),"n/a ") -> n/a | V26: =IFERROR(MEDIAN(V17:V22,V8:V13),"n/a ") -> n/a | W26: =IFERROR(MEDIAN(W17:W22,W8:W13),"n/a ") -> n/a | X26: =IFERROR(MEDIAN(X17:X22,X8:X13),"n/a ") -> n/a | Y26: =IFERROR(MEDIAN(Y17:Y22,Y8:Y13),"n/a ") -> n/a | Z26: =IFERROR(MEDIAN(Z17:Z22,Z8:Z13),"n/a ") -> n/a
E29: 25th Percentile | S29: =IFERROR(_xlfn.PERCENTILE.INC((S8:S13,S17:S22),0.25),"n/a ") -> n/a | T29: =IFERROR(_xlfn.PERCENTILE.INC((T8:T13,T17:T22),0.25),"n/a ") -> n/a | U29: =IFERROR(_xlfn.PERCENTILE.INC((U8:U13,U17:U22),0.25),"n/a ") -> n/a | V29: =IFERROR(_xlfn.PERCENTILE.INC((V8:V13,V17:V22),0.25),"n/a ") -> n/a | W29: =IFERROR(_xlfn.PERCENTILE.INC((W8:W13,W17:W22),0.25),"n/a ") -> n/a | X29: =IFERROR(_xlfn.PERCENTILE.INC((X8:X13,X17:X22),0.25),"n/a ") -> n/a | Y29: =IFERROR(_xlfn.PERCENTILE.INC((Y8:Y13,Y17:Y22),0.25),"n/a ") -> n/a | Z29: =IFERROR(_xlfn.PERCENTILE.INC((Z8:Z13,Z17:Z22),0.25),"n/a ") -> n/a
E30: 75th Percentile | S30: =IFERROR(_xlfn.PERCENTILE.INC((S8:S13,S17:S22),0.75),"n/a ") -> n/a | T30: =IFERROR(_xlfn.PERCENTILE.INC((T8:T13,T17:T22),0.75),"n/a ") -> n/a | U30: =IFERROR(_xlfn.PERCENTILE.INC((U8:U13,U17:U22),0.75),"n/a ") -> n/a | V30: =IFERROR(_xlfn.PERCENTILE.INC((V8:V13,V17:V22),0.75),"n/a ") -> n/a | W30: =IFERROR(_xlfn.PERCENTILE.INC((W8:W13,W17:W22),0.75),"n/a ") -> n/a | X30: =IFERROR(_xlfn.PERCENTILE.INC((X8:X13,X17:X22),0.75),"n/a ") -> n/a | Y30: =IFERROR(_xlfn.PERCENTILE.INC((Y8:Y13,Y17:Y22),0.75),"n/a ") -> n/a | Z30: =IFERROR(_xlfn.PERCENTILE.INC((Z8:Z13,Z17:Z22),0.75),"n/a ") -> n/a
